Workbook
Name aaaa: #REF!
Name aaaa: #REF!
Name aaaaa: #REF!
Name aaaaa: #REF!
Name anomalies: #REF!
Name anomalies: #REF!
Name CAP_01__02__03__04__Clientèle_de_détail___Pas_de_données_complémentaires_obligatoires_associées_à_ces_CAP__Les_expositions_sur_la_Clientèle_de_détail_sont_pondérées_à_75_.: #REF!
Name CAP_01__02__03__04__Clientèle_de_détail___Pas_de_données_complémentaires_obligatoires_associées_à_ces_CAP__Les_expositions_sur_la_Clientèle_de_détail_sont_pondérées_à_75_.: #REF!
Name CAP_de_l_exposition: #REF!
Name CAP_de_l_exposition: #REF!
Name CAPtest: '[1]A1 Degraded Data Entry'!#REF!
Name CAPtest: '[1]A1 Degraded Data Entry'!#REF!
Name Groupe_caractéristiques: #REF!
Name Groupe_caractéristiques: #REF!
Name Méthodo_CAP: #REF!
Name Méthodo_CAP: #REF!
Name Méthodo_Conditions_réglementaires: #REF!
Name Méthodo_Conditions_réglementaires: #REF!
Name Méthodo_Crédit_bail: #REF!
Name Méthodo_Crédit_bail: #REF!
Name Méthodo_DeterminationCAP: #REF!
Name Méthodo_DeterminationCAP: #REF!
Name Méthodo_douteux_impayé: #REF!
Name Méthodo_douteux_impayé: #REF!
Name Méthodo_engagement: #REF!
Name Méthodo_engagement: #REF!
Name Méthodo_impayé: #REF!
Name Méthodo_impayé: #REF!
Name Méthodo_indicateur: #REF!
Name Méthodo_indicateur: #REF!
Name Méthodo_indicateur_couverture: [2]Méthodologie!#REF!
Name Méthodo_indicateur_couverture: #REF!
Name Méthodo_Montants: #REF!
Name Méthodo_Montants: #REF!
Name Méthodo_NATO: #REF!
Name Méthodo_NATO: #REF!
Name Méthodo_PNU: #REF!
Name Méthodo_PNU: #REF!
Name Méthodo_Pond_pref: #REF!
Name Méthodo_Pond_pref: #REF!
Name méthodo_provisions: #REF!
Name Méthodo_provisions: #REF!
Name Méthodo_sûretés: #REF!
Name Méthodo_sûretés: #REF!
Name Méthodo_Tiers_Agrégat: #REF!
Name Méthodo_Tiers_Agrégat: #REF!
Name Méthodo_usage_bien_immo: #REF!
Name Méthodo_usage_bien_immo: #REF!
Name Objets: '[3]Liste des objets'!$A:$A
Name Règles_corr: #REF!
Name Règles_corr: #REF!
Name test: #REF!
Name test: #REF!
Name Tiers_Agrégat: #REF!
Name Tiers_Agrégat: #REF!
Name Toto: #REF!
Name Toto: #REF!

Sheet Modifications
A1: Modifications
H2: Nombre de contrôles par type et sévérité
A3: Emetteur / Issuer | C3: Crédit Agricole SA : Programme Convergence Finances Risques (Crédit Agricole SA/FIG/DOP/CFR) | H3: 7 | I3: 6 | J3: 5 | K3: Mix | L3: total
A4: Date de diffusion / Publication date | C4: Lorsque cette date est renseignée, cela signifie que la notice est publiée dans https://service.ca-mocca.com/maia-collab/CFR/SitePages/Notices.aspx qui reprend l'ensemble des versions publiées. | G4: Présence | H4: =COUNTIF('PACT Corp'!$AJ$4:$AJ$1504,Modifications!H$3) -> 328 | I4: =COUNTIF('PACT Corp'!$AJ$4:$AJ$1504,Modifications!I$3) -> 460 | J4: =COUNTIF('PACT Corp'!$AJ$4:$AJ$1504,Modifications!J$3) -> 59 | K4: =L4-SUM(H4:J4) -> 5 | L4: =COUNTA('PACT Corp'!$AJ$4:$AJ$1504) -> 852
C5: You can find all the published versions on https://service.ca-mocca.com/maia-collab/CFR/SitePages/Notices_EN.aspx | G5: Référentiel | H5: =COUNTIF('PACT Corp'!$AN$4:$AN$1504,Modifications!H$3) -> 615 | I5: =COUNTIF('PACT Corp'!$AN$4:$AN$1504,Modifications!I$3) -> 0 | J5: =COUNTIF('PACT Corp'!$AN$4:$AN$1504,Modifications!J$3) -> 0 | K5: =L5-SUM(H5:J5) -> 0 | L5: =COUNTA('PACT Corp'!$AN$4:$AN$1504) -> 615
A6: Descriptif de la Mise à jour / Modifications | C6: Descriptif de la modification / Modification description | G6: Valeur | H6: =COUNTIF('PACT Corp'!$AR$4:$AR$1504,Modifications!H$3) -> 205 | I6: =COUNTIF('PACT Corp'!$AR$4:$AR$1504,Modifications!I$3) -> 18 | J6: =COUNTIF('PACT Corp'!$AR$4:$AR$1504,Modifications!J$3) -> 0 | K6: =L6-SUM(H6:J6) -> 4 | L6: =COUNTA('PACT Corp'!$AR$4:$AR$1504) -> 227
A7: Couleur / Color | C7: Permet d'identifier les zones ajoutées/modifiées | G7: Intra-objet | H7: =COUNTIF('PACT Corp'!$AV$4:$AV$1504,Modifications!H$3) -> 28 | I7: =COUNTIF('PACT Corp'!$AV$4:$AV$1504,Modifications!I$3) -> 58 | J7: =COUNTIF('PACT Corp'!$AV$4:$AV$1504,Modifications!J$3) -> 0 | K7: =L7-SUM(H7:J7) -> 0 | L7: =COUNTA('PACT Corp'!$AV$4:$AV$1504) -> 86
C8: The color code enables identification of the different kinds of evolutions | G8: Inter-objet | H8: =COUNTIF('PACT Corp'!$AZ$4:$AZ$1504,Modifications!H$3) -> 34 | I8: =COUNTIF('PACT Corp'!$AZ$4:$AZ$1504,Modifications!I$3) -> 18 | J8: =COUNTIF('PACT Corp'!$AZ$4:$AZ$1504,Modifications!J$3) -> 0 | K8: =L8-SUM(H8:J8) -> 23 | L8: =COUNTA('PACT Corp'!$AZ$4:$AZ$1504) -> 75
G9: Cohérence | H9: =COUNTIF('PACT Corp'!$BD$4:$BD$1504,Modifications!H$3) -> 0 | I9: =COUNTIF('PACT Corp'!$BD$4:$BD$1504,Modifications!I$3) -> 20 | J9: =COUNTIF('PACT Corp'!$BD$4:$BD$1504,Modifications!J$3) -> 0 | K9: =L9-SUM(H9:J9) -> 0 | L9: =COUNTA('PACT Corp'!$BD$4:$BD$1504) -> 20
A12: Suivi des versions / Version tracking
A13: Date de diffusion / Publication date | B13: Publication mocca n° | C13: Descriptif de la mise à jour / Modifications | D13: Couleur / Color
A14: 46014 | B14: 45.00 | C14: Ajout de nouvelles données / New data addition
A15: 46014 | B15: 45.00 | C15: Ajouter des séparateurs ';' entre chaque donnée / Semicolon ';' to be added between each data
A16: 46014 | B16: 45.00 | C16: Modifications / Modifications Changement de longueur en passant de 5 à 50 caractères sur P1 21.65 / Length change from 5 to 50 characters on P1 21.65
A17: 46149 | B17: 45.01 | C17: Modifications mineures / Minor modifications Ajustement d'un libéllé de contrôle, ajout des codes contrôles, ajustement de la liste des usages déclarés, ajustement du périmètre de collecte / Control name update, control codes addition, declared usages update, collection scope update
A18: 46149 | B18: 45.01 | C18: Modifications majeures / Major modifications Ajout d'une donnée, modification de contrôle, suppression de contrôle, désactivation de données, / Data addition, Control update or deletion, data deactivation
A19: 46220 | B19: 45.02 | C19: Modifications majeures / Major modifications Modification de définitions, règles de gestion et contrôles pour les données P1 621 et P1 622/ Modification of definitions, management rules and controls for P1 621 and P1 622 data items
A20: 46220 | B20: 45.02 | C20: Modifications mineures / Minor modifications Retrait de l'usage CALCULS PRUDENTIELS des donnée P1 30.x, Ajustement du périmètre de collecte / Removal of CALCULS PRUDENTIELS usage the from the P1 30.X data items, correction of collection scope
A22: Liens utiles / Useful Links
A23: Langages Communs / Common Languages | C23: https://service.ca-mocca.com/maia-collab/CFR/SitePages/Langages_Communs.aspx https://service.ca-mocca.com/maia-collab/CFR/SitePages/Common_Languages.aspx
A24: Manuel des Echanges Entités-Zone de Partage et Notices / Exchange Manual ZP-entities and Notices | C24: https://service.ca-mocca.com/maia-collab/CFR/SitePages/Notices.aspx https://service.ca-mocca.com/maia-collab/CFR/SitePages/Notices_EN.aspx
A25: Guide Méthodologique - Alimentation PACT (ex CRR) / Methodological Guide - PACT (ex CRR) Feeding | C25: https://service.ca-mocca.com/maia-collab/CFR/SitePages/Notices.aspx https://service.ca-mocca.com/maia-collab/CFR/SitePages/Notices_EN.aspx

Sheet PACT Corp
AH1: CTRL PRESENCE / PRESENCE CTRL | AL1: CTRL REFERENTIEL / REFERENTIEL CTRL | AP1: CTRL VALEUR / VALUE CTRL | AT1: CTRL INTRA-OBJET / INTRA-OBJECT CTRL | AX1: CTRL INTER-OBJET / INTER-OBJECT CTRL | BB1: CTRL COHERENCE (cf. onglet dédié) / CONSISTENCY CTRL (cf. dedicated tab)
A2: OBJET DE COLLECTE / COLLECTION OBJECT | B2: N° D'ORDRE TECHNIQUE DE LA DONNEE / TECHNICAL ORDER NUMBER OF THE DATA IN THE FILE | C2: BLOC DE DONNEES | D2: DATA BLOCK | E2: REFERENCE DE COLLECTE / COLLECTION REFERENCE | F2: NOM DE LA DONNEE | G2: DATA NAME | H2: DEFINITION | I2: DEFINITION | J2: TERME METIER | K2: BUSINESS TERM | L2: CODE TECHNIQUE / TECHNICAL CODE | M2: EXIGENCE D'ALIMENTATION | N2: SUPPLY REQUIREMENT | O2: REFERENCE DE LANGAGE COMMUN / COMMON LANGUAGE REFERENCE | P2: TABLE START / START Table | Q2: REGLE DE GESTION | R2: MANAGEMENT RULE | S2: FORMAT | T2: REGLE DE FORMATAGE | U2: FORMATTING RULE | V2: LONGUEUR / LENGTH | W2: POSITION / POSITION | X2: VERSION DE CREATION / FIRST APPEARANCE VERSION | Y2: VERSION DE DERNIERE APPARITION / LAST APPEARANCE VERSION | Z2: VERSION DE MODIFICATION / MODIFICATION VERSION | AA2: USAGE(S) DECLARE(S) / DECLARED USAGE | AB2: DONNEE CRITIQUE POUR / CRITICAL DATA FOR | AC2: DONNEE A CARACTERE PERSONNEL / PERSONNAL DATA | AD2: PERIMETRE DE COLLECTE / COLLECTION SCOPE | AE2: APPLICATION REMETTANTE / REMITTING APPLICATION | AF2: REFERENCE DE LA DONNEE DANS L'APPLICATION REMETTANTE / DATA REFERENCE IN REMITTING APPLICATION | AH2: CTRL PRESENCE | AI2: PRESENCE CTRL | AJ2: PRESENCE SCORE CONSEQUENCE | AK2: PRESENCE Code CTRL ZP | AL2: CTRL REFERENTIEL | AM2: REFERENTIEL CTRL | AN2: REFERENTIEL SCORE CONSEQUENCE | AO2: REFERENTIEL Code CTRL ZP | AP2: CTRL VALEUR | AQ2: VALUE CTRL | AR2: VALEUR SCORE CONSEQUENCE | AS2: VALEUR Code CTRL ZP | AT2: CTRL INTRA-OBJET | AU2: INTRA-OBJECT CTRL | AV2: COHERENCE SCORE CONSEQUENCE | AW2: COHERENCE Code CTRL ZP | AX2: CTRL INTER-OBJECT | AY2: INTER-OBJET CTRL | AZ2: Score Consequence | BA2: Code CTRL ZP | BB2: CTRL COHERENCE | BC2: CONSISTENCY CTRL | BD2: Score Consequence | BE2: Code CTRL ZP
A3: Famille de flux et Objet de Collecte véhiculant la donnée / Flow family and data collection object | B3: Numéro séquentiel correspondant au numéro d'ordre de la donnée dans le fichier physique. Invariant dans le temps (toute nouvelle donnée sera ajoutée en fin de fichier) / Sequential number corresponding to the order number of the data in the physical file. Invariant in time (any new data will be added at the end of the file) | C3: Classification de la donnée dans un des blocs structurant l'Objet de Collecte | D3: Classification of the data in one of the blocks structuring the Collection Object. | E3: Référence de la donnée collectée via l'Objet de Collecte. Attribut communément appelé 'Etiquette' / Reference of the data collected via the Collection Object. Attribute commonly referred to as 'Label' | F3: Libellé Métier de la donnée | G3: Data business name | H3: Définition métier de la donnée | I3: Business data definition | J3: Terme métier parent du glossaire métier auquel se rapporte la donnée | K3: Term parent business of the business glossary to which the data relates | L3: Nom technique de la donnée / Technical name of the data | M3: Exigence de présence de la donnée sur le périmètre de Collecte défini. L'information prend la valeur : - Obligatoire si la donnée est exigée - Obligatoire Si si la donnée est exigée dans des conditions définies dans la Règle de Gestion - Facultatif si la donnée n'est pas exigée - NA si la donnée est devenue obsolète et n'est plus collectée sur le domaine de Collecte - A renseigner si l'information n'est pas encore disponible | N3: Requirement to have the data on the defined Collection perimeter. Information is valued: - Mandatory if data is required - Mandatory If the data is required under conditions defined in the Management Rule - Optional if data is not required - NA if the data has become obsolete and is no longer collected on the Collection domain - To be filled if the information is not yet available | O3: Référence du Langage Commun structurant le format autorisé et la nomenclature autorisée. L'information prend la valeur : - LC.NNNN si la donnée s'adosse au LC.NNNN - LC à référencer si la donnée s'adosse à un LC en cours de référencement - NA si la donnée ne s'adosse à aucun LC /A reference to the Common Language structuring the allowed format and the allowed nomenclature. Information is valued: - LC.NNNN if the data is based on LC.NNNN - LC to be referenced if the data is against an LC being referenced - NA if the data does not support any LC. | P3: Table(s)/Rubrique(s) Start porteuse(s) de la nomenclature du Langage Commun lorsque celui ci est référencé. Il peut être multiple. L'information prend la valeur : - TA XXXXX si la donnée s'adosse à la table TA XXXXX - RB XXXXX si la donnée s'adosse à la rubrique RB XXXXX - NA si la donnée ne s'adosse à aucun référentiel Start /Table(s)/Topic(s) Start carrying the nomenclature of the Common Language when it is referenced. It can be multiple. Information is valued: - TA XXXXX if the data is based on the table TA XXXXX - RB XXXXX if the data is based on RB XXXXX - NA if the data does not support any Start referential | Q3: Précisions sur les exigences posées sur la donnée (de type seuils, formules, calculs, règles d'alimentation hors LC...) ou commentaires. En particulier, les exigences posées sur la donnée peuvent porter sur : - sa présence (dans le contrôle) (ne pas reprendre les conditions du contrôle de présence si assez explicite) Nota Bene sur le domaine de valeurs : -- si la donnée peut s'inscrire dans toute la nomenclature d'un Langage Commun, le LC est directement renseigné dans le champ dédié "Référence LC" -- si la donnée s'inscrit dans un domaine de valeurs plus restreint lié au périmètre fonctionnel de l'objet collecté, ce domaine de valeurs strictement autorisé est indiqué ici (contrôle de valeur). L'information prend la valeur NA sans exigences particulières | R3: Details on the requirements of the data (of the threshold type, formulas, calculations, rules of supply excluding LC...) or comments. In particular, the data requirements may relate to: - its presence (in the control) (do not take over the presence control conditions so explicitly) Note Bene on the value domain: — if the data can be inscribed in the entire nomenclature of a Common Language, the LC is directly filled in the dedicated field "LC Reference" — if the data falls within a narrower value domain related to the functional scope of the collected object, this strictly authorized value domain is indicated here (value control). Information is set to NA without any special requirements | S3: Format de la donnée. L'information prend la valeur : - DATE - ALPHA - NUM - A renseigner si l'information n'est pas encore disponible Data format. Information is valued: - DATE - ALPHA - NUM - To be filled if the information is not yet available | T3: Structure de présentation des données de type date, montant et taux. L'information prend la valeur : - "NA" en l'absence de règle de formatage. - "A renseigner" si l'information n'est pas disponible | U3: Date, amount and rate data presentation structure. Information is valued: - "NA" in the absence of a formatting rule. - "To be filled" if the information is not available | V3: Longueur de la donnée La valeur 8 est attendue sur les formats DATE/ Data length Value 8 is expected on DATE formats | W3: Numéro correspondant à la position de la donnée dans la chaine de caractères du fichier physique. Nécessaire que pour les fichiers plats sans séparateurs (PACT par exemple). Elle prend la valeur NA dans les autres cas. / The number that corresponds to the position of the data item in the character string of the physical file. Required only for flat files without separators. It is set to NA in other cases. | X3: Version de la notice dans laquelle la donnée est apparue. L'information prend la valeur: - De la donnée Verbloc figurant dans l'en-tête de la notice - A renseigner si l'information n'est pas encore disponible./ The version of the notice in which the data appeared. Information takes value: - Verbloc data in the header of the notice - To be filled if the information is not yet available. | Y3: Version de la notice dans laquelle la donnée apparaît pour la dernière fois. L'information prend la valeur: - De la donnée Verbloc figurant dans l'en-tête de la notice quand la donnée est devenue obsolète - NA quand la donnée est toujours collectée/ The version of the notice in which the data last appears. Information takes value: - Verbloc data in the header of the record when the data has become obsolete - NA when data is still collected | Z3: Dernière version de publication de la notice présentant la MAJ de la donnée / Latest publication version of the notice where the data was updated | AA3: Liste des usages industriels déclarant exploiter la donnée. L'information prend la valeur : - Usage1, Usage2, Usage3, ..., UsageN si plusieurs usages sont déclarés - NA en l'absence d'usage déclaré - A renseigner si l'information n'est pas encore disponible /List of industrial uses declaring to exploit the data. Information is valued: - Use1, Use2, Use3, ..., UseN if more than one use is declared - NA in the absence of declared use - To be filled if the information is not yet available | AB3: Liste des usages signalant que la donnée est indispensable pour leur fonctionnement. Le processus de production de reporting de ce(s) usage(s) est compromis par l'absence de cette donnée ou par sa non qualité. L'information prend la valeur : - Usage1, Usage2, Usage3, ..., UsageN si plusieurs usages ont déclaré la donnée critique - NA en l'absence de criticité de la donnée quel que soit l'usage - A renseigner si l'information n'est pas encore disponible/ List of uses indicating that the data is essential for their operation. The reporting production process of this use(s) is compromised by the absence of this data or by its non-quality. Information is valued: - Usage1, Usage2, Usage3, ..., UsageN if several uses have declared critical data - NA in the absence of criticality of the data whatever the use - To be filled if the information is not yet available | AC3: Indicateur signalant que la donnée est à caractère personnel. Une donnée à caractère personnel au sens RGPD est une information se rapportant à une personne physique identifiée ou identifiable. Elle peut permettre d'identifier une personne physique directement (exemple : nom et prénom) ou indirectement (exemple : par un numéro de téléphone ou de plaque d'immatriculation, un identifiant tel que le numéro de sécurité sociale, une adresse postale ou courriel). L'information prend la valeur : - Y si la donnée est une donnée à caractère personnel - N dans le cas contraire - A renseigner si l'information n'est pas encore disponible/ Indicator indicating that the data is personal. Personal data in the sense of GDPR is information relating to an identified or identifiable natural person. It can identify a natural person directly (example: first and last names) or indirectly (example: by a telephone or license plate number, an identifier such as a social security number, a postal or email address). Information is valued: - Y if the data is personal data - N otherwise - To be filled if the information is not yet available | AD3: Information concernant les données du P1, M1 et flux passifs seulement. Le périmètre de Collecte précise le domaine fonctionnel auquel se rapporte la Collecte de la donnée. La nature du domaine fonctionnel varie suivant les objets de collecte. L'information peut être de nature: - Type de risque - Nature juridique de la sûreté - NA dans les autres cas/ Information on P1, M1 and liability flow data only. The Collection scope specifies the functional area to which the Data Collection relates. The nature of the functional area varies according to the collection objects. The information may be of a nature: - Risk type - Legal nature of security interest - NA in other cases | AE3: Application en central qui met la donnée à disposition / Central application that makes data available | AF3: Référence de la donnée en provenance de l'application remettante / Reference of data from remitting application
A4: CRRC | B4: 1 | C4: 00 - En-tête du flux | D4: 00 - File header | E4: CRRC H.ENREG | F4: Type d'enregistrement | G4: Type of record | H4: Type d'enregistrement correspondant au bloc En-tête | I4: Type of record corresponding to Header block | J4: ND | K4: ND | L4: ENREG | M4: Obligatoire | N4: Mandatory | O4: NA | P4: NA | Q4: A alimenter à "00" | R4: To be filled with "00" | S4: ALPHA | T4: NA | U4: NA | V4: 2 | W4: NA | X4: 43 | Y4: NA | Z4: NA | AA4: USAGE ZP | AB4: NA | AC4: NA | AD4: NA | AE4: NA | AF4: NA
A5: CRRC | B5: 2 | C5: 00 - En-tête du flux | D5: 00 - File header | E5: CRRC H.IDFICHIER | F5: Identifiant du fichier | G5: File's identifier | H5: Identifiant caractérisant le contenu véhiculé par le fichier et servant à référencer chaque type de fichier échangé dans le Référentiel des Echanges du Groupe afin de favoriser la réutilisation | I5: Identifier characterising the content reported by the file and serving to reference each type of file exchanged in the Group's Exchange Referential to facilitate re-use | J5: ND | K5: ND | L5: IDFICHIER | M5: Obligatoire | N5: Mandatory | O5: NA | P5: NA | Q5: A alimenter à "00000533" | R5: To be filled with "00000533" | S5: ALPHA | T5: NA | U5: NA | V5: 8 | W5: NA | X5: 43 | Y5: NA | Z5: NA | AA5: USAGE ZP | AB5: NA | AC5: NA | AD5: NA | AE5: NA | AF5: NA
A6: CRRC | B6: 3 | C6: 00 - En-tête du flux | D6: 00 - File header | E6: CRRC H.VERFICHIER | F6: Version technique du fichier | G6: File's technical version | H6: Qualifie les modalités techniques de constitution du fichier (positionnel, XML, …) | I6: Characterises the technical modalities for producing the file (positional, XML, etc.) | J6: ND | K6: ND | L6: VERFICHIER | M6: Obligatoire | N6: Mandatory | O6: NA | P6: NA | Q6: A alimenter à "001" | R6: To be filled with "001" | S6: ALPHA | T6: NA | U6: NA | V6: 3 | W6: NA | X6: 43 | Y6: NA | Z6: NA | AA6: USAGE ZP | AB6: NA | AC6: NA | AD6: NA | AE6: NA | AF6: NA
A7: CRRC | B7: 4 | C7: 00 - En-tête du flux | D7: 00 - File header | E7: CRRC H.TIMESTAMP | F7: Horodatage | G7: Timestamp | H7: Date et heure de production du fichier (norme ISO 8601 : séparateur normalisé « T » entre la date et l'heure) | I7: Date and time of the file's production (ISO 8601 standard: normalised separator “T” between the date and time) | J7: ND | K7: ND | L7: TIMESTAMP | M7: Obligatoire | N7: Mandatory | O7: NA | P7: NA | Q7: NA | R7: NA | S7: ALPHA | T7: AAAAMMJJTHHMMSS | U7: YYYYMMDDTHHMMSS | V7: 15 | W7: NA | X7: 43 | Y7: NA | Z7: NA | AA7: USAGE ZP | AB7: NA | AC7: NA | AD7: NA | AE7: NA | AF7: NA
A8: CRRC | B8: 5 | C8: 00 - En-tête du flux | D8: 00 - File header | E8: CRRC H.UOE | F8: Entité émettrice | G8: Issuing entity | H8: Identifiant national de l'entité produisant le fichier (pour son propre compte ou en cas de sous-traitance pour le compte de l'entité déclarante) | I8: National identifier of the entity producing the file (for its own account or, in the event of subcontracting, on behalf of the issuing entity) | J8: ND | K8: ND | L8: UOE | M8: Obligatoire | N8: Mandatory | O8: LC.0003 | P8: RB NM281 | Q8: NA | R8: NA | S8: ALPHA | T8: NA | U8: NA | V8: 5 | W8: NA | X8: 43 | Y8: NA | Z8: 45.00 | AA8: USAGE ZP | AB8: NA | AC8: NA | AD8: NA | AE8: NA | AF8: NA
A9: CRRC | B9: 6 | C9: 00 - En-tête du flux | D9: 00 - File header | E9: CRRC H.UOD | F9: Entité déclarante | G9: Reporting entity | H9: Identifiant national de l'entité à laquelle se rapporte le contenu du fichier (entité porteuse du risque) | I9: National identifier of the entity to which the file's content relates (entity carrying the risk) | J9: ND | K9: ND | L9: UOD | M9: Obligatoire | N9: Mandatory | O9: LC.0003 | P9: RB NM281 | Q9: NA | R9: NA | S9: ALPHA | T9: NA | U9: NA | V9: 5 | W9: NA | X9: 43 | Y9: NA | Z9: NA | AA9: USAGE ZP | AB9: NA | AC9: NA | AD9: NA | AE9: NA | AF9: NA
A10: CRRC | B10: 7 | C10: 00 - En-tête du flux | D10: 00 - File header | E10: CRRC H.NMAPPU | F10: Application émettrice | G10: Issuing application | H10: Code ou nom de l'application ou du job utilisés pour produire le fichier dans le SI de l'entité | I10: Code or name of the application or job used to produce the file in the entity's IT system | J10: ND | K10: ND | L10: NMAPPU | M10: Facultatif | N10: Optional | O10: NA | P10: NA | Q10: NA | R10: NA | S10: ALPHA | T10: NA | U10: NA | V10: 32 | W10: NA | X10: 43 | Y10: NA | Z10: NA | AA10: USAGE ZP | AB10: NA | AC10: NA | AD10: NA | AE10: NA | AF10: NA
A11: CRRC | B11: 8 | C11: 00 - En-tête du flux | D11: 00 - File header | E11: CRRC H.CDBLOC | F11: Code du flux | G11: Flow code | H11: Code du flux correspondant aux objets métier véhiculés par le fichier | I11: Flow code corresponding to the business objects reported by the file | J11: ND | K11: ND | L11: CDBLOC | M11: Obligatoire | N11: Mandatory | O11: NA | P11: NA | Q11: A alimenter à "CRRC" | R11: To filled filled with "CRRC" | S11: ALPHA | T11: NA | U11: NA | V11: 4 | W11: NA | X11: 43 | Y11: NA | Z11: NA | AA11: USAGE ZP | AB11: NA | AC11: NA | AD11: NA | AE11: NA | AF11: NA
A12: CRRC | B12: 9 | C12: 00 - En-tête du flux | D12: 00 - File header | E12: CRRC H.VERBLOC | F12: Version du flux | G12: Flow version | H12: Version du flux correspondant aux objets métier véhiculés par le fichier | I12: Version of flow corresponding to the business objects reported by the file | J12: ND | K12: ND | L12: VERBLOC | M12: Obligatoire | N12: Mandatory | O12: NA | P12: NA | Q12: A alimenter à "45" | R12: To filled filled with "45" | S12: ALPHA | T12: NA | U12: NA | V12: 2 | W12: NA | X12: 43 | Y12: NA | Z12: 45.00 | AA12: USAGE ZP | AB12: NA | AC12: NA | AD12: NA | AE12: NA | AF12: NA
A13: CRRC | B13: 10 | C13: 00 - En-tête du flux | D13: 00 - File header | E13: CRRC H.NUMENV | F13: Numéro d'envoi du fichier | G13: File's dispatch number | H13: Permet de gérer les réemissions | I13: Serves to manage re-issues | J13: ND | K13: ND | L13: NUMENV | M13: Obligatoire | N13: Mandatory | O13: NA | P13: NA | Q13: A alimenter à "00001" et à incrémenter de +1 à chaque réémission | R13: To be filled with "00001"and incrementing by +1 at each reissue | S13: ALPHA | T13: NA | U13: NA | V13: 5 | W13: NA | X13: 43 | Y13: NA | Z13: NA | AA13: USAGE ZP | AB13: NA | AC13: NA | AD13: NA | AE13: NA | AF13: NA
A14: CRRC | B14: 11 | C14: 00 - En-tête du flux | D14: 00 - File header | E14: CRRC H.CRARRETE | F14: Type d'arrêté | G14: Reporting type | H14: Périodicité de l'arrêté | I14: Reporting frequency | J14: ND | K14: ND | L14: CRARRETE | M14: Obligatoire | N14: Mandatory | O14: LC.0056 | P14: TA KVFREQU | Q14: NA | R14: NA | S14: ALPHA | T14: NA | U14: NA | V14: 1 | W14: NA | X14: 43 | Y14: NA | Z14: NA | AA14: USAGE ZP | AB14: NA | AC14: NA | AD14: NA | AE14: NA | AF14: NA
A15: CRRC | B15: 12 | C15: 00 - En-tête du flux | D15: 00 - File header | E15: CRRC H.DTARRETE | F15: Date d'arrêté | G15: Closing date | H15: Date d'arrêté correspondant au contenu du fichier (norme ISO 8601) | I15: Closing date corresponding to the file's content (ISO 8601 standard) | J15: ND | K15: ND | L15: DTARRETE | M15: Obligatoire | N15: Mandatory | O15: NA | P15: NA | Q15: NA | R15: NA | S15: DATE | T15: AAAAMMJJ | U15: YYYYMMDD | V15: 8 | W15: NA | X15: 43 | Y15: NA | Z15: NA | AA15: USAGE ZP | AB15: NA | AC15: NA | AD15: NA | AE15: NA | AF15: NA
... A17: CRRC | B17: 14 | C17: 00 - En-tête du flux | D17: 00 - File header | E17: CRRC H.NMAPPFIN | F17: Application émettrice Finance | G17: Issuing Finance application code | H17: Code de l'application émettrice spécifique à PALMA | I17: Issuing application code specific to PALMA | J17: ND | K17: ND | L17: NMAPPFIN | M17: Facultatif | N17: Optional | O17: NA | P17: NA | Q17: NA | R17: NA | S17: ALPHA | T17: NA | U17: NA | V17: 5 | W17: NA | X17: 43 | Y17: NA | Z17: NA | AA17: USAGE ZP | AB17: NA | AC17: NA | AD17: NA | AE17: NA | AF17: NA
A18: CRRC | B18: 15 | C18: 00 - En-tête du flux | D18: 00 - File header | E18: CRRC H.FILLER | F18: Filler | G18: Filler | H18: Filler pour évolutions futures | I18: Filler for future evolution | J18: ND | K18: ND | L18: FILLER | M18: Facultatif | N18: Optional | O18: NA | P18: NA | Q18: NA | R18: NA | S18: ALPHA | T18: NA | U18: NA | V18: =8000-(SUM(V4:V17)+COUNT(V4:V17)) -> 7886 | W18: NA | X18: 43 | Y18: NA | Z18: NA | AA18: USAGE ZP | AB18: NA | AC18: NA | AD18: NA | AE18: NA | AF18: NA
A19: C1 | B19: 1 | C19: 02 - Caractéristiques d'identification fonctionnelles | D19: 02 - Functional identification characteristics | E19: 0.1 (C1) | F19: Date d'arrêté | G19: Closing date | H19: Correspond à la date d'arrêté des données transmises (dernier jour calendaire du mois) | I19: Represents the cut-off date of the data transmitted (final calendar day of the month) | J19: ND | K19: ND | L19: NA | M19: Obligatoire | N19: Mandatory | O19: NA | P19: NA | Q19: Il doit y avoir unicité de la date d'arrêté au sein du flux | R19: The cut-off date must be the same across the flow | S19: DATE | T19: AAAAMMJJ | U19: YYYYMMDD | V19: 8 | W19: NA | X19: 40 | Y19: NA | Z19: NA | AA19: TIGRE | AB19: ND | AC19: N | AD19: NA | AE19: NA | AF19: NA | AH19: La donnée est obligatoire | AI19: The data is mandatory | AK19: EN0011 | AP19: Si renseignée, pour un même BAAPID, la date d'arrêté doit être supérieure ou égale à la date d'arrêté du dernier lot intégré. (= on n'accepte pas de flux sur un arrêté précédent) Dans la table INTEGRATED_PARENT, pour le même SCOPE_SRC_CD (= BAAPID), la date d'arrêté doit être supérieure ou égale à la dernière date d'arrêté avec le statut « QUALITY_OK ». --- Si renseignée, la date doit être égale au dernier jour calendaire du mois de l'arrêté en cours (ex : 20190131, 20190228, 20190331, etc.) | AQ19: If filled in, for the same BAAPID, the cut-off date must be greater than or equal to the cut-off date of the last integrated batch. (= no flow on previous order accepted) In the INTEGRATED_PARENT table, for the same SCOPE_SRC_CD (= BAAPID), the stop date must be greater than or equal to the last stop date with the status 'QUALITY_OK'. — If filled in, the date must be equal to the last calendar day of the month of the current order (e.g. 20190131, 20190228, 20190331, etc.) | AS19: EN0017 EN0019 | AT19: Si renseignée, pour le même BAAPID, si le dernier lot a un statut "rejeté" ou "à recycler" ou "abandonner", et qu'il n'y a pas d'autres lots en attente, la date d'arrêté doit être inférieure ou égale à la date d'arrêté du dernier lot. Dans la table INTEGRATED_PARENT, pour le même SCOPE_SRC_CD (= BAAPID), la date doit être inférieure ou égale à la dernière date (= STTM_DT) avec le statut « QUALITY_KO », « REJECTED » ou « DECERTIFIED ». | AU19: If filled in for the same BAAPID, if the last batch has a "rejected" or "to recycle" or "abort" status, and there are no other batches pending, the stop date must be less than or equal to the last batch stop date. In the INTEGRATED_PARENT table, for the same SCOPE_SRC_CD (= BAAPID), the date must be less than or equal to the last date (= STTM_DT) with the status “QUALITY_KO”, “REJECTED” or “DECERTIFIED”. | AW19: EN001B
A20: C1 | B20: 2 | C20: 02 - Caractéristiques d'identification fonctionnelles | D20: 02 - Functional identification characteristics | E20: 0.2 (C1) | F20: Entité Porteuse de Risques | G20: Risk taker entity | H20: Correspond au code consolidation comptable de l'Entité porteuse de risque dans les comptes de Crédit Agricole S.A. | I20: Represents the accounting consolidation code of the Entity in the financial statements of Crédit Agricole S.A. | J20: ND | K20: ND | L20: NA | M20: Obligatoire | N20: Mandatory | O20: LC.0003 | P20: TA FI59 | Q20: NA | R20: NA | S20: ALPHA | T20: NA | U20: NA | V20: 5 | W20: NA | X20: 40 | Y20: NA | Z20: NA | AA20: TIGRE | AB20: ND | AC20: N | AD20: NA | AE20: NA | AF20: NA | AH20: La donnée est obligatoire | AI20: The data is mandatory | AK20: EN0021 | AL20: Si renseignée, 1/ Si dans la table START "TA 0990 KVAPPBK", il existe un KVBAPPID pour le KVAPPBK valant la concaténation "Entité porteuse de risque" [EN 0.2] et "Application source" [EN 0.3], alors, les 9 premiers caractères de ce KVBAPPID doivent être présents dans la colonne TMNOMOBE de la table TMTAKOBE. 2/ Si pas présent dans TMTAKOBE, l'entité porteuse de risque [EN 0.2] doit exister dans la colonne TMCCONSU de la table TMTAKOBU. | AM20: If filled, 1/ If in the START table "TA 0990 KVAPPBK", there is a KVBAPPID for the KVAPPBK with the concatenation "risk-carrying Entity" [EN 0.2] and "Source application" [EN 0.3], then the first 9 characters of this KVBAPPID must be present in the TMNOMOBE column of the TMTAKOBE table. 2/ If not present in TMTAKOBE, the risk carrying entity [EN 0.2] shall exist in the TMCCONSU column of the TMTAKOBU table. | AO20: EN0023
A21: C1 | B21: 3 | C21: 02 - Caractéristiques d'identification fonctionnelles | D21: 02 - Functional identification characteristics | E21: 0.3 (C1) | F21: Application source | G21: Source application | H21: Correspond au code du Système d'Information utilisé en local pour générer le flux Dans le flux Grande Clientèle, il faut préfixer par la lettre ‘C' le code application source | I21: Represents the code of the Information System used locally to generate the flow In Corporate flow, the source application code must be prefix with the letter 'C' | J21: ND | K21: ND | L21: NA | M21: Obligatoire | N21: Mandatory | O21: NA | P21: TA KVAPPBK | Q21: La codification est ‘libre' mais doit être obligatoirement préfixé par la valeur "C" (Corporate). Il convient à chaque entité émettrice du flux de déterminer le(s) code(s) ‘Application source' qu'elle utilise et de le(s) porter à la connaissance de la DRG avant première utilisation dans le flux. Une fois communiqué, le code est définitif Il s'agit d'un critère discriminant à l'acquisition des flux par CASA DRG | R21: The code is entered as ‘Free zone' but must be pre-fixed with "C" (Corporate). Every entity issuing flows must determine what ‘Source application' code(s) it uses and inform the Group Risk Management Division thereof prior to using them in the flow. Once notified, the code can't be changed This is a determining factor as regards flow capture by Crédit Agricole S.A. Group Risk Management Division | S21: ALPHA | T21: NA | U21: NA | V21: 12 | W21: NA | X21: 40 | Y21: NA | Z21: NA | AA21: TIGRE | AB21: ND | AC21: N | AD21: NA | AE21: NA | AF21: NA | AH21: La donnée est obligatoire | AI21: The data is mandatory | AK21: EN0031 | AL21: Si elle est renseignée, la valeur doit être connue du Langage Commun associé | AM21: If specified, the value must be known to the associated Common Language | AO21: EN0035
A22: C1 | B22: 4 | C22: 01 - Caractéristiques d'identification techniques | D22: 01 - Technical identification characteristics | E22: 0.4 (C1) | F22: Fréquence de transmission | G22: Transmission frequency | H22: Permet d'identifier le flux dans les traitements | I22: Makes it possible to identify the flow in the treatments | J22: ND | K22: ND | L22: NA | M22: Obligatoire | N22: Mandatory | O22: NA | P22: NA | Q22: La seule valeur admise est 'M' pour mensuel | R22: The only permitted value is 'M' for month | S22: ALPHA | T22: NA | U22: NA | V22: 1 | W22: NA | X22: 40 | Y22: NA | Z22: NA | AA22: TIGRE | AB22: ND | AC22: N | AD22: NA | AE22: NA | AF22: NA | AH22: La donnée est obligatoire | AI22: The data is mandatory | AK22: EN0041 | AP22: Si renseignée, la donnée doit être égale à 'M' ou 'C'. | AQ22: If filled, the data must be equal to 'M' or 'C'. | AS22: EN0043
A23: C1 | B23: 5 | C23: 01 - Caractéristiques d'identification techniques | D23: 01 - Technical identification characteristics | E23: 0.5 (C1) | F23: Date et Heure de traitement | G23: Date and time of processing | H23: Correspond à la date et heure du début du traitement ayant produit le flux | I23: Represents the date and time at which treatment began | J23: ND | K23: ND | L23: NA | M23: Obligatoire | N23: Mandatory | O23: NA | P23: NA | Q23: Unicité obligatoire au sein d'un Lot déterminé | R23: Has to be unique within a specific Batch | S23: ALPHA | T23: NA | U23: NA | V23: 12 | W23: NA | X23: 40 | Y23: NA | Z23: NA | AA23: TIGRE | AB23: ND | AC23: N | AD23: NA | AE23: NA | AF23: NA | AH23: La donnée est obligatoire | AI23: The data is mandatory | AK23: EN0051 | AT23: Si renseignée, la date doit être strictement supérieure à la date de traitement [EN 0.5] du dernier lot traité et non recyclé. (= on ne peut pas intégrer un lot déjà présenté sauf si ce lot avait été mis en recyclage) Dans la table INTEGRATED_PARENT, pour le même SCOPE_SRC_CD (= BAAPID), la date doit être supérieure à la dernière date (= SRC_DT) avec le statut « QUALITY_OK ». | AU23: If filled in, the date must be strictly greater than the treatment date [EN 0.5] of the last batch processed and not recycled. (= a previously submitted batch cannot be included unless the batch has been placed in recycling) In the INTEGRATED_PARENT table, for the same SCOPE_SRC_CD (= BAAPID), the date must be greater than the last date (= SRC_DT) with the status 'QUALITY_OK'. | AW23: EN0056
A24: C1 | B24: 6 | C24: 01 - Caractéristiques d'identification techniques | D24: 01 - Technical identification characteristics | E24: 0.6 (C1) | F24: Type d'enregistrement | G24: Record type | H24: Caractérise le type d'enregistrement remonté par l'entité | I24: Represents the record type reported by the entity | J24: ND | K24: ND | L24: NA | M24: Obligatoire | N24: Mandatory | O24: NA | P24: NA | Q24: La valeur admise est 'C1' pour le domaine Tiers | R24: The permitted value is 'C1' for the External Counterparty section | S24: ALPHA | T24: NA | U24: NA | V24: 2 | W24: NA | X24: 40 | Y24: NA | Z24: NA | AA24: TIGRE | AB24: ND | AC24: N | AD24: NA | AE24: NA | AF24: NA | AH24: La donnée est obligatoire | AI24: The data is mandatory | AK24: EN0061 | AP24: Si renseignée, la donnée doit être égale à 'C1' | AQ24: If filled in, the data must be equal to 'C1' | AS24: EN0061
A25: C1 | B25: 7 | C25: NA | D25: NA | E25: 0.7 (C1) | F25: Nature de flux (Zone réservée DRG) | G25: Nature of flow (Zone reserved for Group Risk Management Division) | H25: Nature de flux (Zone réservée DRG) | I25: Nature of flow (Zone reserved for Group Risk Management Division) | J25: NA | K25: NA | L25: NA | M25: NA | N25: NA | O25: NA | P25: NA | Q25: (Zone réservée DRG) | R25: (Zone reserved for the Group Risk Management Division) | S25: ALPHA | T25: NA | U25: NA | V25: 1 | W25: NA | X25: NA | Y25: 42 | Z25: NA | AA25: NA | AB25: NA | AC25: N | AD25: NA | AE25: NA | AF25: NA
A26: C1 | B26: 8 | C26: NA | D26: NA | E26: 0.99 (C1) | F26: Filler | G26: Filler | H26: Zone libre | I26: Free zone | J26: NA | K26: NA | L26: NA | M26: NA | N26: NA | O26: NA | P26: NA | Q26: Laisser à vide | R26: Leave empty | S26: ALPHA | T26: NA | U26: NA | V26: 9 | W26: NA | X26: NA | Y26: NA | Z26: NA | AA26: NA | AB26: NA | AC26: N | AD26: NA | AE26: NA | AF26: NA
A27: C1 | B27: 9 | C27: 16 - Identification Tiers | D27: 16 - Third party identification | E27: 1.1 (C1) | F27: Identifiant local du tiers | G27: Local identifier for the counterparty | H27: Identifiant du tiers dans le système utilisé pour générer le flux | I27: ID of external counterparty in the system used to generate the flow | J27: ND | K27: ND | L27: NA | M27: Obligatoire | N27: Mandatory | O27: NA | P27: NA | Q27: La codification est à discrétion de chaque entité mais il est nécessaire d'utiliser un identifiant stable Pour un lot déterminé, l'identifiant local doit être unique | R27: The coding is at the discretion of each entity but IDs must be permanent For a given batch, the local ID must be unique | S27: ALPHA | T27: NA | U27: NA | V27: 20 | W27: NA | X27: 40 | Y27: NA | Z27: NA | AA27: TIGRE | AB27: ND | AC27: N | AD27: NA | AE27: NA | AF27: NA
A28: C1 | B28: 10 | C28: 16 - Identification Tiers | D28: 16 - Third party identification | E28: 1.2 (C1) | F28: Identifiant interne du tiers Crédit Agricole | G28: Central identifier for the counterparty | H28: Identifiant du tiers dans le SI DRG IDTCA – (i.e. Identifiant Tiers Central CASA) | I28: ID of the external counterparty in the Group Risk Management Division IT System IDTCA – (i.e. Identifier Central CASA counterparty) | J28: ND | K28: ND | L28: NA | M28: Facultatif | N28: Optional | O28: NA | P28: NA | Q28: Identifiant central fourni par la DRG dans le flux diffusion Tiers (DTG) transmis aux entités émettrices du flux A la première remontée d'un tiers nouvellement créé via le flux , cet identifiant doit être à vide L'identifiant interne est déterminé en central et communiqué aux entités via le flux diffusion Tiers (DTG) et doit être fourni dans le flux du mois suivant (si toujours des engagements sur ce Tiers) | R28: Central ID provided by the Group Risk Management Division in the External Counterparty distribution flow (DTG) sent out to entities issuing flows. When first reporting an external counterparty that has just been added via the flow, this ID must be left empty. The internal ID is determined centrally and sent out to the entities via the External Counterparty distribution flow (DTG) and must be provided in the subsequent month's flow (if there are still commitments vis-à-vis this External Counterparty) | S28: ALPHA | T28: NA | U28: NA | V28: 10 | W28: NA | X28: 40 | Y28: NA | Z28: NA | AA28: TIGRE | AB28: ND | AC28: N | AD28: NA | AE28: NA | AF28: NA
A29: C1 | B29: 11 | C29: NA | D29: NA | E29: 1.4 (C1) | F29: Référence de l'Autorisation Mise En Place | G29: Overall facility reference | H29: Référence de l'Autorisation Mise En Place | I29: Reference code of Arranged facility | J29: NA | K29: NA | L29: NA | M29: NA | N29: NA | O29: NA | P29: NA | Q29: NA | R29: NA | S29: ALPHA | T29: NA | U29: NA | V29: 30 | W29: NA | X29: NA | Y29: 42 | Z29: NA | AA29: NA | AB29: NA | AC29: N | AD29: NA | AE29: NA | AF29: NA
A30: C1 | B30: 12 | C30: NA | D30: NA | E30: 1.6 (C1) | F30: Référence de la ligne de détail de l'Autorisation Mise En Place | G30: Facility detail line reference | H30: Référence de la ligne de détail de l'Autorisation Mise En Place | I30: Reference code of the line of the Arranged facility | J30: NA | K30: NA | L30: NA | M30: NA | N30: NA | O30: NA | P30: NA | Q30: NA | R30: NA | S30: ALPHA | T30: NA | U30: NA | V30: 30 | W30: NA | X30: NA | Y30: 42 | Z30: NA | AA30: NA | AB30: NA | AC30: N | AD30: NA | AE30: NA | AF30: NA
A31: C1 | B31: 13 | C31: NA | D31: NA | E31: 1.8 (C1) | F31: Identifiant de la sûreté reçue | G31: Mitigant identifier | H31: Identifiant de la sûreté reçue | I31: ID of Mitigant received | J31: NA | K31: NA | L31: NA | M31: NA | N31: NA | O31: NA | P31: NA | Q31: NA | R31: NA | S31: ALPHA | T31: NA | U31: NA | V31: 40 | W31: NA | X31: NA | Y31: 42 | Z31: NA | AA31: NA | AB31: NA | AC31: N | AD31: NA | AE31: NA | AF31: NA
A32: C1 | B32: 14 | C32: NA | D32: NA | E32: 1.11 (C1) | F32: Identifiant de l'engagement | G32: Product identifier | H32: Identifiant de l'engagement | I32: ID of commitment | J32: NA | K32: NA | L32: NA | M32: NA | N32: NA | O32: NA | P32: NA | Q32: NA | R32: NA | S32: ALPHA | T32: NA | U32: NA | V32: 40 | W32: NA | X32: NA | Y32: 42 | Z32: NA | AA32: NA | AB32: NA | AC32: N | AD32: NA | AE32: NA | AF32: NA
A33: C1 | B33: 15 | C33: NA | D33: NA | E33: 1.16 (C1) | F33: Référence de la provision sur tiers | G33: Reference for the counterparty provision | H33: Référence de la provision sur tiers | I33: Reference code of the provision for external counterparties | J33: NA | K33: NA | L33: NA | M33: NA | N33: NA | O33: NA | P33: NA | Q33: NA | R33: NA | S33: ALPHA | T33: NA | U33: NA | V33: 40 | W33: NA | X33: NA | Y33: 42 | Z33: NA | AA33: NA | AB33: NA | AC33: N | AD33: NA | AE33: NA | AF33: NA
A34: C1 | B34: 16 | C34: NA | D34: NA | E34: 1.99 (C1) | F34: Filler | G34: Filler | H34: Zone libre | I34: Free zone | J34: NA | K34: NA | L34: NA | M34: NA | N34: NA | O34: NA | P34: NA | Q34: Laisser à vide | R34: Leave empty | S34: ALPHA | T34: NA | U34: NA | V34: 20 | W34: NA | X34: NA | Y34: NA | Z34: NA | AA34: NA | AB34: NA | AC34: N | AD34: NA | AE34: NA | AF34: NA
A35: C1 | B35: 17 | C35: 16 - Identification Tiers | D35: 16 - Third party identification | E35: C1 2.1 | F35: Dénomination sociale INSEE | G35: Counterparty name | H35: Dénomination sociale INSEE pour les tiers français | I35: Corporate name INSEE for French counterparties National's corporate name for other counterparties when it exists; corporate name otherwise | J35: ND | K35: ND | L35: NA | M35: Obligatoire | N35: Mandatory | O35: NA | P35: NA | Q35: Obligatoire pour les tiers français (c'est-à-dire siréné), valoriser le champ avec la dénomination officielle INSEE sinon à vide Donnée sous responsabilité du RUN. | R35: Mandatory for French external counterparties (i.e. those with SIREN numbers). Input the official INSEE corporate name, otherwise leave empty Data owned by the «RUN». | S35: ALPHA | T35: NA | U35: NA | V35: 40 | W35: NA | X35: 40 | Y35: NA | Z35: NA | AA35: TIGRE | AB35: ND | AC35: N | AD35: NA | AE35: NA | AF35: NA
A36: C1 | B36: 18 | C36: 16 - Identification Tiers | D36: 16 - Third party identification | E36: C1 4.22 | F36: Date de génération du CRE ANADEFI | G36: CRE ANADEFI processing Date | H36: Date de génération du CRE ANADEFI | I36: CRE ANADEFI processing Date | J36: ND | K36: ND | L36: NA | M36: Obligatoire | N36: Mandatory | O36: NA | P36: NA | Q36: Obligatoire si le tiers est noté (la note finale retenue du tiers (C1 4.1) est renseignée et différente de 'ND' ) | R36: Mandatory where the assigned rating (C1 4.1) <> ‘ND' or equals spaces | S36: ALPHA | T36: AAAAMMJJHHMMSS | U36: SSAAMMJJHHMMSS | V36: 14 | W36: NA | X36: 40 | Y36: NA | Z36: NA | AA36: TIGRE | AB36: ND | AC36: N | AD36: NA | AE36: NA | AF36: NA
A37: C1 | B37: 19 | C37: 16 - Identification Tiers | D37: 16 - Third party identification | E37: C1 4.30 | F37: Identifiant de l'entreprise mère immédiate | G37: Immediate parent undertaking identifier | H37: Permet d'identifier la maison mère immédiate | I37: Enable the identification of the immediate mother entity | J37: ND | K37: ND | L37: NA | M37: Facultatif | N37: Optional | O37: NA | P37: NA | Q37: Identifiant de l'entreprise mère immédiate correspondant à l'Identifiant Central du Tiers (IDTCA) présent dans le référentiel Tiers & Groupes - Si le tiers représente une succursale d'un établissement dont le siège social à l'étranger (et connu de Tiers et Groupe) alors : C1 4.30 = identifiant IDTCA du siège social (ou maison mère) à l'étranger C1 4.31 = 1 - Si le tiers appartient à un groupe dont le parent immédiat existe (et connu de Tiers et Groupe) alors on renseigne : C1 4.30 = identifiant IDTCA du parent immédiat C1 4.31 = 0 Remarque : dans certains cas, le parent immédiat peut être l'ECU - Sinon, ne pas renseigner l'Identifiant de l'entreprise mère immédiate et l'Indicateur Maison mère identifiée | R37: The Immediate parent undertaking identifier corresponding to the IDTCA of the counterparty in the referential ‘Counterparties & Groups' - If the client of the FTCA represents a branch of a credit insititution whose head office is abroad (and known of the process T&G), then: C10430 = Identifier IDTCA of the head office (or mother entity) abroad C10431 = 1 - If the client of the FTCA is part of a Groupe whose immediate parent exists (and known of the process T&G) then: C10430 = Identifier IDTCA of the immediate parent C10431 = 0 Note : in some cases, the immediate parent may be the ECU - If none of the mis known, the field C10430 remains empty | S37: ALPHA | T37: NA | U37: NA | V37: 10 | W37: NA | X37: 42 | Y37: NA | Z37: NA | AA37: ANACREDIT | AB37: ND | AC37: N | AD37: NA | AE37: NA | AF37: NA
A38: C1 | B38: 20 | C38: 16 - Identification Tiers | D38: 16 - Third party identification | E38: C1 4.31 | F38: Maison Mère Identifiée | G38: Head Office Identifier | H38: Permet d'identifier si le tiers est la maison mère | I38: Enable the identification of the mother entity | J38: ND | K38: ND | L38: NA | M38: Facultatif | N38: Optional | O38: LC.0302 | P38: TA KVMAMEID | Q38: Indicateur 0 ou 1 permettant de préciser que le tiers déclaré est maison mère | R38: Value 0 or 1 aiming at precising if the counterparty is the mother entity | S38: ALPHA | T38: NA | U38: NA | V38: 1 | W38: NA | X38: 42 | Y38: NA | Z38: NA | AA38: ANACREDIT | AB38: ND | AC38: N | AD38: NA | AE38: NA | AF38: NA
A39: C1 | B39: 21 | C39: 16 - Identification Tiers | D39: 16 - Third party identification | E39: C1 4.32 | F39: Adresse : département/division administrative (NUTS) | G39: Address: department/administrative division (NUTS) | H39: Permet d'identifier le département du tiers | I39: Enable the identification of the administrative area of the counterparty | J39: ND | K39: ND | L39: NA | M39: Facultatif | N39: Optional | O39: LC.0265 | P39: TA NMNUTS | Q39: NA | R39: NA | S39: ALPHA | T39: NA | U39: NA | V39: 5 | W39: NA | X39: 42 | Y39: NA | Z39: NA | AA39: ANACREDIT | AB39: ND | AC39: N | AD39: NA | AE39: NA | AF39: NA
A40: C1 | B40: 22 | C40: 16 - Identification Tiers | D40: 16 - Third party identification | E40: C1 4.33 | F40: État d'avancement des procédures judiciaires | G40: Status of legal Proceeding | H40: Permet d'identifier si une procédure judiciaire est en cours | I40: Enable to indicate if a legal procedure is ongoing | J40: ND | K40: ND | L40: NA | M40: Facultatif | N40: Optional | O40: LC.0226 | P40: TA KVINPROC | Q40: NA | R40: NA | S40: ALPHA | T40: NA | U40: NA | V40: 1 | W40: NA | X40: 42 | Y40: NA | Z40: NA | AA40: ANACREDIT | AB40: ND | AC40: N | AD40: NA | AE40: NA | AF40: NA
A41: C1 | B41: 23 | C41: 16 - Identification Tiers | D41: 16 - Third party identification | E41: C1 4.34 | F41: Date d'ouverture de la procédure judiciaire | G41: Date of initiation of legal proceedings | H41: Informe sur la date de début de cette procédure | I41: Indicate the original date of the legal procedure | J41: ND | K41: ND | L41: NA | M41: Obligatoire | N41: Mandatory | O41: NA | P41: NA | Q41: Si la valeur du champ « Etat d'avancement des procédures judiciaires » est différente de 0 ou 1 alors date obligatoire sinon le champ doit rester à vide | R41: Mandatory where status of legal proceeding different from 0 or 1 | S41: DATE | T41: AAAAMMJJ | U41: YYYYMMDD | V41: 8 | W41: NA | X41: 42 | Y41: NA | Z41: NA | AA41: ANACREDIT | AB41: ND | AC41: N | AD41: NA | AE41: NA | AF41: NA
A42: C1 | B42: 24 | C42: 16 - Identification Tiers | D42: 16 - Third party identification | E42: C1 4.35 | F42: Nombre de salariés | G42: Number of employees | H42: Informe sur le nombre de salariés de l'entreprise | I42: Indicate the number of employees | J42: ND | K42: ND | L42: NA | M42: Facultatif | N42: Optional | O42: NA | P42: NA | Q42: NA | R42: NA | S42: ALPHA | T42: NA | U42: NA | V42: 6 | W42: NA | X42: 42 | Y42: NA | Z42: NA | AA42: ANACREDIT | AB42: ND | AC42: N | AD42: NA | AE42: NA | AF42: NA
A43: C1 | B43: 25 | C43: 16 - Identification Tiers | D43: 16 - Third party identification | E43: C1 4.40 | F43: Indicateur CEL (Corporate Leveraged) | G43: Corporate Leveraged indicator | H43: Cette valeur permet d'identifier un tiers pour lequel un financement à effet de levier est en place | I43: This criteria identifies the counterpart leveraged | J43: ND | K43: ND | L43: NA | M43: Obligatoire | N43: Mandatory | O43: NA | P43: NA | Q43: Donnée sous responsabilité du RUN. Si renseigné, les valeurs autorisées sont : - 0 : " Pas de financements à effet de levier pour ce tiers" - 1 : " Tiers déclaré à effet de levier" | R43: Data owned by the «RUN» Value 0 or 1 aiming at precising if the counterparty is leveraged : - 0: "No leveraged transaction for this counterparty" - 1: "Leveraged counterparty" | S43: ALPHA | T43: NA | U43: NA | V43: 1 | W43: NA | X43: 43 | Y43: NA | Z43: NA | AA43: FEL | AB43: ND | AC43: N | AD43: NA | AE43: NA | AF43: NA
A44: C1 | B44: 26 | C44: 16 - Identification Tiers | D44: 16 - Third party identification | E44: C1 4.41 | F44: Niveau d'intégration groupe du tiers | G44: Group Integration degree | H44: Cette donnée permet de définir le soutien financier de la maison mère à sa filiale | I44: This criteria defines the support of the group to the subsidiary | J44: ND | K44: ND | L44: NA | M44: Obligatoire | N44: Mandatory | O44: LC.0304 | P44: TA KVNIVITG | Q44: Donnée sous responsabilité du RUN | R44: Data owned by the «RUN» | S44: ALPHA | T44: NA | U44: NA | V44: 1 | W44: NA | X44: 43 | Y44: NA | Z44: NA | AA44: FEL | AB44: ND | AC44: N | AD44: NA | AE44: NA | AF44: NA
A45: C1 | B45: 27 | C45: 16 - Identification Tiers | D45: 16 - Third party identification | E45: C1 4.42 | F45: Indicateur OPCVM à effet de levier | G45: Leveraged FUNDS indicator | H45: Permet d'identifier les fonds à effet de levier | I45: This criteria identifies the leveraged FUNDS | J45: ND | K45: ND | L45: NA | M45: Obligatoire | N45: Mandatory | O45: LC.0321 | P45: TA KVIOPCEL | Q45: La donnée concerne les catégories de contreparties MCG31, MCG32, MCG41, MCG42, MCG43 et MCG44 Donnée sous responsabilité du RUN | R45: This data aims to precising if the FUNDS is leveraged for the following counterparties categories MCG31, MGC32, MCG41, MCG42, MCG43 and MCG44 Data owned by the «RUN» | S45: ALPHA | T45: NA | U45: NA | V45: 1 | W45: NA | X45: 43 | Y45: NA | Z45: NA | AA45: FEL | AB45: ND | AC45: N | AD45: NA | AE45: NA | AF45: NA
A46: C1 | B46: 28 | C46: 16 - Identification Tiers | D46: 16 - Third party identification | E46: C1 4.43 | F46: Typologie du fonds OPCVM | G46: FUNDS categories | H46: Permet de renseigner la typologie du fonds | I46: This criteria identifies the FUNDS categories | J46: ND | K46: ND | L46: NA | M46: Obligatoire | N46: Mandatory | O46: LC.0320 | P46: TA KVCLASFD | Q46: Obligatoire si l'entité est RUN du tiers et si la catégorie de contrepartie du fonds est MCG31, MCG32, MCG41, MCG42, MCG43 et MCG44 Donnée sous responsabilité du RUN | R46: Mandatory if the entity is the RUN of the counterparty and the fund's counterparty category is MCG31, MCG32, MCG41, MCG42, MCG43 and MCG44 Data owned by the «RUN» | S46: ALPHA | T46: NA | U46: NA | V46: 4 | W46: NA | X46: 43 | Y46: NA | Z46: NA | AA46: TIGRE | AB46: ND | AC46: N | AD46: NA | AE46: NA | AF46: NA
A47: C1 | B47: 29 | C47: 16 - Identification Tiers | D47: 16 - Third party identification | E47: C1 4.44 | F47: Agent économique | G47: Economic Agent | H47: Identifie le code de l'agent économique FINREP | I47: Relates to the FINREP Economic Agent codes | J47: ND | K47: ND | L47: NA | M47: Obligatoire | N47: Mandatory | O47: LC.0323 | P47: TA H8AESTAT | Q47: Donnée sous responsabilité du RUN | R47: Data owned by the «RUN» | S47: ALPHA | T47: NA | U47: NA | V47: 6 | W47: NA | X47: 43 | Y47: NA | Z47: NA | AA47: TIGRE | AB47: ND | AC47: N | AD47: NA | AE47: NA | AF47: NA
A48: C1 | B48: 30 | C48: NA | D48: NA | E48: C1 4.45 | F48: Type d'identifiant national BCE | G48: Type d'identifiant national BCE | H48: Identification du type d'identifiant National selon la norme BCE | I48: Identification of the National identifier type according to the BCE standard | J48: NA | K48: NA | L48: NA | M48: NA | N48: NA | O48: LC.0356 | P48: TA Z8TIDBCE | Q48: Concerne tous les tiers dont le pays de résidence fiscal est hors de France. Des types d'identifiants nationaux sont donnés pour 41 pays hors de France (AT, BE, BG, BR, CA, CH, CN, CY, CZ, DE, DK, EE, ES, FI, GB, GR, HK, IE, IN, IT, JP, LT, LU, LV, MC, MH, MT, MX, NL, NO, PL, PT, RO, RU, SE, SI, SK, TR, US,HR, HU) et pour les autres un code générique est prévu | R48: Concerns all third parties whose country of tax residence is outside France. National identifier types are given for 41 countries outside of France (AT, BE, BG, BR, CA, CH, CN, CY, CZ, DE, DK, EE, ES, FI, GB, GR, HK, IE , IN, IT, JP, LT, LU, LV, MC, MH, MT, MX, NL, NO, PL, PT, RO, RU, SE, SI, SK, TR, US, HR, HU) and for others a generic code is provided | S48: ALPHA | T48: NA | U48: NA | V48: 4 | W48: NA | X48: NA | Y48: 43 | Z48: NA | AA48: ANACREDIT | AB48: NA | AC48: N | AD48: NA | AE48: NA | AF48: NA
A49: C1 | B49: 31 | C49: NA | D49: NA | E49: C1 4.46 | F49: Valeur de l'identifiant national BCE | G49: Valeur de l'identifiant national BCE | H49: Valeur de l'identifiant national associé au type d'identifiant national | I49: Value of the national identifier associated with the type of national identifier | J49: NA | K49: NA | L49: NA | M49: NA | N49: NA | O49: NA | P49: NA | Q49: Concerne tous les tiers dont le pays de résidence fiscal est hors de France | R49: Concerns all third parties whose country of tax residence is outside France | S49: ALPHA | T49: NA | U49: NA | V49: 21 | W49: NA | X49: NA | Y49: 43 | Z49: NA | AA49: ANACREDIT | AB49: NA | AC49: N | AD49: NA | AE49: NA | AF49: NA
A50: C1 | B50: 32 | C50: 16 - Identification Tiers | D50: 16 - Third party identification | E50: C1 4.47 | F50: Forme juridique BCE du tiers | G50: Third Party ECB Legal Form | H50: Décrit la forme juridique BCE du tiers en UE | I50: Describes the ECB legal form of third parties outside France in the EU | J50: ND | K50: ND | L50: NA | M50: Facultatif | N50: Optional | O50: LC.0357 | P50: TA Z8FJUBCE | Q50: Concerne tous les tiers dont le pays de résidence fiscal est hors de France et dans l'UE. Des formes juridiques génériques peuvent être utilisées pour les autres pays Donnée sous responsabilité du RUN | R50: Concerns all third parties whose country of tax residence is outside France and in the EU. Generic legal forms can be used for other countries Data owned by the «RUN» | S50: ALPHA | T50: NA | U50: NA | V50: 6 | W50: NA | X50: 43 | Y50: NA | Z50: NA | AA50: ANACREDIT | AB50: ND | AC50: N | AD50: NA | AE50: NA | AF50: NA
A51: C1 | B51: 33 | C51: NA | D51: NA | E51: C1 2.98 | F51: Filler | G51: Filler | H51: Zone libre | I51: Free zone | J51: NA | K51: NA | L51: NA | M51: NA | N51: NA | O51: NA | P51: NA | Q51: Laisser à vide | R51: Leave empty | S51: ALPHA | T51: NA | U51: NA | V51: 1 | W51: NA | X51: NA | Y51: NA | Z51: NA | AA51: NA | AB51: NA | AC51: N | AD51: NA | AE51: NA | AF51: NA
A52: C1 | B52: 34 | C52: 16 - Identification Tiers | D52: 16 - Third party identification | E52: C1 2.3 | F52: Référence d'Identification nationale | G52: National ID framework | H52: Type de référence d'identification nationale | I52: Type of national ID framework | J52: ND | K52: ND | L52: NA | M52: Obligatoire | N52: Mandatory | O52: LC.0013 | P52: TA KVIDENT | Q52: Cette donnée indique le référentiel de l'identifiant national renseigné au champ suivant | R52: This data indicates the national ID framework input into the next field | S52: ALPHA | T52: NA | U52: NA | V52: 2 | W52: NA | X52: 40 | Y52: NA | Z52: NA | AA52: ANACREDIT | AB52: ND | AC52: N | AD52: NA | AE52: NA | AF52: NA
A53: C1 | B53: 35 | C53: 16 - Identification Tiers | D53: 16 - Third party identification | E53: C1 2.4 | F53: Identifiant national | G53: National ID | H53: Code issu de la référence d'identification nationale | I53: Code under the national ID framework | J53: ND | K53: ND | L53: NA | M53: Obligatoire | N53: Mandatory | O53: NA | P53: NA | Q53: Le champ est obligatoire si la Référence d'identification nationale (C1 2.3) est renseignée - SIREN pour les tiers unitaires résidant en France, Guadeloupe, Martinique, Réunion, Guyane Française, Mayotte ou St Pierre et Miquelon ; - Tax ID pour les tiers unitaires résidant aux USA. - codice fiscale pour les tiers Italiens - ... Si le tiers est siréné, alors valoriser obligatoirement le champ avec le code SIREN Sinon, fournir si disponible le code d'identification du référentiel national concerné (à vide si indisponible) | R53: The field is mandatory where the National ID framework (C1 2.3) is indicated - SIREN for individual external counterparties resident in France, Guadeloupe, Martinique, Reunion, French Guyana, Mayotte or St Pierre et Miquelon; - Tax ID for individual external counterparties resident in the US. - codice fiscale for Italian external counterparties - ... Where the external counterparty has a SIREN number it must be input into the field Otherwise, where available provide the ID code of the relevant national framework (empty where not available) | S53: ALPHA | T53: NA | U53: NA | V53: 20 | W53: NA | X53: 40 | Y53: NA | Z53: NA | AA53: ANACREDIT, NZBA | AB53: ND | AC53: N | AD53: NA | AE53: NA | AF53: NA
A54: C1 | B54: 36 | C54: 16 - Identification Tiers | D54: 16 - Third party identification | E54: C1 2.5 | F54: Identification en local | G54: Local identification flag | H54: Réservé à CACIB – Permet à l'entité CACIB d'indiquer qu'elle a procédé à l'identification du Tiers au sein du SI central et qu'il s'agit bien d'un nouveau tiers de catégorie de contrepartie autorisée dont la création peut être validée automatiquement. | I54: For CACIB only - Using this field, CACIB can confirm that the identification of the counterparty within the central IS has been made properly, and the category of counterparty is authorized.(Specific CASA CACIB) | J54: ND | K54: ND | L54: NA | M54: Facultatif | N54: Optional | O54: NA | P54: NA | Q54: Zone reservée pour CACIB. Laisser à vide si non concerné | R54: Zone reserved for CACIB. Leave empty if not concerned | S54: ALPHA | T54: NA | U54: NA | V54: 1 | W54: NA | X54: 42 | Y54: NA | Z54: NA | AA54: TIGRE | AB54: ND | AC54: N | AD54: NA | AE54: NA | AF54: NA
A55: C1 | B55: 37 | C55: 16 - Identification Tiers | D55: 16 - Third party identification | E55: C1 4.48 | F55: Numéro du Registre Nationale des associations | G55: Number of the National Register of associations | H55: Identification de l'association (Sous la forme W + 9 chiffres) au Registre National des Associations (RNA) | I55: Identification of the association (as W + 9 digits) in the National Register of Associations (RNA) | J55: ND | K55: ND | L55: NA | M55: Obligatoire | N55: Mandatory | O55: NA | P55: NA | Q55: Le numéro du RNA est obligatoire pour les associations qui n'ont pas de SIREN | R55: The NAS No. is mandatory for associations that do not have a SIREN | S55: ALPHA | T55: NA | U55: NA | V55: 10 | W55: NA | X55: 43 | Y55: NA | Z55: NA | AA55: ANACREDIT | AB55: ND | AC55: N | AD55: NA | AE55: NA | AF55: NA
A56: C1 | B56: 38 | C56: NA | D56: NA | E56: C1 5.13 | F56: Filler | G56: Filler | H56: Zone libre | I56: Free zone | J56: NA | K56: NA | L56: NA | M56: NA | N56: NA | O56: NA | P56: NA | Q56: Laisser à vide | R56: Leave empty | S56: ALPHA | T56: NA | U56: NA | V56: 1 | W56: NA | X56: NA | Y56: NA | Z56: NA | AA56: NA | AB56: NA | AC56: N | AD56: NA | AE56: NA | AF56: NA
A57: C1 | B57: 39 | C57: 25 - Notation du tiers | D57: 25 - Third party rating | E57: C1 2.9 | F57: Agence de notation | G57: Rating agency | H57: Organisme de notation reconnu | I57: Recognised rating body | J57: ND | K57: ND | L57: NA | M57: Facultatif | N57: Optional | O57: LC.0189 | P57: TA KVON | Q57: A renseigner pour les Tiers domicilié à l'étranger si l'agence de notation est autorisée par la DRG Donnée sous responsabilité du RUN | R57: Fill in for “Corporate” Clients domiciled abroad Data owned by the «RUN» | S57: ALPHA | T57: NA | U57: NA | V57: 2 | W57: NA | X57: 40 | Y57: NA | Z57: NA | AA57: TIGRE | AB57: ND | AC57: N | AD57: NA | AE57: NA | AF57: NA
A58: C1 | B58: 40 | C58: 16 - Identification Tiers | D58: 16 - Third party identification | E58: C1 2.10 | F58: Type de cotation | G58: Type of rating | H58: Codification indiquant le type LT ou CT de la cotation | I58: Codification giving the LT or CT type of rating | J58: ND | K58: ND | L58: NA | M58: Obligatoire | N58: Mandatory | O58: LC.0181 | P58: TA KVTCOTA | Q58: Obligatoire si agence de notation renseignée. Donnée sous responsabilité du RUN | R58: Mandatory where Rating agency is indicated Data owned by the «RUN» | S58: ALPHA | T58: NA | U58: NA | V58: 2 | W58: NA | X58: 40 | Y58: NA | Z58: NA | AA58: TIGRE | AB58: ND | AC58: N | AD58: NA | AE58: NA | AF58: NA
A59: C1 | B59: 41 | C59: 16 - Identification Tiers | D59: 16 - Third party identification | E59: C1 2.11 | F59: Cotation | G59: Rating | H59: Cotation externes (selon le la nomenclature de l'organisme) | I59: External rating (depending on the body classification) | J59: ND | K59: ND | L59: NA | M59: Obligatoire | N59: Mandatory | O59: NA | P59: NA | Q59: Obligatoire si agence de notation renseignée. Donnée sous responsabilité du RUN | R59: Mandatory where Rating agency is indicated Data owned by the «RUN» | S59: ALPHA | T59: NA | U59: NA | V59: 10 | W59: NA | X59: 40 | Y59: NA | Z59: NA | AA59: TIGRE | AB59: ND | AC59: N | AD59: NA | AE59: NA | AF59: NA
A60: C1 | B60: 42 | C60: 16 - Identification Tiers | D60: 16 - Third party identification | E60: C1 2.12 | F60: Date de cotation | G60: Date of rating | H60: Date de cotation | I60: Date of rating | J60: ND | K60: ND | L60: NA | M60: Obligatoire | N60: Mandatory | O60: NA | P60: NA | Q60: Obligatoire si agence de notation renseignée. Donnée sous responsabilité du RUN | R60: Mandatory where Rating agency is indicated Data owned by the «RUN» | S60: DATE | T60: AAAAMMJJ | U60: YYYYMMDD | V60: 8 | W60: NA | X60: 40 | Y60: NA | Z60: NA | AA60: TIGRE | AB60: ND | AC60: N | AD60: NA | AE60: NA | AF60: NA
A61: C1 | B61: 43 | C61: 16 - Identification Tiers | D61: 16 - Third party identification | E61: C1 3.1 | F61: Pays de résidence du siège social | G61: Country of residence of registered office | H61: Code du pays d'immatriculation du tiers | I61: Code of country of registration of external counterparty | J61: ND | K61: ND | L61: NA | M61: Obligatoire | N61: Mandatory | O61: LC.0004 | P61: TA NM252 | Q61: Norme ISO 2. Code du pays de l'adresse du siège social prenant en compte le cas échéant la notion de territoire (ex: Guadeloupe). Cette notion diffère du pays de nationalité (ex: la France pour la Guadeloupe) Donnée sous responsabilité du RUN | R61: ISO 2 standard. Code of country of registered address encompassing where necessary territories (e.g. Guadeloupe). This concept differs from country of nationality (e.g. France for Guadeloupe) Data owned by the «RUN» | S61: ALPHA | T61: NA | U61: NA | V61: 2 | W61: NA | X61: 40 | Y61: NA | Z61: NA | AA61: TIGRE | AB61: ND | AC61: N | AD61: NA | AE61: NA | AF61: NA
A62: C1 | B62: 44 | C62: 16 - Identification Tiers | D62: 16 - Third party identification | E62: C1 3.2 | F62: Pays de résidence | G62: Country of tax residence | H62: Code du pays dans lequel est implanté le tiers | I62: Code of country in which the third party is established. Corresponds to country of tax residence | J62: ND | K62: ND | L62: NA | M62: Obligatoire | N62: Mandatory | O62: LC.0004 | P62: TA NM252 | Q62: Norme ISO 2 Code du pays de l'adresse fiscale Il permet de connaître le système de droit dans lequel s'inscrit la contrepartie financée Donnée sous responsabilité du RUN | R62: ISO 2 standard Code of country of tax address This makes it possible to identify the legal system under which the financed counterparty operates Data owned by the «RUN» | S62: ALPHA | T62: NA | U62: NA | V62: 2 | W62: NA | X62: 40 | Y62: NA | Z62: NA | AA62: ANACREDIT, CORFOU | AB62: ND | AC62: N | AD62: NA | AE62: NA | AF62: NA
A63: C1 | B63: 45 | C63: 16 - Identification Tiers | D63: 16 - Third party identification | E63: C1 3.3 | F63: Pays de contrôle | G63: Country of control | H63: Code du pays de la maison mère ou du principal actionnaire. Tous les tiers d'un même groupe ont le même pays de contrôle | I63: Code of country of parent company or main shareholder. All external counterparties within a single group share the same country of control | J63: ND | K63: ND | L63: NA | M63: Obligatoire | N63: Mandatory | O63: LC.0004 | P63: TA NM252 | Q63: Le pays de contrôle par défaut est le pays de résidence du siège social Dans le cas du tiers isolé: il s'agit du pays de la principale activité économique du bénéficiaire principal de la contrepartie, i.e. le pays où elle a ses principaux intérêts économiques (activité, avoirs, patrimoine, ...) Dans le cas d'un tiers est rattaché à un groupe: cette information est sous responsabilité de l'entité RUN groupe car tous les tiers d'un même groupe ont le même pays de contrôle | R63: The default country of control is the country of residence of the registered office In the case of an individual external counterparty: it is the country in which the counterparty's primary beneficiary has its main business activities, i.e. the country in which it has its main economic interests (business activities, holdings, assets, ...) In the event of an external counterparty that belongs to a group: this information is the responsibility of the Group RUN entity because all external counterparties within the same group share the same country of control | S63: ALPHA | T63: NA | U63: NA | V63: 2 | W63: NA | X63: 40 | Y63: NA | Z63: NA | AA63: TIGRE | AB63: ND | AC63: N | AD63: NA | AE63: NA | AF63: NA
A64: C1 | B64: 46 | C64: 16 - Identification Tiers | D64: 16 - Third party identification | E64: C1 3.5 | F64: Adresse | G64: Address | H64: Adresse fiscale. Numéro et nom de la rue Fournir prioritairement le nom de la rue | I64: Tax address. Street name and number First provide the street name | J64: ND | K64: ND | L64: NA | M64: Obligatoire | N64: Mandatory | O64: NA | P64: NA | Q64: Adresse fiscale de niveau personne morale. Obligatoire à la création du Tiers | R64: Tax address of legal entity. Mandatory for the creation of External Counterparties | S64: ALPHA | T64: NA | U64: NA | V64: 70 | W64: NA | X64: 40 | Y64: NA | Z64: NA | AA64: ANACREDIT | AB64: ND | AC64: N | AD64: NA | AE64: NA | AF64: NA
A65: C1 | B65: 47 | C65: 16 - Identification Tiers | D65: 16 - Third party identification | E65: C1 3.6 | F65: Ville | G65: City | H65: Ville de résidence du tiers | I65: City of residence of external counterparty | J65: ND | K65: ND | L65: NA | M65: Obligatoire | N65: Mandatory | O65: NA | P65: NA | Q65: Ville de l'adresse fiscale de niveau personne morale. Obligatoire à la création du Tiers | R65: City component of tax address of legal entity. Mandatory for the creation of External Counterparties | S65: ALPHA | T65: NA | U65: NA | V65: 30 | W65: NA | X65: 40 | Y65: NA | Z65: NA | AA65: ANACREDIT | AB65: ND | AC65: N | AD65: NA | AE65: NA | AF65: NA
A66: C1 | B66: 48 | C66: 16 - Identification Tiers | D66: 16 - Third party identification | E66: C1 3.7 | F66: Code postal | G66: Postcode | H66: Code postal de la ville de résidence | I66: Postcode of the city of residence | J66: ND | K66: ND | L66: NA | M66: Obligatoire | N66: Mandatory | O66: NA | P66: NA | Q66: Code postal de l'adresse fiscale de niveau personne morale. Obligatoire à la création du Tiers | R66: Postcode component of tax address of legal entity. Mandatory for the creation of External Counterparties | S66: ALPHA | T66: NA | U66: NA | V66: 15 | W66: NA | X66: 40 | Y66: NA | Z66: NA | AA66: ANACREDIT | AB66: ND | AC66: N | AD66: NA | AE66: NA | AF66: NA
A67: C1 | B67: 49 | C67: 25 - Notation du tiers | D67: 25 - Third party rating | E67: C1 4.0 | F67: Date d'arrêté des comptes pour la notation | G67: Reporting date of accounts used for the rating | H67: Date de clôture des comptes ayant servi pour noter le tiers | I67: Closing date of financial statements used to rate the external counterparty | J67: ND | K67: ND | L67: NA | M67: Obligatoire | N67: Mandatory | O67: NA | P67: NA | Q67: Obligatoire dès que le tiers est noté (note finale retenue (C1 4.1) <> ‘ND') A vide si C1 4.1 = ‘ND' Donnée sous responsabilité du RUN | R67: Mandatory once the external counterparty is rated (assigned rating (C1 4.1) <> ‘ND') Empty where C1 4.1 = ‘ND' Data owned by the «RUN» | S67: DATE | T67: AAAAMMJJ | U67: YYYYMMDD | V67: 8 | W67: NA | X67: 40 | Y67: NA | Z67: NA | AA67: ANACREDIT | AB67: ND | AC67: N | AD67: NA | AE67: NA | AF67: NA
A68: C1 | B68: 50 | C68: 16 - Identification Tiers | D68: 16 - Third party identification | E68: C1 4.1 | F68: Note finale retenue | G68: Assigned final rating | H68: La NOte finale Retenue (NOR) est la note attribuée au tiers en fin de processus de calcul, et validée par l'instance décisionnelle de l'entité RUN | I68: The assigned rating is the rating given to the external counterparty at the end of the calculation process, and approved by the decision-making body of the RUN entity | J68: ND | K68: ND | L68: NA | M68: Obligatoire | N68: Mandatory | O68: LC.0006 | P68: TA NM648 | Q68: La valeur par défaut étant ‘ND' Donnée sous responsabilité du RUN. | R68: The default value being ‘ND' Data owned by the «RUN». | S68: ALPHA | T68: NA | U68: NA | V68: 2 | W68: NA | X68: 40 | Y68: NA | Z68: NA | AA68: ANACREDIT | AB68: ND | AC68: N | AD68: NA | AE68: NA | AF68: NA
... A74: C1 | B74: 56 | C74: 16 - Identification Tiers | D74: 16 - Third party identification | E74: C1 4.20 | F74: Note après correctif groupe | G74: Rating following group adjustment | H74: Note après prise en compte du défaut et des facteurs d'alerte, l'éventuel appartenance à un groupe mais avant correctif pays | I74: Rating after factoring in of the default and warning factors, possible membership of a group but prior to country correction | J74: ND | K74: ND | L74: NA | M74: Obligatoire | N74: Mandatory | O74: LC.0006 | P74: TA NM648 | Q74: Obligatoire si la note (NOR) est renseignée et différente de 'ND' Donnée sous responsabilité du RUN | R74: Mandatory where the assigned rating is indicated and doesn't equal 'ND' Data owned by the «RUN» | S74: ALPHA | T74: NA | U74: NA | V74: 2 | W74: NA | X74: 40 | Y74: NA | Z74: NA | AA74: TIGRE | AB74: ND | AC74: N | AD74: NA | AE74: NA | AF74: NA
A75: C1 | B75: 57 | C75: NA | D75: NA | E75: C1 4.21 | F75: Filler | G75: Filler | H75: Zone libre | I75: Free zone | J75: NA | K75: NA | L75: NA | M75: NA | N75: NA | O75: NA | P75: NA | Q75: Laisser à vide | R75: Leave empty | S75: ALPHA | T75: NA | U75: NA | V75: 1 | W75: NA | X75: NA | Y75: NA | Z75: NA | AA75: NA | AB75: NA | AC75: N | AD75: NA | AE75: NA | AF75: NA
A76: C1 | B76: 58 | C76: 25 - Notation du tiers | D76: 25 - Third party rating | E76: C1 4.5 | F76: Grille modèle de notation | G76: Rating scale model | H76: Référence de la grille de notation utilisée pour la détermination de la note interne | I76: Reference code of the rating scale used to determine the internal rating | J76: ND | K76: ND | L76: NA | M76: Obligatoire | N76: Mandatory | O76: LC.0153 | P76: TA KVVGNTIE | Q76: Obligatoire si la note finale retenue (C1 4.1) <> ‘ND'. La Grille de notation doit être cohérente avec la Méthodologie de notation (C1 4.3) Donnée sous responsabilité du RUN | R76: Mandatory where the assigned rating (C1 4.1) <> ‘ND' The rating scale must be consistent with the rating methodology (C1 4.3) Data owned by the «RUN» | S76: ALPHA | T76: NA | U76: NA | V76: 46 | W76: NA | X76: 40 | Y76: NA | Z76: NA | AA76: TIGRE | AB76: ND | AC76: N | AD76: NA | AE76: NA | AF76: NA
A77: C1 | B77: 59 | C77: 16 - Identification Tiers | D77: 16 - Third party identification | E77: C1 4.6 | F77: Catégorie de contrepartie | G77: Category of counterparty | H77: Code de la catégorie de contrepartie du tiers. La catégorie de contrepartie est une segmentation détaillée des tiers utilisée pour déterminer les catégories d'exposition réglementaires | I77: Code of the external counterparty category. Counterparty categories represent a low level segmentation of external counterparties used to determine the regulatory exposure categories | J77: ND | K77: ND | L77: NA | M77: Obligatoire | N77: Mandatory | O77: LC.0009 | P77: TA NM201 | Q77: Le code renseigné doit correspondre au niveau de rattachement le plus fin Cette catégorie dérive du code activité interne, du chiffre d'affaires consolidé de référence (c) et de la catégorie juridique. La valeur dérivée est modifiable à dire d'expert Donnée sous responsabilité du RUN | R77: The code input must represent the lowest possible reporting level This category is derived from the internal business activity code, from the reference consolidated revenue (c) and the legal classification. The value calculated can be changed on the basis of expert opinion Data owned by the «RUN» | S77: ALPHA | T77: NA | U77: NA | V77: 5 | W77: NA | X77: 40 | Y77: NA | Z77: NA | AA77: ANACREDIT, CORFOU | AB77: ND | AC77: N | AD77: NA | AE77: NA | AF77: NA
A78: C1 | B78: 60 | C78: 31 - Paramètres bâlois | D78: 31 - Basel settings | E78: C1 4.7 | F78: Portefeuille Bâle Tiers | G78: Basel External Counterparty Portfolio | H78: Identifie le portefeuille de Bâle au niveau du tiers | I78: Identifies the Basel portfolio of the External Counterparty | J78: ND | K78: ND | L78: NA | M78: Obligatoire | N78: Mandatory | O78: LC.0010 | P78: TA NM205 | Q78: Segmentation plus agrégée que la catégorie de contrepartie permettant de faire le lien entre les catégories d'exposition réglementaire et les classes d'actifs de pondération Dérive de la catégorie de contrepartie, mais forçage possible Donnée sous responsabilité du RUN | R78: More highly aggregated segmentation than the counterparty category, making it possible to link regulatory exposure categories and asset classes for weighting purposes Derived from the counterparty category, but can be forced Data owned by the «RUN» | S78: ALPHA | T78: NA | U78: NA | V78: 3 | W78: NA | X78: 40 | Y78: NA | Z78: NA | AA78: ANACREDIT, CORFOU | AB78: ND | AC78: N | AD78: NA | AE78: NA | AF78: NA
A79: C1 | B79: 61 | C79: 16 - Identification Tiers | D79: 16 - Third party identification | E79: C1 4.8 | F79: Secteur d'activité | G79: Business sector | H79: Code du secteur d'activité du tiers traduisant son activité dominante quelle que soit sa nationalité | I79: Business sector code of the external counterparty, constituting its main business activity regardless of its nationality | J79: ND | K79: ND | L79: NA | M79: Obligatoire | N79: Mandatory | O79: LC.0011 | P79: TA NM199 | Q79: Le code renseigné correspond au niveau de rattachement le plus fin. Le secteur d'activité utilisé pour la notation doit être cohérent avec le code APE interne Donnée sous responsabilité du RUN | R79: The code input must represent the lowest possible reporting level. The business sector used for the rating must be consistent with the internal APE code Data owned by the «RUN» | S79: ALPHA | T79: NA | U79: NA | V79: 6 | W79: NA | X79: 40 | Y79: NA | Z79: NA | AA79: TIGRE | AB79: ND | AC79: N | AD79: NA | AE79: NA | AF79: NA
A80: C1 | B80: 62 | C80: NA | D80: NA | E80: C1 4.9 | F80: Filler | G80: Filler | H80: Zone libre | I80: Free zone | J80: NA | K80: NA | L80: NA | M80: NA | N80: NA | O80: NA | P80: NA | Q80: Laisser à vide | R80: Leave empty | S80: ALPHA | T80: NA | U80: NA | V80: 2 | W80: NA | X80: NA | Y80: NA | Z80: NA | AA80: NA | AB80: NA | AC80: N | AD80: NA | AE80: NA | AF80: NA
A81: C1 | B81: 63 | C81: 16 - Identification Tiers | D81: 16 - Third party identification | E81: C1 4.10 | F81: Norme locale de l'activité | G81: Local business regulations | H81: Norme locale de l'activité principale exercée | I81: Local regulations governing the main business activity | J81: ND | K81: ND | L81: NA | M81: Obligatoire | N81: Mandatory | O81: LC.0014 | P81: TA KVNORM | Q81: Obligatoire si l'activité dans la norme locale (C1 4.11) est renseignée Elle précise le référentiel local utilisé pour le code activité renseigné au champ suivant (C1 4.11) Donnée sous responsabilité du RUN | R81: Mandatory where business activity code under local regulations (C1 4.11) is indicated It specifies the local framework from which the business code input into the next field (C1 4.11) is drawn Data owned by the «RUN» | S81: ALPHA | T81: NA | U81: NA | V81: 1 | W81: NA | X81: 40 | Y81: NA | Z81: NA | AA81: ANACREDIT | AB81: ND | AC81: N | AD81: NA | AE81: NA | AF81: NA
A82: C1 | B82: 64 | C82: 16 - Identification Tiers | D82: 16 - Third party identification | E82: C1 4.11 | F82: Activité dans la norme locale | G82: Business activity code under local regulations | H82: Code de l'Activité économique dominante du tiers issue de la norme locale (ex. : Code APE – Activité Principale Exercée - tel qu'il est attribué par l'INSEE, i.e. le "code APE officiel") | I82: Code of the main business activity of the external counterparty under local regulations (e.g.: APE Code – Main Business Activity - as attributed by INSEE, i.e. the "official APE code") | J82: ND | K82: ND | L82: NA | M82: Obligatoire | N82: Mandatory | O82: LC.0123 | P82: RB NM160 | Q82: Code activité de l'activité principale exercée - Résidents en France : code APE 'officiel' de l'INSEE - Non-résidents en France : code activité selon la norme locale Obligatoire pour les résidents Francais: à renseigner avec le code NAF Donnée sous responsabilité du RUN | R82: Business activity code of the main business carried on - Resident in France: “Official” INSEE APE code - Non-resident in France: business activity code under local regulations Mandatory for French residents: input the NAF code Data owned by the «RUN» | S82: ALPHA | T82: NA | U82: NA | V82: 6 | W82: NA | X82: 40 | Y82: NA | Z82: NA | AA82: ANACREDIT | AB82: ND | AC82: N | AD82: NA | AE82: NA | AF82: NA
A83: C1 | B83: 65 | C83: 29 - Ratio | D83: 29 - Ratio | E83: C1 8.81 | F83: Indicateur ratio CET 1 >= 14% | G83: Indicator CET 1 ratio >= 14% | H83: Indique si le ratio de fonds propres de base de catégorie 1 de l'institution financière est égal ou supérieur à 14 %. | I83: Indicates whether the Common Equity Tier 1 capital ratio of the financial institution is equal to or greater than 14%. | J83: ND | K83: ND | L83: NA | M83: Obligatoire | N83: Mandatory | O83: LC.0507 | P83: TA Z8ICET14 | Q83: Indicateur en lien avec la notion du grade SCRA. Concerne les institutions financières. Se référer l'article 121 de la réglementation CRR3 | R83: Indicator related to the concept of SCRA grade. Only for financial institutions. Refer to Article 121 of the CRR3 Regulation | S83: ALPHA | T83: NA | U83: NA | V83: 1 | W83: NA | X83: 44 | Y83: NA | Z83: NA | AA83: CALCULS PRUDENTIELS | AB83: ND | AC83: N | AD83: NA | AE83: NA | AF83: NA
A84: C1 | B84: 66 | C84: 29 - Ratio | D84: 29 - Ratio | E84: C1 8.82 | F84: Indicateur Ratio de Levier supérieur ou égal à 5 % | G84: Indicator Leverage Ratio greater than or equal to 5 % | H84: Indique si le ratio de levier de l'institution financière est supérieur ou égal à 5%. | I84: Indicates if the leverage ratio of the financial institution is greater than or equal to 5%. | J84: ND | K84: ND | L84: NA | M84: Obligatoire | N84: Mandatory | O84: LC.0508 | P84: TA Z8IRLEV5 | Q84: Indicateur en lien avec la notion du grade SCRA. Concerne les institutions financières. Se référer l'article 121 de la réglementation CRR3 | R84: Indicator related to the concept of SCRA grade. Only for financial institutions. Refer to Article 121 of the CRR3 Regulation | S84: ALPHA | T84: NA | U84: NA | V84: 1 | W84: NA | X84: 44 | Y84: NA | Z84: NA | AA84: CALCULS PRUDENTIELS | AB84: ND | AC84: N | AD84: NA | AE84: NA | AF84: NA
A85: C1 | B85: 67 | C85: NA | D85: NA | E85: C1 4.13 | F85: Zone libre (Ex Statut de filiation) | G85: Free zone (ex-Subsidiary relationship) | H85: Indique si le tiers a des liens juridiques ou financiers avec une autre entité | I85: Indicates whether the external counterparty has legal or financial ties to another entity | J85: NA | K85: NA | L85: NA | M85: NA | N85: NA | O85: NA | P85: NA | Q85: NA | R85: NA | S85: NUM | T85: NA | U85: NA | V85: 1 | W85: NA | X85: NA | Y85: 43 | Z85: NA | AA85: NA | AB85: NA | AC85: N | AD85: NA | AE85: NA | AF85: NA
A86: C1 | B86: 68 | C86: 16 - Identification Tiers | D86: 16 - Third party identification | E86: C1 4.18 | F86: Indicateur Watch List | G86: Watch list indicator | H86: Indicateur qui permet d’identifier si le tiers est en WatchList (Alertes Précoces) | I86: Flag to identify whether the third party is in WatchList (Early Warnings) | J86: ND | K86: ND | L86: NA | M86: Obligatoire | N86: Mandatory | O86: LC.0526 | P86: TA Z8INWALI | Q86: NA | R86: NA | S86: ALPHA | T86: NA | U86: NA | V86: 1 | W86: NA | X86: 44 | Y86: NA | Z86: NA | AA86: OMP, PAP | AB86: ND | AC86: N | AD86: NA | AE86: NA | AF86: NA
A87: C1 | B87: 69 | C87: 16 - Identification Tiers | D87: 16 - Third party identification | E87: C1 4.23 | F87: Date d'entrée en Watch List | G87: Date of entry into the Watch List | H87: Date à laquelle le tiers est entré en WatchList (Alertes Précoces) | I87: Date the third party entered the WatchList (Early Warnings) | J87: ND | K87: ND | L87: NA | M87: Obligatoire | N87: Mandatory | O87: NA | P87: NA | Q87: NA | R87: NA | S87: DATE | T87: AAAAMMJJ | U87: YYYYMMDD | V87: 8 | W87: NA | X87: 44 | Y87: NA | Z87: NA | AA87: OMP, PAP | AB87: ND | AC87: N | AD87: NA | AE87: NA | AF87: NA
A88: C1 | B88: 70 | C88: 16 - Identification Tiers | D88: 16 - Third party identification | E88: C1 4.24 | F88: Date de sortie en Watch List | G88: Date of release in Watch list | H88: Date à laquelle le tiers est sorti de WatchList (Alertes Précoces) | I88: Date the third party exited WatchList (Early Warnings) | J88: ND | K88: ND | L88: NA | M88: Obligatoire | N88: Mandatory | O88: NA | P88: NA | Q88: NA | R88: NA | S88: DATE | T88: AAAAMMJJ | U88: YYYYMMDD | V88: 8 | W88: NA | X88: 44 | Y88: NA | Z88: NA | AA88: PAP | AB88: ND | AC88: N | AD88: NA | AE88: NA | AF88: NA
A89: C1 | B89: 71 | C89: 16 - Identification Tiers | D89: 16 - Third party identification | E89: C1 4.25 | F89: Motif d'entrée en Watch List | G89: Reason for entry in Watch List | H89: Motif pour lequel le tiers est entré en Watch List (Alertes Précoces) | I89: Reason the third party entered the Watch List (Early Warnings) | J89: ND | K89: ND | L89: NA | M89: Facultatif | N89: Optional | O89: LC.0527 | P89: RB Z8MOTIGE | Q89: NA | R89: NA | S89: ALPHA | T89: NA | U89: NA | V89: 2 | W89: NA | X89: 44 | Y89: NA | Z89: NA | AA89: PAP | AB89: ND | AC89: N | AD89: NA | AE89: NA | AF89: NA
A90: C1 | B90: 72 | C90: 16 - Identification Tiers | D90: 16 - Third party identification | E90: C1 4.26 | F90: Motif de sortie en Watch List | G90: Watch List Exit Pattern | H90: Motif pour lequel le tiers est sortie de Watch List (Alertes Précoces) | I90: Reason the third party is removed from Watch List (Early Warnings) | J90: ND | K90: ND | L90: NA | M90: Facultatif | N90: Optional | O90: LC.0527 | P90: TA Z8MOTIWL | Q90: NA | R90: NA | S90: ALPHA | T90: NA | U90: NA | V90: 5 | W90: NA | X90: 44 | Y90: NA | Z90: NA | AA90: PAP | AB90: ND | AC90: N | AD90: NA | AE90: NA | AF90: NA
A91: C1 | B91: 73 | C91: NA | D91: NA | E91: C1 4.17 | F91: Zone libre (Ex Type d'Acteur (Banque Assurance) | G91: Free zone (ex-Type of player (Bank Insurance)) | H91: Classification des tiers de portefeuille Bâle Banque ou Assurance en fonction du soutien de l'Etat Banque Centrale ou de l'importance de la position sur leur Marché | I91: Classification of external counterparties in the Basel Banking or Insurance portfolio on the basis of Government Central Bank backing or their standing in their Market | J91: NA | K91: NA | L91: NA | M91: NA | N91: NA | O91: NA | P91: NA | Q91: NA | R91: NA | S91: ALPHA | T91: NA | U91: NA | V91: 26 | W91: NA | X91: NA | Y91: 43 | Z91: NA | AA91: NA | AB91: NA | AC91: N | AD91: NA | AE91: NA | AF91: NA
A92: C1 | B92: 74 | C92: NA | D92: NA | E92: C1 4.99 | F92: Filler | G92: Filler | H92: Zone libre | I92: Free zone | J92: NA | K92: NA | L92: NA | M92: NA | N92: NA | O92: NA | P92: NA | Q92: Laisser à vide | R92: Leave empty | S92: ALPHA | T92: NA | U92: NA | V92: 2 | W92: NA | X92: NA | Y92: NA | Z92: NA | AA92: NA | AB92: NA | AC92: N | AD92: NA | AE92: NA | AF92: NA
A93: C1 | B93: 75 | C93: 16 - Identification Tiers | D93: 16 - Third party identification | E93: C1 5.1 | F93: Type de relation | G93: Type of relationship | H93: Définit le type de relation entre une contrepartie et un déclarant (client, garant, prospect….). Lorsque l'entité entretient avec une contrepartie des relations de plusieurs types (par exemple, la contrepartie est à la fois cliente de l'entité et l'émetteur de titres détenus par l'entité) elle déclare le type de relation du niveau le plus élevé | I93: Defines the type of relationship between a counterparty and a reporter (client, guarantor, prospect….). Where the entity has a number of different relationships with a counterparty (for example, the counterparty is both a client of the entity and the issuer of securities held by the entity) it declares the highest level relationship | J93: ND | K93: ND | L93: NA | M93: Obligatoire | N93: Mandatory | O93: LC.0018 | P93: TA KVRELA | Q93: La hiérarchie des types de relation est la suivante : C (client) > G (garant) E (émetteur) > D (Déposant) > S ( Sponsor ) etc. Devient obligatoire par défaut il sera forcé à ‘C' pour Client par le traducteur si non renseigné | R93: The types of relationship hierarchy is as follows: C (client) > G (guarantor) > I (issuer) > D (Depositor) > S (Sponsor) etc | S93: ALPHA | T93: NA | U93: NA | V93: 1 | W93: NA | X93: 40 | Y93: NA | Z93: NA | AA93: FEL, MREL | AB93: ND | AC93: N | AD93: NA | AE93: NA | AF93: NA
A94: C1 | B94: 76 | C94: 25 - Notation du tiers | D94: 25 - Third party rating | E94: C1 5.2 | F94: Chiffre d'Affaires utilisé pour la notation | G94: Revenue used for rating | H94: Chiffre d'Affaires utilisé pour la notation | I94: Revenue used for rating | J94: ND | K94: ND | L94: NA | M94: Obligatoire | N94: Mandatory | O94: NA | P94: NA | Q94: Obligatoire dès que le tiers est noté avec une NOR (C1 4.1) renseignée <> 'ND' Exprimé obligatoirement en EURO …. (unité euro) Donnée sous responsabilité du RUN | R94: Mandatory once an external counterparty is given an assigned rating (C1 4.1) <> 'ND' Must be denominated in EURO …. (euro units) Data owned by the «RUN» | S94: NUM | T94: NA | U94: NA | V94: 12 | W94: NA | X94: 40 | Y94: NA | Z94: NA | AA94: ANACREDIT | AB94: ND | AC94: N | AD94: NA | AE94: NA | AF94: NA
A95: C1 | B95: 77 | C95: 16 - Identification Tiers | D95: 16 - Third party identification | E95: C1 5.3 | F95: Indicateur Chiffre d'Affaires consolidé | G95: Consolidated turnover indicator | H95: Indique si le CA renseigné est établi sur une base consolidée | I95: Indicates whether the specified revenue is calculated on a consolidated basis | J95: ND | K95: ND | L95: NA | M95: Obligatoire | N95: Mandatory | O95: LC.0424 | P95: TA TMCACONS | Q95: Obligatoire si Chiffre d'affaires utilisé pour la notation (C1 5.2) est renseigné Donnée sous responsabilité du RUN | R95: Mandatory where revenue used for rating (C1 5.2) is indicated Data owned by the «RUN» | S95: ALPHA | T95: NA | U95: NA | V95: 1 | W95: NA | X95: 40 | Y95: NA | Z95: NA | AA95: TIGRE | AB95: ND | AC95: N | AD95: NA | AE95: NA | AF95: NA
A96: C1 | B96: 78 | C96: 16 - Identification Tiers | D96: 16 - Third party identification | E96: C1 5.4 | F96: Devise du Chiffre d'Affaires | G96: Currency of revenue | H96: Code de la devise d'expression du CA | I96: Code of the currency in which the revenue is denominated | J96: ND | K96: ND | L96: NA | M96: Obligatoire | N96: Mandatory | O96: LC.0005 | P96: TA NM253 | Q96: Obligatoire si Chiffre d'affaires utilisé pour la notation (C1 5.2) est renseigné Seule valeur autorisée = EUR Donnée sous responsabilité du RUN | R96: Mandatory where revenue used for rating (C1 5.2) is indicated Only permitted value = EUR Data owned by the «RUN» | S96: ALPHA | T96: NA | U96: NA | V96: 3 | W96: NA | X96: 40 | Y96: NA | Z96: NA | AA96: TIGRE | AB96: ND | AC96: N | AD96: NA | AE96: NA | AF96: NA
A97: C1 | B97: 79 | C97: 16 - Identification Tiers | D97: 16 - Third party identification | E97: C1 5.5 | F97: Année du Chiffre d'Affaires | G97: Financial year of revenue | H97: Année de l'exercice pour lequel le CA est fourni | I97: Financial year in which the revenue was generated | J97: ND | K97: ND | L97: NA | M97: Obligatoire | N97: Mandatory | O97: NA | P97: NA | Q97: Obligatoire si Chiffre d'affaires utilisé pour la notation (C1 5.2) est renseigné Format de la date 'AAAA' Donnée sous responsabilité du RUN | R97: Mandatory where revenue used for rating (C1 5.2) is indicated “YYYY” date format Data owned by the «RUN» | S97: NUM | T97: NA | U97: NA | V97: 4 | W97: NA | X97: 40 | Y97: NA | Z97: NA | AA97: TIGRE | AB97: ND | AC97: N | AD97: NA | AE97: NA | AF97: NA
A98: C1 | B98: 80 | C98: NA | D98: NA | E98: C1 5.6 | F98: Filler | G98: Filler | H98: Zone libre | I98: Free zone | J98: NA | K98: NA | L98: NA | M98: NA | N98: NA | O98: NA | P98: NA | Q98: Laisser à vide | R98: Leave empty | S98: NUM | T98: NA | U98: NA | V98: 1 | W98: NA | X98: NA | Y98: NA | Z98: NA | AA98: NA | AB98: NA | AC98: N | AD98: NA | AE98: NA | AF98: NA
A99: C1 | B99: 81 | C99: 16 - Identification Tiers | D99: 16 - Third party identification | E99: C1 8.1 | F99: Durée d'exercice | G99: Duration of financial year | H99: Durée d'exercice auquel se rapporte le chiffre d'affaires | I99: Duration of the financial year in which the revenue was generated | J99: ND | K99: ND | L99: NA | M99: Obligatoire | N99: Mandatory | O99: NA | P99: NA | Q99: Obligatoire si Chiffre d'affaires utilisé pour la notation (C1 5.2) est renseigné Format JJJ Donnée sous responsabilité du RUN | R99: Mandatory where revenue used for rating (C1 5.2) is indicated DDD format Data owned by the «RUN» | S99: NUM | T99: NA | U99: NA | V99: 3 | W99: NA | X99: 40 | Y99: NA | Z99: NA | AA99: TIGRE | AB99: ND | AC99: N | AD99: NA | AE99: NA | AF99: NA
A100: C1 | B100: 82 | C100: 16 - Identification Tiers | D100: 16 - Third party identification | E100: C1 8.2 | F100: Nature du chiffre d'affaires | G100: Nature of revenue | H100: Nature du chiffre d'affaires | I100: Nature of revenue | J100: ND | K100: ND | L100: NA | M100: Obligatoire | N100: Mandatory | O100: LC.0135 | P100: TA NM218 | Q100: Obligatoire si Chiffre d'affaires utilisé pour la notation (C1 5.2) est renseigné Précise si le chiffre d'affaires est prévisionnel, publié ou retraité Donnée sous responsabilité du RUN | R100: Mandatory where revenue used for rating (C1 5.2) is indicated It specifies whether revenue is forecast, published or restated Data owned by the «RUN» | S100: ALPHA | T100: NA | U100: NA | V100: 1 | W100: NA | X100: 40 | Y100: NA | Z100: NA | AA100: TIGRE | AB100: ND | AC100: N | AD100: NA | AE100: NA | AF100: NA
A101: C1 | B101: 83 | C101: NA | D101: NA | E101: C1 8.9 | F101: Zone libre (Ex Chiffre d'affaires retraité (IFRS) en unité d'euros | G101: Free zone (ex-Restated (IFRS) revenue in euro units) | H101: Chiffre d'affaires retraité (IFRS) en unite d'euros | I101: Restated (IFRS) revenue in euro units | J101: NA | K101: NA | L101: NA | M101: NA | N101: NA | O101: NA | P101: NA | Q101: NA | R101: NA | S101: NUM | T101: NA | U101: NA | V101: 12 | W101: NA | X101: NA | Y101: 43 | Z101: NA | AA101: NA | AB101: NA | AC101: N | AD101: NA | AE101: NA | AF101: NA
A102: C1 | B102: 84 | C102: 16 - Identification Tiers | D102: 16 - Third party identification | E102: C1 8.10 | F102: Montant de résultat net retraité en unité d'euros | G102: Amount of restated net income in euro units | H102: Résultat net retraité en unite d'euros | I102: Restated net income in euro units | J102: ND | K102: ND | L102: NA | M102: Obligatoire | N102: Mandatory | O102: NA | P102: NA | Q102: Obligatoire dès que le tiers est noté avec une NOR (C1 4.1) renseignée <> 'ND' Donnée sous responsabilité du RUN | R102: Mandatory once an external counterparty is given an assigned rating (C1 4.1) <> 'ND' Data owned by the «RUN» | S102: NUM | T102: 13 dont signe | U102: 13 including sign | V102: 13 | W102: NA | X102: 40 | Y102: NA | Z102: NA | AA102: TIGRE | AB102: ND | AC102: N | AD102: NA | AE102: NA | AF102: NA
A103: C1 | B103: 85 | C103: NA | D103: NA | E103: C1 99.98 | F103: Filler | G103: Filler | H103: Zone libre | I103: Free zone | J103: NA | K103: NA | L103: NA | M103: NA | N103: NA | O103: NA | P103: NA | Q103: Laisser à vide | R103: Leave empty | S103: ALPHA | T103: NA | U103: NA | V103: 1 | W103: NA | X103: NA | Y103: NA | Z103: NA | AA103: NA | AB103: NA | AC103: N | AD103: NA | AE103: NA | AF103: NA
A104: C1 | B104: 86 | C104: 16 - Identification Tiers | D104: 16 - Third party identification | E104: C1 8.3 | F104: Code APE interne | G104: Internal APE code | H104: Code APE interne | I104: Internal APE code | J104: ND | K104: ND | L104: NA | M104: Obligatoire | N104: Mandatory | O104: NA | P104: NA | Q104: Obligatoire, doit être valorisée par défaut avec le code APE officiel INSEE (C1 4.11) dans le cas d'un résident Il permet, à dire d'expert : 1- d'attribuer un code activité NAF différent du code APE officiel INSEE du tiers, quand celui-ci ne correspond pas à l'activité réelle (ex. : holding) 2- d'attribuer un code activité NAF à un tiers non résident. Cette opération à dire d'expert est dans ce cas obligatoire (en vue de la détermination du secteur d'activité, notamment) Donnée sous responsabilité du RUN | R104: Mandatory, must be indicated by default with the INSEE official APE code (C1 4.11) in the case of a resident It makes it possible, with expert support: 1- to assign a NAF business activity code that differs from the external counterparty's INSEE official APE code, when the latter doesn't reflect the actual business activity (e.g.: a holding company) 2- to assign a NAF business activity code to a non-resident external counterparty. This expert assessment is mandatory in this instance (in order to, in particular, determine the business sector) Data owned by the «RUN» | S104: ALPHA | T104: NA | U104: NA | V104: 6 | W104: NA | X104: 40 | Y104: NA | Z104: NA | AA104: ANACREDIT | AB104: ND | AC104: N | AD104: NA | AE104: NA | AF104: NA
A105: C1 | B105: 87 | C105: 16 - Identification Tiers | D105: 16 - Third party identification | E105: C1 8.4 | F105: Statut d'activité / inactivité du tiers | G105: Counterparty activity / inactivity status | H105: Permet de distinguer si le tiers possède une relation locale active ou inactive avec l'entité contributrice du flux | I105: Makes it possible to distinguish whether the external counterparty has an active or inactive local relationship with the entity contributing the flow | J105: ND | K105: ND | L105: NA | M105: Obligatoire | N105: Mandatory | O105: LC.0290 | P105: TA KVSACTI | Q105: La seule valeur admise est 'A' pour Actif | R105: The only permitted value is 'A' for Active | S105: ALPHA | T105: NA | U105: NA | V105: 1 | W105: NA | X105: 40 | Y105: NA | Z105: NA | AA105: TIGRE | AB105: ND | AC105: N | AD105: NA | AE105: NA | AF105: NA
A106: C1 | B106: 88 | C106: 16 - Identification Tiers | D106: 16 - Third party identification | E106: C1 8.5 | F106: Date du statut d'activité/Inactivité du tiers | G106: Date of change in activity status | H106: Date à laquelle le statut d'activité a évolué | I106: Date at which the trading status changed | J106: ND | K106: ND | L106: NA | M106: Obligatoire | N106: Mandatory | O106: NA | P106: NA | Q106: Ex. : Date de changement de statut | R106: E.g.: Date on which status changed | S106: DATE | T106: AAAAMMJJ | U106: YYYYMMDD | V106: 8 | W106: NA | X106: 40 | Y106: NA | Z106: NA | AA106: TIGRE | AB106: ND | AC106: N | AD106: NA | AE106: NA | AF106: NA
...

Sheet Ctrl cohérence-consistency ctr 
B2: Contrôles de cohérence | L2: Consistency controls
B4: Principe : Ces contrôles consistent à vérifier que la valeur portée par une donnée pivot est cohérente avec des données associées. Un contrôle de cohérence peut porter sur : · Une ou plusieurs données d’un même objet de collecte · Plusieurs données de plusieurs objets de collecte | L4: Principle: These controls are to ensure that the value of a pivot data is consistent with associated data. A consistency check may cover: ・ One or more data from the same data collection object ・ Several data from several data collection objects
B6: Périmètre d'application : - CRR Corporate - CRR Retail Agrégé - CRR Adapté | L6: Scope of application: - CRR Corporate - CRR Aggregated Retail - Adapted CRR
B8: Fonctionnement : - Contrôles exécutés en étape E4.4 des traitements ZP (après mise au modèle) - Contrôles paramétrés en score 6TA (non bloquant) - Les combinaisons de valeurs conformes sont précisées ci-dessous pour chaque contrôle sauf contrôle TC0C03 pour lequel sont précisées les combinaisons en anomalie. En dehors des combinaisons conformes, la Zone de Partage recensera une anomalie. | L8: Functions: - Checks performed in step E4.4 of ZP treatments (after the model has been set) - Controls configured in scoring 6TA (non-blocking) - The combinations of conforming values are specified below for each control except control TC0C03 for which the combinations in anomaly are specified. Apart from the compliant combinations, the Sharing Zone will identify an anomaly.
B10: Légende : | L10: Legend:
B11: * : Quelle que soit la valeur | L11: * Whatever the value
B12: Donnée pivot | L12: Pivot data
B13: Donnée complémentaire | L13: Additional data
B17: Contrôle TC0C01 : Cohérence Tiers en défaut/Engagement douteux | L17: Control TC0C01 : Third party consistency in default/doubtful Funds in use
B18: Description du contrôle | D18: Périmètre | L18: Description of control | N18: Scope
B19: Ce contrôle consiste à vérifier la convergence entre les douteux (de niveau engagement) et les défauts (de niveau client) | D19: Grande Clientèle et Clientèle de détail en méthode IRB | L19: This control consists in checking the convergence between doubtful (funds in use-level) and flawed (customer-level) assets | N19: Corporate customers and Retail customers in IRB method
B21: P1/P2 | L21: P1/P2
C23: control entry point | M23: control entry point
B24: Identifiant de l'engagement (1.11 (P1), 1.11 (P2)) | C24: Méthodologie Bâloise (P1 1.1, P2 1.1) | D24: Note Interne Retenue (C1 4.1) | E24: Date d'entrée en défaut (C1 4.15) | F24: Indicateur 'Engagement Douteux' (P1 5.2, P2 5.2) | G24: Date de passage en 'Engagement douteux' (P1 5.3, P2 5.3) | L24: Commitment ID (1.11 (P1), 1.11 (P2)) | M24: Basel Methodology (P1 1.1, P2 1.1) | N24: Internal Rating Assigned (C1 4.1) | O24: Default Entry Date (C1 4.15) | P24: Doubtful Commitment' Indicator (P1 5.2, P2 5.2) | Q24: Date of Transfer to 'Doubtful Commitment' (P1 5.3, P2 5.3)
B25: * | C25: 'IRB A' or 'IRB F' | D25: F or Z | E25: < Date d'arrêté - 1 mois | F25: Y | G25: (non vide) | L25: * | M25: 'IRB A' or 'IRB F' | N25: F or Z | O25: < Date d'arrêté - 1 mois | P25: Y | Q25: (non vide)
C27: control entry point | M27: control entry point
B28: Indicateur 'Engagement Douteux' (P1 5.2, P2 5.2) | C28: Méthodologie Bâloise (P1 1.1, P2 1.1) | D28: Date de passage en 'Engagement douteux' (P1 5.3, P2 5.3) | E28: Note Interne Retenue (C1 4.1) | F28: Date d'entrée en défaut (C1 4.15) | L28: Doubtful Commitment' Indicator (P1 5.2, P2 5.2) | M28: Basel Methodology (P1 1.1, P2 1.1) | N28: Date of Transfer to 'Doubtful Commitment' (P1 5.3, P2 5.3) | O28: Internal Rating Assigned (C1 4.1) | P28: Default Entry Date (C1 4.15)
B29: Y | C29: 'IRB A' or 'IRB F' | D29: < Date d'arrêté - 1 mois | E29: F or Z | F29: (non vide) | L29: Y | M29: 'IRB A' or 'IRB F' | N29: < Date d'arrêté - 1 mois | O29: F or Z | P29: (non vide)
B33: Contrôle TC0C03 : Cohérence Données de détermination de la CAP | L33: Control TC0C03 : Consistency CAP determination data
B34: Description du contrôle | D34: Périmètre | L34: Description of control | N34: Scope
B35: Le contrôle consiste à vérifier la cohérence entre les données qui permettent de déterminer la Classe d’Actifs de Pondération (CAP) | D35: Grande Clientèle et Clientèle de détail | L35: The control consists in checking the consistency between the data used to determine the Risk Weighting Asset Class () | N35: Corporate customers and Retail customers
B37: P1/P2 | L37: P1/P2
B39: Portefeuille Bâle Opération (P1 2.18, P2 2.18) | C39: Portefeuille Bâle Tiers (C1 4.7) | D39: Catégorie de contrepartie (C1 4.6) | E39: Méthodologie Bâloise (P1 1.1, P2 1.1) | L39: Basel Portfolio Operation (P1 2.18, P2 2.18) | M39: Basel Portfolio Counterparty (C1 4.7) | N39: Counterparty Category (C1 4.6) | O39: Basel Methodology (P1 1.1, P2 1.1)
B40: 061, 062, 063, 064 , 065, 070, 077 or 090 | C40: 022, 030 or 050 | D40: * except PCG10, PC21, PCG22, PCG23, PCG24 | E40: IRB A, IRB F or STD | L40: 061, 062, 063, 064 , 065, 070, 077 or 090 | M40: 022, 030 or 050 | N40: * except PCG10, PC21, PCG22, PCG23, PCG24 | O40: IRB A, IRB F or STD
B41: 061, 062, 063, 064 , 065, 070, 077 or 090 | C41: 040 | D41: * except PCG10, PC21, PCG22, PCG23, PCG24 | E41: IRB F or STD | L41: 061, 062, 063, 064 , 065, 070, 077 or 090 | M41: 040 | N41: * except PCG10, PC21, PCG22, PCG23, PCG24 | O41: IRB F or STD
B42: 080 or 081 | C42: 022, 030, 040 or 050 | D42: * except PCG10, PC21, PCG22, PCG23, PCG24 | E42: STD | L42: 080 or 081 | M42: 022, 030, 040 or 050 | N42: * except PCG10, PC21, PCG22, PCG23, PCG24 | O42: STD
B43: 900 | C43: 040 | D43: ACG12, ACG13, ACG20, ACG31, ACG32, ACG42, BCG23, BCG24, BCG25, BCG26, BCG27, BCG28, BCG29, FCG11, FCG12, FCG13, FCG21 , FCG24 or SCG10 | E43: IRB F or STD | L43: 900 | M43: 040 | N43: ACG12, ACG13, ACG20, ACG31, ACG32, ACG42, BCG23, BCG24, BCG25, BCG26, BCG27, BCG28, BCG29, FCG11, FCG12, FCG13, FCG21 , FCG24 or SCG10 | O43: IRB F or STD
B44: 900 | C44: 050 | D44: ACG11, ACG12, ACG13, ACG20, SCG10, SCG11 or BCG10 | E44: IRB A, IRB F or STD | L44: 900 | M44: 050 | N44: ACG11, ACG12, ACG13, ACG20, SCG10, SCG11 or BCG10 | O44: IRB A, IRB F or STD
B45: 900 | C45: 030 | D45: SCG20, ECG11, ECG13, ECG21, ECG31, ECG41, FCG22, FCG23, FCG31, FCG32, FCG33, ICG11, ICG12, ICG21, ICG22, ICG23, ICG30, MCG11, MCG12, MCG21, MCG22, MCG31, MCG32, MCG33, MCG34, MCG35, MCG36, MCG41, MCG42, MCG43, MCG44 or MCG60 | E45: IRB A, IRB F or STD | L45: 900 | M45: 030 | N45: SCG20, ECG11, ECG13, ECG21, ECG31, ECG41, FCG22, FCG23, FCG31, FCG32, FCG33, ICG11, ICG12, ICG21, ICG22, ICG23, ICG30, MCG11, MCG12, MCG21, MCG22, MCG31, MCG32, MCG33, MCG34, MCG35, MCG36, MCG41, MCG42, MCG43, MCG44 or MCG60 | O45: IRB A, IRB F or STD
B46: 900 | C46: 022 | D46: ECG12, ECG32 or ECG42 | E46: IRB A, IRB F or STD | L46: 900 | M46: 022 | N46: ECG12, ECG32 or ECG42 | O46: IRB A, IRB F or STD
B49: Contrôle TC0C11 : Cohérence NATO/Domaine CRR | L49: Control TC0C11 : NATO/CRR domain consistency
B50: Description du contrôle | D50: Périmètre | L50: Description of control | N50: Scope
B51: Ce contrôle consiste à vérifier l’utilisation de la NATO avec les domaines du CRR pour chacun des flux CRR transmis | D51: Grande Clientèle, Clientèle de détail et Alimentation adaptée | L51: This control consists in checking the use of the NATO with the CRR domains for each of the CRR flows transmitted | N51: Corporate customers, Retail customers and Adapted food
B53: P1/P2/M1 | L53: P1/P2/M1
C55: Nature d'Opération (P1 2.29, P2 2.29, M1 2.3) | D55: Objet de collecte | M55: NATure of funds in use transaction (P1 2.29, P2 2.29, M1 2.3) | N55: Business object
B56: P1 2.29 | C56: NA010, NA011, NA012, NA020, NA021, NA022, NA300, NA311, NA312, NA321, NA322, NA323, NA330, NA341, NA342, NA343, NA344, NA350, NA361, NA362, NA363, NA364, NA365, NA366, NA367, NA368, NA369, NA370, NA371, NAT41, NAT42, NAT43, NAT44, NAT06, NAT07, NA100, NA101, NA102 | D56: P1 | L56: P1 2.29 | M56: NA010, NA011, NA012, NA020, NA021, NA022, NA300, NA311, NA312, NA321, NA322, NA323, NA330, NA341, NA342, NA343, NA344, NA350, NA361, NA362, NA363, NA364, NA365, NA366, NA367, NA368, NA369, NA370, NA371, NAT41, NAT42, NAT43, NAT44, NAT06, NAT07, NA100, NA101, NA102 | N56: P1
B57: P2 2.29 | C57: NAT06, NAT07 | D57: P2 | L57: P2 2.29 | M57: NAT06, NAT07 | N57: P2
B58: M1 2.3 | C58: NAT81, NAT82, NAT83, NAT84, NAT85 | D58: M1 | L58: M1 2.3 | M58: NAT81, NAT82, NAT83, NAT84, NAT85 | N58: M1
B63: Contrôle TC0C14 : Cohérence Portefeuille Bâle Tiers / Domaine CRRC | L63: Control TC0C14 : Third Parties Basel Portfolio / CRRC perimeter consistency
B64: Description du contrôle | D64: Périmètre | L64: Description of control | N64: Scope
B65: Le contrôle consiste à vérifier la cohérence de l'utilisation du Portefeuille Bâle Tiers vis-à-vis des domaines du CRR | D65: Grande Clientèle et Clientèle de détail | L65: The control consists in checking that the Basel Portfolio of Third Parties is consistent with the CRR fields | N65: Corporate customers and Retail customers
B67: P1/P2/M1 | L67: P1/P2/M1
B69: Identifiant de l'objet (1.11 (P1), 1.11 (P2), 1.8 (M1)) | C69: Objet de collecte | D69: Portefeuille Bâle Tiers (C1 4.7) | L69: Funds in use ID (1.11 (P1), 1.11 (P2), 1.8 (M1)) | M69: Business object | N69: Basel Portfolio of Third Parties (C1 4.7)
B70: * | C70: P1, P2, M1 | D70: 022, 030, 040, 050 | L70: * | M70: P1, P2, M1 | N70: 022, 030, 040, 050
B74: Contrôle TC0C16 : Cohérence Crédit-bail | L74: Control TC0C16 : Credit-lease consistency
B75: Description du contrôle | D75: Périmètre | L75: Description of control | N75: Scope
B76: Le contrôle consiste à s’assurer que la saisie de certains champs a bien été effectuée pour les expositions du portefeuille CREDIT BAIL | D76: Grande Clientèle, Clientèle de détail et Standard en Alimentation adaptée | L76: The control consists in ensuring that certain fields have been entered for exposures of the CREDIT BAIL portfolio | N76: Corporate customers, Retail Customers and Standard in Adapted Feeding
B78: P1 | L78: P1
B80: Achat en fin de contrat du bien loué (P1 3.45) | C80: Type de risque (P1 2.0) | D80: Usage du bien immobilier financé (P1 8.13) | E80: Valeur estimée en fin de période du bien loué (P1 5.19) | F80: Devise de la valeur estimée en fin de période du bien loué (P1 5.20) | G80: Valeur hypothécaire du bien immobilier loué à la date d'évaluation (P1 3.42) | H80: Devise de la valeur hypothécaire du bien immobilier loué à la date d'évaluation (P1 3.43) | I80: Valeur de marché du bien immobilier loué à la dernière date d'évaluation (P1 3.40) | J80: Devise de la valeur de marché du bien immobilier loué à la date d'évaluation (P1 3.41) | L80: Purchase at the end of the lease of the leased property (P1 3.45) | M80: Risk type (P1 2.0) | N80: Use of real estate (P1 8.13) | O80: Estimated value at the end of the period of the leased property (P1 5.19) | P80: Currency of the estimated value at the end of the period of the leased property (P1 5.20) | Q80: Mortgage value of leased real estate at valuation date (P1 3.42) | R80: Currency of the mortgage value of the leased property on the valuation date (P1 3.43) | S80: Market value|fair value of leased real estate at the latest valuation date (P1 3.40) | T80: Currency of the market value|fair value of leased real estate at valuation date (P1 3.41)
B81: 1 | C81: TRE502 | D81: 1 | E81: ≠ 0 | F81: (Non vide) | G81: ≠ 0 | H81: (Non vide) | I81: ≠ 0 | J81: (Non vide) | L81: 1 | M81: TRE502 | N81: 1 | O81: ≠ 0 | P81: (Non vide) | Q81: ≠ 0 | R81: (Non vide) | S81: ≠ 0 | T81: (Non vide)
B82: 2 | C82: TRE502 | D82: 1 | E82: * | F82: * | G82: ≠ 0 | H82: (Non vide) | I82: ≠ 0 | J82: (Non vide) | L82: 2 | M82: TRE502 | N82: 1 | O82: * | P82: * | Q82: ≠ 0 | R82: (Non vide) | S82: ≠ 0 | T82: (Non vide)
B83: 1 | C83: TRE502 | D83: 2 | E83: ≠ 0 | F83: (Non vide) | G83: * | H83: * | I83: ≠ 0 | J83: (Non vide) | L83: 1 | M83: TRE502 | N83: 2 | O83: ≠ 0 | P83: (Non vide) | Q83: * | R83: * | S83: ≠ 0 | T83: (Non vide)
B84: 2 | C84: TRE502 | D84: 2 | E84: * | F84: * | G84: * | H84: * | I84: ≠ 0 | J84: (Non vide) | L84: 2 | M84: TRE502 | N84: 2 | O84: * | P84: * | Q84: * | R84: * | S84: ≠ 0 | T84: (Non vide)
B85: 1 | C85: TRE501, TRE503, TRE509 | D85: * | E85: ≠ 0 | F85: (Non vide) | G85: * | H85: * | I85: * | J85: * | L85: 1 | M85: TRE501, TRE503, TRE509 | N85: * | O85: ≠ 0 | P85: (Non vide) | Q85: * | R85: * | S85: * | T85: *
B90: Contrôle TC0C17 : Cohérence Type de risque et données liées | L90: Control TC0C17 : Consistency risk type and related data
B91: Description du contrôle | D91: Périmètre | L91: Description of control | N91: Scope
B92: Ce contrôle consiste à vérifier la cohérence entre la donnée Type de risque et l'utilisation de certaines données risque pour chacun des flux CRR transmis | D92: Grande Clientèle et Clientèle de détail | L92: This control consists in checking the consistency between the risk Type data and the use of certain data risk for each CRR flow transmitted | N92: Corporate customers and Retail customers
B94: P1 | L94: P1
B96: Portefeuille Bâle Opération (P1 2.18, P2 2.18) | C96: Objet de collecte | D96: Type de risque (P1 2.0, P2 2.0) | E96: Méthodologie Bâloise (P1 1.1, P2 1.1) | F96: Portefeuille de booking / Intention de Gestion (P1 2.4, P2 2.4) | G96: NATure d'Opération (P1 2.29, P2 2.29) | H96: Nature du Sous Jacent (P1 12.1) | L96: Basel Portfolio Operation (P1 2.18, P2 2.18) | M96: Business object | N96: Risk type (P1 2.0, P2 2.0) | O96: Basel methodology (P1 1.1, P2 1.1) | P96: Booking portfolio / Management intention (P1 2.4, P2 2.4) | Q96: NATure of funds in use transaction (P1 2.29, P2 2.29) | R96: Nature of the Underlying (P1 12.1)
B97: 080 | C97: P1 | D97: EQU101 | E97: STD | F97: B | G97: NA300, NA311, NA312, NA321, NA322, NA323, NA341, NA342, NA343, NA344, NA350 | H97: 01, 02, 03 ou 98 | L97: 080 | M97: P1 | N97: EQU101 | O97: STD | P97: B | Q97: NA300, NA311, NA312, NA321, NA322, NA323, NA341, NA342, NA343, NA344, NA350 | R97: 01, 02, 03 ou 98
B98: * | C98: P1 | D98: EQU101 | E98: RM | F98: T | G98: NA300, NA311, NA312, NA321, NA322, NA323, NA341, NA342, NA343, NA344, NA350 | H98: 01 | L98: * | M98: P1 | N98: EQU101 | O98: RM | P98: T | Q98: NA300, NA311, NA312, NA321, NA322, NA323, NA341, NA342, NA343, NA344, NA350 | R98: 01
B99: 080 | C99: P1 | D99: EQU201 | E99: STD | F99: B | G99: NA323, NA350 | H99: * | L99: 080 | M99: P1 | N99: EQU201 | O99: STD | P99: B | Q99: NA323, NA350 | R99: *
B100: 900 | C100: P1 | D100: TRE100 | E100: STD | F100: B | G100: NA011 ou NA012 | H100: * | L100: 900 | M100: P1 | N100: TRE100 | O100: STD | P100: B | Q100: NA011 ou NA012 | R100: *
B101: 900 | C101: P1 | D101: TRE100 | E101: IRB F | F101: B | G101: NA010 | H101: * | L101: 900 | M101: P1 | N101: TRE100 | O101: IRB F | P101: B | Q101: NA010 | R101: *
B102: 900 | C102: P2 | D102: TRE100 | E102: IRB F ou STD | F102: B | G102: NAT07 | H102: * | L102: 900 | M102: P2 | N102: TRE100 | O102: IRB F ou STD | P102: B | Q102: NAT07 | R102: *
B103: 080 | C103: P1 | D103: TRE405 ou TRE406 | E103: STD | F103: B | G103: NA361, NA363, NA364, NA365, NA367, NA368, NA369, NA370, NA371 | H103: * | L103: 080 | M103: P1 | N103: TRE405 ou TRE406 | O103: STD | P103: B | Q103: NA361, NA363, NA364, NA365, NA367, NA368, NA369, NA370, NA371 | R103: *
B104: 900, 070 ou 06* | C104: P1 | D104: TRE2*, TRE3* ou TRE4* | E104: IRB A ou IRB F | F104: B | G104: NA010 ou NA020 | H104: * | L104: 900, 070 ou 06* | M104: P1 | N104: TRE2*, TRE3* ou TRE4* | O104: IRB A ou IRB F | P104: B | Q104: NA010 ou NA020 | R104: *
B105: 900, 070 ou 06* | C105: P1 | D105: TRE2*, TRE3* ou TRE4* | E105: STD | F105: B | G105: NA011 ou NA012 ou NA021 ou NA022 | H105: * | L105: 900, 070 ou 06* | M105: P1 | N105: TRE2*, TRE3* ou TRE4* | O105: STD | P105: B | Q105: NA011 ou NA012 ou NA021 ou NA022 | R105: *
B106: 900, 070 ou 06* | C106: P2 | D106: TRE2*, TRE3* ou TRE4* | E106: IRB A ou IRB F ou STD | F106: B | G106: NAT07 | H106: * | L106: 900, 070 ou 06* | M106: P2 | N106: TRE2*, TRE3* ou TRE4* | O106: IRB A ou IRB F ou STD | P106: B | Q106: NAT07 | R106: *
B107: 900 ou 06* | C107: P1 | D107: TRE5* | E107: IRB A ou IRB F | F107: B | G107: NA010 ou NA020 | H107: * | L107: 900 ou 06* | M107: P1 | N107: TRE5* | O107: IRB A ou IRB F | P107: B | Q107: NA010 ou NA020 | R107: *
B108: 900 ou 06* | C108: P1 | D108: TRE5* | E108: STD | F108: B | G108: NA011 ou NA012 ou NA021 ou NA022 | H108: * | L108: 900 ou 06* | M108: P1 | N108: TRE5* | O108: STD | P108: B | Q108: NA011 ou NA012 ou NA021 ou NA022 | R108: *
B109: 900 ou 06* | C109: P2 | D109: TRE5* | E109: IRB A ou IRB F ou STD | F109: B | G109: NAT07 | H109: * | L109: 900 ou 06* | M109: P2 | N109: TRE5* | O109: IRB A ou IRB F ou STD | P109: B | Q109: NAT07 | R109: *
B110: 900 ou 06* | C110: P1 | D110: SIG101, SIG102, SIG103 ou SIG104 | E110: IRB A ou IRB F ou STD | F110: B | G110: NAT07 | H110: * | L110: 900 ou 06* | M110: P1 | N110: SIG101, SIG102, SIG103 ou SIG104 | O110: IRB A ou IRB F ou STD | P110: B | Q110: NAT07 | R110: *
B111: 900 ou 06* | C111: P1 | D111: SIG105, SIG106 ou SIG107 | E111: IRB A ou IRB F ou STD | F111: B | G111: NAT06 | H111: * | L111: 900 ou 06* | M111: P1 | N111: SIG105, SIG106 ou SIG107 | O111: IRB A ou IRB F ou STD | P111: B | Q111: NAT06 | R111: *
B112: 900, 070 ou 06* | C112: P1 | D112: SIG2* ou SIG3* | E112: IRB A ou IRB F ou STD | F112: B | G112: NAT06 | H112: * | L112: 900, 070 ou 06* | M112: P1 | N112: SIG2* ou SIG3* | O112: IRB A ou IRB F ou STD | P112: B | Q112: NAT06 | R112: *
B113: 900 ou 06* | C113: P2 | D113: SIG101, SIG102, SIG103 ou SIG104 | E113: IRB A ou IRB F ou STD | F113: B | G113: NAT07 | H113: * | L113: 900 ou 06* | M113: P2 | N113: SIG101, SIG102, SIG103 ou SIG104 | O113: IRB A ou IRB F ou STD | P113: B | Q113: NAT07 | R113: *
... B124: 081 | C124: P1 | D124: ISS200 ou ISS300 | E124: STD | F124: B | G124: NA330 | H124: 12, 13, 14, 15, 16 ou 17 | L124: 081 | M124: P1 | N124: ISS200 ou ISS300 | O124: STD | P124: B | Q124: NA330 | R124: 12, 13, 14, 15, 16 ou 17
B128: Contrôle TC0C22 : Cohérence Nature de la dépréciation/Type de risque | L128: Control TC0C22 : Consistency Type of impairment/Type of risk
B129: Description du contrôle | D129: Périmètre | L129: Description of control | N129: Scope
B130: Le contrôle consiste à vérifier que si la nature de la dépréciation est une décote alors l’exposition associée est une opération de trésorerie (hors opérations de crédit-bail) ou un titre de créance durablement déprécié | D130: Grande Clientèle et et Clientèle de détail | L130: The control consists in checking that if the nature of the impairment is a discount then the associated exposure is a cash flow transaction (excl. credit-lease transactions) or a sustainably impaired debt instrument | N130: LARGE CUSTOMERS and Retail customers
B133: P9 | L133: P9
B135: Nature de la dépréciation (P9 2.3) | C135: Type de risque (P1 2.0) | L135: Nature of impairment (P9 2.3) | M135: Risk type (P1 2.0)
B136: D | C136: TRE* sauf TRE5*/TRE203/TRE205/TRE206/TRE207, ISS200 ou ISS300 | L136: D | M136: TRE* sauf TRE5*/TRE203/TRE205/TRE206/TRE207, ISS200 ou ISS300
B140: Contrôle TC0C25 : Cohérence Portefeuille Bâle Tiers sur NOSTRI & LORI | L140: Control TC0C25 : Basel Portfolio compliance of Third Parties on NOSTRI & LORI
B141: Description du contrôle | D141: Périmètre | L141: Description of control | N141: Scope
B142: Le contrôle consiste à vérifier que pour les opérations de NOSTRI et LORI, le tiers en risque soit bien un établissement, ou un souverain | D142: Grande Clientèle | L142: The control consists in checking that for NOSTRI and LORI operations, the third party in risk is a institution, or a sovereign | N142: LARGE CUSTOMERS
B144: Type de risque (P1 2.0) | C144: Portefeuille Bâle Tiers (C1 4.7) | L144: Risk type (P1 2.0) | M144: Basel Portfolio of Third Parties (C1 4.7)
B145: TRE100 | C145: 040 ou 050 | L145: TRE100 | M145: 040 or 050
B149: Contrôle TC0C26 : Cohérence NATO/Engagement douteux en STD | L149: Control TC0C26 : NATO/doubtful Funds in use consistency in STD
B150: Description du contrôle | D150: Périmètre | L150: Description of control | N150: Scope
B151: Le contrôle consiste à vérifier que la NATure d’Opération dans laquelle l’encours a été classé est cohérente avec le caractère douteux/non douteux de l’encours traité en méthode Standard STD | D151: Grande Clientèle, Clientèle de détail et Alimentation adaptée, en méthode Standard | L151: The control consists in checking that the NATure of the operation in which the outstanding has been classified is consistent with the doubtful/undoubted nature of the outstanding treated in the STD standard method | N151: Corporate customers, Retail customers and appropriate food, using the Standard method
B154: P1/P2 | L154: P1/P2
B156: NATure d'Opération de l'engagement (P1 2.29, P2 2.29) | C156: Indicateur 'Engagement Douteux' (P1 5.2, P2 5.2) | L156: NATure of funds in use transaction (P1 2.29, P2 2.29) | M156: Doubtful Funds in use' indicator (P1 5.2, P2 5.2)
B157: NA011, NA021, NA101 | C157: N | L157: NA011, NA021, NA101 | M157: N
B158: NA012, NA022, NA102 | C158: Y | L158: NA012, NA022, NA102 | M158: Y
B162: Contrôle TC0C27 : Cohérence Forbeance/indicateur créance performante | L162: Control TC0C27 : Forbeance consistency/performing debt indicator
B163: Description du contrôle | D163: Périmètre | L163: Description of control | N163: Scope
B164: Le contrôle consiste à vérifier la cohérence des données forbearance, de l’indicateur de performance de la créance et de l’indicateur engagement douteux | D164: Grande Clientèle et Clientèle de détail | L164: The control consists in checking the consistency of the forbearance data, of the performance indicator of the doubtful loan and funds in use indicator | N164: LARGE CUSTOMERS and Retail customers
B166: P1/P2 | L166: P1/P2
B168: Statut du crédit (P1 21.5, P2 21.5) | C168: Indicateur créance performante (P1 21.6, P2 21.6) | D168: Nature contextuelle évènement de crédit (P1 21.4, P2 21.4) | E168: Indicateur 'Engagement Douteux' (P1 5.2, P2 5.2) | L168: Credit status (P1 21.5, P2 21.5) | M168: Performance debt indicator (P1 21.6, P2 21.6) | N168: Contextual nature of credit event (P1 21.4, P2 21.4) | O168: Doubtful Funds in use' indicator (P1 5.2, P2 5.2)
...
