Workbook
Name aaaa: #REF!
Name aaaa: #REF!
Name aaaaa: #REF!
Name aaaaa: #REF!
Name anomalies: #REF!
Name anomalies: #REF!
Name CAP_01__02__03__04__Clientèle_de_détail___Pas_de_données_complémentaires_obligatoires_associées_à_ces_CAP__Les_expositions_sur_la_Clientèle_de_détail_sont_pondérées_à_75_.: #REF!
Name CAP_01__02__03__04__Clientèle_de_détail___Pas_de_données_complémentaires_obligatoires_associées_à_ces_CAP__Les_expositions_sur_la_Clientèle_de_détail_sont_pondérées_à_75_.: #REF!
Name CAP_de_l_exposition: #REF!
Name CAP_de_l_exposition: #REF!
Name CAPtest: '[1]A1 Degraded Data Entry'!#REF!
Name CAPtest: '[1]A1 Degraded Data Entry'!#REF!
Name Groupe_caractéristiques: #REF!
Name Groupe_caractéristiques: #REF!
Name Groupe_caractéristiques: #REF!
Name Méthodo_CAP: #REF!
Name Méthodo_CAP: #REF!
Name Méthodo_Conditions_réglementaires: #REF!
Name Méthodo_Conditions_réglementaires: #REF!
Name Méthodo_Crédit_bail: #REF!
Name Méthodo_Crédit_bail: #REF!
Name Méthodo_DeterminationCAP: #REF!
Name Méthodo_DeterminationCAP: #REF!
Name Méthodo_douteux_impayé: #REF!
Name Méthodo_douteux_impayé: #REF!
Name Méthodo_engagement: #REF!
Name Méthodo_engagement: #REF!
Name Méthodo_impayé: #REF!
Name Méthodo_impayé: #REF!
Name Méthodo_indicateur: #REF!
Name Méthodo_indicateur: #REF!
Name Méthodo_indicateur_couverture: [2]Méthodologie!#REF!
Name Méthodo_indicateur_couverture: [2]Méthodologie!#REF!
Name Méthodo_indicateur_couverture: [2]Méthodologie!#REF!
Name Méthodo_indicateur_couverture: [2]Méthodologie!#REF!
Name Méthodo_Montants: #REF!
Name Méthodo_Montants: #REF!
Name Méthodo_NATO: #REF!
Name Méthodo_NATO: #REF!
Name Méthodo_PNU: #REF!
Name Méthodo_PNU: #REF!
Name Méthodo_Pond_pref: #REF!
Name Méthodo_Pond_pref: #REF!
Name méthodo_provisions: #REF!
Name méthodo_provisions: #REF!
Name Méthodo_sûretés: #REF!
Name Méthodo_sûretés: #REF!
Name Méthodo_Tiers_Agrégat: #REF!
Name Méthodo_Tiers_Agrégat: #REF!
Name Méthodo_usage_bien_immo: #REF!
Name Méthodo_usage_bien_immo: #REF!
Name Objets: '[3]Liste des objets'!$A:$A
Name Règles_corr: #REF!
Name Règles_corr: #REF!
Name test: #REF!
Name test: #REF!
Name test: #REF!
Name Tiers_Agrégat: #REF!
Name Tiers_Agrégat: #REF!
Name Toto: #REF!

Sheet Modifications
A1: Modifications
H2: Nombre de contrôles par type et sévérité
A3: Emetteur / Issuer | C3: Crédit Agricole SA : Programme Convergence Finances Risques (Crédit Agricole SA/FIG/DOP/CFR) | H3: 7 | I3: 6 | J3: 5 | K3: Mix | L3: total
A4: Date de diffusion / Publication date | C4: Lorsque cette date est renseignée, cela signifie que la notice est publiée dans https://service.ca-mocca.com/maia-collab/CFR/SitePages/Notices.aspx qui reprend l'ensemble des versions publiées. | G4: Présence | H4: =COUNTIF('A1 Alimentation Adaptée'!$AP$4:$AP$121,$H$3) -> 30 | I4: =COUNTIF('A1 Alimentation Adaptée'!$AP$4:$AP$121,$I$3) -> 26 | J4: =COUNTIF('A1 Alimentation Adaptée'!$AP$4:$AP$121,$J$3) -> 0 | K4: =L4-SUM(H4:J4) -> 2 | L4: =COUNTA('A1 Alimentation Adaptée'!$AP$4:$AP$121) -> 58
C5: You can find all the published versions on https://service.ca-mocca.com/maia-collab/CFR/SitePages/Notices_EN.aspx | G5: Référentiel | H5: =COUNTIF('A1 Alimentation Adaptée'!$AT$4:$AT$129,$H$3) -> 51 | I5: =COUNTIF('A1 Alimentation Adaptée'!$AT$4:$AT$129,$I$3) -> 0 | J5: =COUNTIF('A1 Alimentation Adaptée'!$AT$4:$AT$129,$J$3) -> 0 | K5: =L5-SUM(H5:J5) -> 0 | L5: =COUNTA('A1 Alimentation Adaptée'!$AT$4:$AT$129) -> 51
A6: Descriptif de la Mise à jour / Modifications | C6: Descriptif de la modification / Modification description | G6: Valeur | H6: =COUNTIF('A1 Alimentation Adaptée'!$AX$3:$AX$122,$H$3) -> 17 | I6: =COUNTIF('A1 Alimentation Adaptée'!$AX$3:$AX$122,I3) -> 7 | J6: =COUNTIF('A1 Alimentation Adaptée'!$AX$3:$AX$122,J3) -> 0 | K6: =L6-SUM(H6:J6) -> 1 | L6: =COUNTA('A1 Alimentation Adaptée'!$AX$3:$AX$122) -> 25
A7: Couleur / Color | C7: Permet d'identifier les zones ajoutées/modifiées | G7: Intra-objet | H7: =COUNTIF('A1 Alimentation Adaptée'!$BB$4:$BB$126,$H$3) -> 7 | I7: =COUNTIF('A1 Alimentation Adaptée'!$BB$4:$BB$126,I3) -> 5 | J7: =COUNTIF('A1 Alimentation Adaptée'!$BB$4:$BB$126,J3) -> 0 | K7: =L7-SUM(H7:J7) -> 0 | L7: =COUNTA('A1 Alimentation Adaptée'!$BB$4:$BB$126) -> 12
C8: The color code enables identification of the different kinds of evolutions | G8: Inter-objet | H8: =COUNTIF('A1 Alimentation Adaptée'!$BF$5:$BF$125,$H$3) -> 6 | I8: =COUNTIF('A1 Alimentation Adaptée'!$BF$5:$BF$125,I3) -> 0 | J8: =COUNTIF('A1 Alimentation Adaptée'!$BF$5:$BF$125,J3) -> 0 | K8: =L8-SUM(H8:J8) -> 0 | L8: =COUNTA('A1 Alimentation Adaptée'!$BF$5:$BF$125) -> 6
G9: Cohérence | H9: =COUNTIF('A1 Alimentation Adaptée'!$BJ$3:$BJ$124,Modifications!$H$3) -> 0 | I9: =COUNTIF('A1 Alimentation Adaptée'!$BJ$3:$BJ$124,Modifications!$I$3) -> 3 | J9: =COUNTIF('A1 Alimentation Adaptée'!$BJ$3:$BJ$124,Modifications!$J$3) -> 0 | K9: =L9-SUM(H9:J9) -> 0 | L9: =COUNTA('A1 Alimentation Adaptée'!$BJ$3:$BJ$124) -> 3
A12: Suivi des versions / Version tracking
A13: Date de diffusion / Publication date | B13: Publication mocca n° | C13: Descriptif de la mise à jour / Modifications | D13: Couleur / Color
A14: 46014 | B14: 45.00 | C14: Ajout de nouvelles données / New data addition
A15: 46014 | B15: 45.00 | C15: Ajouter des séparateurs ';' entre chaque donnée / Semicolon ';' to be added between each data
A16: 46014 | B16: 45.00 | C16: Modifications / Modifications
A19: Liens utiles / Useful Links
A20: Langages Communs / Common Languages | C20: https://service.ca-mocca.com/maia-collab/CFR/SitePages/Langages_Communs.aspx https://service.ca-mocca.com/maia-collab/CFR/SitePages/Common_Languages.aspx
A21: Manuel des Echanges Entités-Zone de Partage et Notices / Exchange Manual ZP-entities and Notices | C21: https://service.ca-mocca.com/maia-collab/CFR/SitePages/Notices.aspx https://service.ca-mocca.com/maia-collab/CFR/SitePages/Notices_EN.aspx
A22: Guide Méthodologique - Alimentation PACT (ex CRR) / Methodological Guide - PACT (ex CRR) Feeding | C22: https://service.ca-mocca.com/maia-collab/CFR/SitePages/Notices.aspx https://service.ca-mocca.com/maia-collab/CFR/SitePages/Notices_EN.aspx

Sheet A1 Alimentation Adaptée
AN1: CTRL PRESENCE / PRESENCE CTRL | AR1: CTRL REFERENTIEL / REFERENTIEL CTRL - CIBLE | AV1: CTRL VALEUR / VALUE CTRL - CIBLE | AZ1: CTRL INTRA-OBJET / INTRA-OBJECT CTRL - CIBLE | BD1: CTRL INTER-OBJET / INTER-OBJECT CTRL | BH1: CTRL COHERENCE (cf. onglet dédié) / CONSISTENCY CTRL (cf. dedicated tab)
A2: OBJET DE COLLECTE / COLLECTION OBJECT | B2: N° D'ORDRE TECHNIQUE DE LA DONNEE / TECHNICAL ORDER NUMBER OF THE DATA IN THE FILE | C2: BLOC DE DONNEES | D2: DATA BLOCK | E2: REFERENCE DE COLLECTE / COLLECTION REFERENCE | F2: NOM DE LA DONNEE | G2: DATA NAME | H2: DEFINITION | I2: DEFINITION | J2: Inclus CALF | K2: Provenance | L2: Table DDR | M2: RG | N2: Commentaire | O2: Version | P2: TERME METIER | Q2: BUSINESS TERM | R2: CODE TECHNIQUE / TECHNICAL CODE | S2: EXIGENCE D'ALIMENTATION | T2: SUPPLY REQUIREMENT | U2: REFERENCE DE LANGAGE COMMUN / COMMON LANGUAGE REFERENCE | V2: TABLE START / START Table | W2: REGLE DE GESTION | X2: MANAGEMENT RULE | Y2: FORMAT | Z2: REGLE DE FORMATAGE | AA2: FORMATTING RULE | AB2: LONGUEUR / LENGTH | AC2: POSITION / POSITION | AD2: VERSION DE CREATION / FIRST APPEARANCE VERSION | AE2: VERSION DE DERNIERE APPARITION / LAST APPEARANCE VERSION | AF2: VERSION DE MODIFICATION / MODIFICATION VERSION | AG2: USAGE(S) DECLARE(S) / DECLARED USAGE | AH2: DONNEE CRITIQUE POUR / CRITICAL DATA FOR | AI2: DONNEE A CARACTERE PERSONNEL / PERSONNAL DATA | AJ2: PERIMETRE DE COLLECTE / COLLECTION SCOPE | AK2: APPLICATION REMETTANTE / REMITTING APPLICATION | AL2: REFERENCE DE LA DONNEE DANS L'APPLICATION REMETTANTE / DATA REFERENCE IN REMITTING APPLICATION | AN2: CTRL PRESENCE | AO2: PRESENCE CTRL | AP2: PRESENCE SCORE CONSEQUENCE | AQ2: PRESENCE Code CTRL ZP | AR2: CTRL REFERENTIEL | AS2: REFERENTIEL CTRL | AT2: REFERENTIEL SCORE CONSEQUENCE | AU2: REFERENTIEL Code CTRL ZP | AV2: CTRL VALEUR | AW2: VALUE CTRL | AX2: VALEUR SCORE CONSEQUENCE | AY2: VALEUR Code CTRL ZP | AZ2: CTRL INTRA-OBJET | BA2: INTRA-OBJECT CTRL | BB2: COHERENCE SCORE CONSEQUENCE | BC2: COHERENCE Code CTRL ZP | BD2: CTRL INTER-OBJET | BE2: INTER-OBJECT CTRL | BF2: SCORE CONSEQUENCE | BG2: Code CTRL ZP | BH2: CTRL COHERENCE | BI2: CONSISTENCY CTRL | BJ2: Score Consequence | BK2: Code CTRL ZP
A3: Famille de flux et Objet de Collecte véhiculant la donnée / Flow family and data collection object | B3: Numéro séquentiel correspondant au numéro d'ordre de la donnée dans le fichier physique. Invariant dans le temps (toute nouvelle donnée sera ajoutée en fin de fichier) / Sequential number corresponding to the order number of the data in the physical file. Invariant in time (any new data will be added at the end of the file) | C3: Classification de la donnée dans un des blocs structurant l'Objet de Collecte | D3: Classification of the data in one of the blocks structuring the Collection Object. | E3: Référence de la donnée collectée via l'Objet de Collecte. Attribut communément appelé 'Etiquette' / Reference of the data collected via the Collection Object. Attribute commonly referred to as 'Label' | F3: Libellé Métier de la donnée | G3: Data business name | H3: Définition métier de la donnée | I3: Business data definition | P3: Terme métier parent du glossaire métier auquel se rapporte la donnée | Q3: Term parent business of the business glossary to which the data relates | R3: Nom technique de la donnée / Technical name of the data | S3: Exigence de présence de la donnée sur le périmètre de Collecte défini. L'information prend la valeur : - Obligatoire si la donnée est exigée - Obligatoire Si si la donnée est exigée dans des conditions définies dans la Règle de Gestion - Facultatif si la donnée n'est pas exigée - NA si la donnée est devenue obsolète et n'est plus collectée sur le domaine de Collecte - A renseigner si l'information n'est pas encore disponible | T3: Requirement to have the data on the defined Collection perimeter. Information is valued: - Mandatory if data is required - Mandatory If the data is required under conditions defined in the Management Rule - Optional if data is not required - NA if the data has become obsolete and is no longer collected on the Collection domain - To be filled if the information is not yet available | U3: Référence du Langage Commun structurant le format autorisé et la nomenclature autorisée. L'information prend la valeur : - LC.NNNN si la donnée s'adosse au LC.NNNN - LC à référencer si la donnée s'adosse à un LC en cours de référencement - NA si la donnée ne s'adosse à aucun LC /A reference to the Common Language structuring the allowed format and the allowed nomenclature. Information is valued: - LC.NNNN if the data is based on LC.NNNN - LC to be referenced if the data is against an LC being referenced - NA if the data does not support any LC. | V3: Table(s)/Rubrique(s) Start porteuse(s) de la nomenclature du Langage Commun lorsque celui ci est référencé. Il peut être multiple. L'information prend la valeur : - TA XXXXX si la donnée s'adosse à la table TA XXXXX - RB XXXXX si la donnée s'adosse à la rubrique RB XXXXX - NA si la donnée ne s'adosse à aucun référentiel Start /Table(s)/Topic(s) Start carrying the nomenclature of the Common Language when it is referenced. It can be multiple. Information is valued: - TA XXXXX if the data is based on the table TA XXXXX - RB XXXXX if the data is based on RB XXXXX - NA if the data does not support any Start referential | W3: Précisions sur les exigences posées sur la donnée (de type seuils, formules, calculs, règles d'alimentation hors LC...) ou commentaires. En particulier, les exigences posées sur la donnée peuvent porter sur : - sa présence (dans le contrôle) (ne pas reprendre les conditions du contrôle de présence si assez explicite) Nota Bene sur le domaine de valeurs : -- si la donnée peut s'inscrire dans toute la nomenclature d'un Langage Commun, le LC est directement renseigné dans le champ dédié "Référence LC" -- si la donnée s'inscrit dans un domaine de valeurs plus restreint lié au périmètre fonctionnel de l'objet collecté, ce domaine de valeurs strictement autorisé est indiqué ici (contrôle de valeur). L'information prend la valeur NA sans exigences particulières | X3: Details on the requirements of the data (of the threshold type, formulas, calculations, rules of supply excluding LC...) or comments. In particular, the data requirements may relate to: - its presence (in the control) (do not take over the presence control conditions so explicitly) Note Bene on the value domain: — if the data can be inscribed in the entire nomenclature of a Common Language, the LC is directly filled in the dedicated field "LC Reference" — if the data falls within a narrower value domain related to the functional scope of the collected object, this strictly authorized value domain is indicated here (value control). Information is set to NA without any special requirements | Y3: Format de la donnée. L'information prend la valeur : - DATE - ALPHA - NUM - A renseigner si l'information n'est pas encore disponible Data format. Information is valued: - DATE - ALPHA - NUM - To be filled if the information is not yet available | Z3: Structure de présentation des données de type date, montant et taux. L'information prend la valeur : - "NA" en l'absence de règle de formatage. - "A renseigner" si l'information n'est pas disponible | AA3: Date, amount and rate data presentation structure. Information is valued: - "NA" in the absence of a formatting rule. - "To be filled" if the information is not available | AB3: Longueur de la donnée La valeur 8 est attendue sur les formats DATE/ Data length Value 8 is expected on DATE formats | AC3: Numéro correspondant à la position de la donnée dans la chaine de caractères du fichier physique. Nécessaire que pour les fichiers plats sans séparateurs (PACT par exemple). Elle prend la valeur NA dans les autres cas. / The number that corresponds to the position of the data item in the character string of the physical file. Required only for flat files without separators. It is set to NA in other cases. | AD3: Version de la notice dans laquelle la donnée est apparue. L'information prend la valeur: - De la donnée Verbloc figurant dans l'en-tête de la notice - A renseigner si l'information n'est pas encore disponible./ The version of the notice in which the data appeared. Information takes value: - Verbloc data in the header of the notice - To be filled if the information is not yet available. | AE3: Version de la notice dans laquelle la donnée apparaît pour la dernière fois. L'information prend la valeur: - De la donnée Verbloc figurant dans l'en-tête de la notice quand la donnée est devenue obsolète - NA quand la donnée est toujours collectée/ The version of the notice in which the data last appears. Information takes value: - Verbloc data in the header of the record when the data has become obsolete - NA when data is still collected | AF3: Dernière version de publication de la notice présentant la MAJ de la donnée / Latest publication version of the notice where the data was updated | AG3: Liste des usages industriels déclarant exploiter la donnée. L'information prend la valeur : - Usage1, Usage2, Usage3, ..., UsageN si plusieurs usages sont déclarés - NA en l'absence d'usage déclaré - A renseigner si l'information n'est pas encore disponible /List of industrial uses declaring to exploit the data. Information is valued: - Use1, Use2, Use3, ..., UseN if more than one use is declared - NA in the absence of declared use - To be filled if the information is not yet available | AH3: Liste des usages signalant que la donnée est indispensable pour leur fonctionnement. Le processus de production de reporting de ce(s) usage(s) est compromis par l'absence de cette donnée ou par sa non qualité. L'information prend la valeur : - Usage1, Usage2, Usage3, ..., UsageN si plusieurs usages ont déclaré la donnée critique - NA en l'absence de criticité de la donnée quel que soit l'usage - A renseigner si l'information n'est pas encore disponible/ List of uses indicating that the data is essential for their operation. The reporting production process of this use(s) is compromised by the absence of this data or by its non-quality. Information is valued: - Usage1, Usage2, Usage3, ..., UsageN if several uses have declared critical data - NA in the absence of criticality of the data whatever the use - To be filled if the information is not yet available | AI3: Indicateur signalant que la donnée est à caractère personnel. Une donnée à caractère personnel au sens RGPD est une information se rapportant à une personne physique identifiée ou identifiable. Elle peut permettre d'identifier une personne physique directement (exemple : nom et prénom) ou indirectement (exemple : par un numéro de téléphone ou de plaque d'immatriculation, un identifiant tel que le numéro de sécurité sociale, une adresse postale ou courriel). L'information prend la valeur : - Y si la donnée est une donnée à caractère personnel - N dans le cas contraire - A renseigner si l'information n'est pas encore disponible/ Indicator indicating that the data is personal. Personal data in the sense of GDPR is information relating to an identified or identifiable natural person. It can identify a natural person directly (example: first and last names) or indirectly (example: by a telephone or license plate number, an identifier such as a social security number, a postal or email address). Information is valued: - Y if the data is personal data - N otherwise - To be filled if the information is not yet available | AJ3: Information concernant les données du P1, M1 et flux passifs seulement. Le périmètre de Collecte précise le domaine fonctionnel auquel se rapporte la Collecte de la donnée. La nature du domaine fonctionnel varie suivant les objets de collecte. L'information peut être de nature: - Type de risque - Nature juridique de la sûreté - NA dans les autres cas/ Information on P1, M1 and liability flow data only. The Collection scope specifies the functional area to which the Data Collection relates. The nature of the functional area varies according to the collection objects. The information may be of a nature: - Risk type - Legal nature of security interest - NA in other cases | AK3: Application en central qui met la donnée à disposition / Central application that makes data available | AL3: Référence de la donnée en provenance de l'application remettante / Reference of data from remitting application
A4: A1 | B4: 1 | C4: 00 - En-tête du flux | D4: 00 - File header | E4: A1 H.ENREG | F4: Type d'enregistrement | G4: Type of record | H4: Type d'enregistrement correspondant au bloc En-tête | I4: Type of record corresponding to Header block | P4: ND | Q4: ND | R4: ENREG | S4: Obligatoire | T4: Mandatory | U4: NA | V4: NA | W4: A alimenter à "00" | X4: To be filled with "00" | Y4: ALPHA | Z4: NA | AA4: NA | AB4: 2 | AC4: NA | AD4: 43 | AE4: NA | AF4: NA | AG4: USAGE ZP | AH4: NA | AI4: NA | AJ4: NA | AK4: NA | AL4: NA
A5: A1 | B5: 2 | C5: 00 - En-tête du flux | D5: 00 - File header | E5: A1 H.IDFICHIER | F5: Identifiant du fichier | G5: File's identifier | H5: Identifiant caractérisant le contenu véhiculé par le fichier et servant à référencer chaque type de fichier échangé dans le Référentiel des Echanges du Groupe afin de favoriser la réutilisation | I5: Identifier characterising the content reported by the file and serving to reference each type of file exchanged in the Group's Exchange Referential to facilitate re-use | P5: ND | Q5: ND | R5: IDFICHIER | S5: Obligatoire | T5: Mandatory | U5: NA | V5: NA | W5: A alimenter à "00000535" | X5: To be filled with "00000535" | Y5: ALPHA | Z5: NA | AA5: NA | AB5: 8 | AC5: NA | AD5: 43 | AE5: NA | AF5: NA | AG5: USAGE ZP | AH5: NA | AI5: NA | AJ5: NA | AK5: NA | AL5: NA
A6: A1 | B6: 3 | C6: 00 - En-tête du flux | D6: 00 - File header | E6: A1 H.VERFICHIER | F6: Version technique du fichier | G6: File's technical version | H6: Qualifie les modalités techniques de constitution du fichier (positionnel, XML, …) | I6: Characterises the technical modalities for producing the file (positional, XML, etc.) | P6: ND | Q6: ND | R6: VERFICHIER | S6: Obligatoire | T6: Mandatory | U6: NA | V6: NA | W6: A alimenter à "001" | X6: To be filled with "001" | Y6: ALPHA | Z6: NA | AA6: NA | AB6: 3 | AC6: NA | AD6: 43 | AE6: NA | AF6: NA | AG6: USAGE ZP | AH6: NA | AI6: NA | AJ6: NA | AK6: NA | AL6: NA
A7: A1 | B7: 4 | C7: 00 - En-tête du flux | D7: 00 - File header | E7: A1 H.TIMESTAMP | F7: Horodatage | G7: Timestamp | H7: Date et heure de production du fichier (norme ISO 8601 : séparateur normalisé « T » entre la date et l'heure) | I7: Date and time of the file's production (ISO 8601 standard: normalised separator “T” between the date and time) | P7: ND | Q7: ND | R7: TIMESTAMP | S7: Obligatoire | T7: Mandatory | U7: NA | V7: NA | W7: NA | X7: NA | Y7: ALPHA | Z7: AAAAMMJJTHHMMSS | AA7: YYYYMMDDTHHMMSS | AB7: 15 | AC7: NA | AD7: 43 | AE7: NA | AF7: NA | AG7: USAGE ZP | AH7: NA | AI7: NA | AJ7: NA | AK7: NA | AL7: NA
A8: A1 | B8: 5 | C8: 00 - En-tête du flux | D8: 00 - File header | E8: A1 H.UOE | F8: Entité émettrice | G8: Issuing entity | H8: Identifiant national de l'entité produisant le fichier (pour son propre compte ou en cas de sous-traitance pour le compte de l'entité déclarante) | I8: National identifier of the entity producing the file (for its own account or, in the event of subcontracting, on behalf of the issuing entity) | P8: ND | Q8: ND | R8: UOE | S8: Obligatoire | T8: Mandatory | U8: LC.0003 | V8: TA FI59 | W8: NA | X8: NA | Y8: ALPHA | Z8: NA | AA8: NA | AB8: 5 | AC8: NA | AD8: 43 | AE8: NA | AF8: NA | AG8: USAGE ZP | AH8: NA | AI8: NA | AJ8: NA | AK8: NA | AL8: NA
A9: A1 | B9: 6 | C9: 00 - En-tête du flux | D9: 00 - File header | E9: A1 H.UOD | F9: Entité déclarante | G9: Reporting entity | H9: Identifiant national de l'entité à laquelle se rapporte le contenu du fichier (entité porteuse du risque) | I9: National identifier of the entity to which the file's content relates (entity carrying the risk) | P9: ND | Q9: ND | R9: UOD | S9: Obligatoire | T9: Mandatory | U9: LC.0003 | V9: TA FI59 | W9: NA | X9: NA | Y9: ALPHA | Z9: NA | AA9: NA | AB9: 5 | AC9: NA | AD9: 43 | AE9: NA | AF9: NA | AG9: USAGE ZP | AH9: NA | AI9: NA | AJ9: NA | AK9: NA | AL9: NA
A10: A1 | B10: 7 | C10: 00 - En-tête du flux | D10: 00 - File header | E10: A1 H.NMAPPU | F10: Application émettrice | G10: Issuing application | H10: Code ou nom de l'application ou du job utilisés pour produire le fichier dans le SI de l'entité | I10: Code or name of the application or job used to produce the file in the entity's IT system | P10: ND | Q10: ND | R10: NMAPPU | S10: Facultatif | T10: Optional | U10: NA | V10: NA | W10: Non alimenté | X10: Not filled | Y10: ALPHA | Z10: NA | AA10: NA | AB10: 32 | AC10: NA | AD10: 43 | AE10: NA | AF10: NA | AG10: USAGE ZP | AH10: NA | AI10: NA | AJ10: NA | AK10: NA | AL10: NA
A11: A1 | B11: 8 | C11: 00 - En-tête du flux | D11: 00 - File header | E11: A1 H.CDBLOC | F11: Code du flux | G11: Flow code | H11: Code du flux correspondant aux objets métier véhiculés par le fichier | I11: Flow code corresponding to the business objects reported by the file | P11: ND | Q11: ND | R11: CDBLOC | S11: Obligatoire | T11: Mandatory | U11: NA | V11: NA | W11: A alimenter à "CRRA" | X11: To be filled with "CRRA" | Y11: ALPHA | Z11: NA | AA11: NA | AB11: 4 | AC11: NA | AD11: 43 | AE11: NA | AF11: NA | AG11: USAGE ZP | AH11: NA | AI11: NA | AJ11: NA | AK11: NA | AL11: NA
A12: A1 | B12: 9 | C12: 00 - En-tête du flux | D12: 00 - File header | E12: A1 H.VERBLOC | F12: Version du flux | G12: Flow version | H12: Version du flux correspondant aux objets métier véhiculés par le fichier | I12: Version of flow corresponding to the business objects reported by the file | J12: OUI | K12: NA | L12: NA | M12: Alimenter à '45' | N12: Il s'agit de la version du flux Elle sera alimenté à "45" | O12: Version 1 | P12: ND | Q12: ND | R12: VERBLOC | S12: Obligatoire | T12: Mandatory | U12: NA | V12: NA | W12: A alimenter à "45" | X12: To be filled with "45" | Y12: ALPHA | Z12: NA | AA12: NA | AB12: 2 | AC12: NA | AD12: 43 | AE12: NA | AF12: 45.00 | AG12: USAGE ZP | AH12: NA | AI12: NA | AJ12: NA | AK12: NA | AL12: NA
A13: A1 | B13: 10 | C13: 00 - En-tête du flux | D13: 00 - File header | E13: A1 H.NUMENV | F13: Numéro d'envoi du fichier | G13: File's dispatch number | H13: Permet de gérer les réemissions | I13: Serves to manage re-issues | P13: ND | Q13: ND | R13: NUMENV | S13: Obligatoire | T13: Mandatory | U13: NA | V13: NA | W13: A alimenter à "00001" et à incrémenter de +1 à chaque réémission | X13: To be filled with "00001"and incrementing by +1 at each reissue | Y13: ALPHA | Z13: NA | AA13: NA | AB13: 5 | AC13: NA | AD13: 43 | AE13: NA | AF13: NA | AG13: USAGE ZP | AH13: NA | AI13: NA | AJ13: NA | AK13: NA | AL13: NA
A14: A1 | B14: 11 | C14: 00 - En-tête du flux | D14: 00 - File header | E14: A1 H.CRARRETE | F14: Type d'arrêté | G14: Reporting type | H14: Périodicité de l'arrêté | I14: Reporting frequency | P14: ND | Q14: ND | R14: CRARRETE | S14: Obligatoire | T14: Mandatory | U14: LC.0056 | V14: TA KVFREQU | W14: NA | X14: NA | Y14: ALPHA | Z14: NA | AA14: NA | AB14: 1 | AC14: NA | AD14: 43 | AE14: NA | AF14: NA | AG14: USAGE ZP | AH14: NA | AI14: NA | AJ14: NA | AK14: NA | AL14: NA
A15: A1 | B15: 12 | C15: 00 - En-tête du flux | D15: 00 - File header | E15: A1 H.DTARRETE | F15: Date d'arrêté | G15: Closing date | H15: Date d'arrêté correspondant au contenu du fichier (norme ISO 8601) | I15: Closing date corresponding to the file's content (ISO 8601 standard) | P15: ND | Q15: ND | R15: DTARRETE | S15: Obligatoire | T15: Mandatory | U15: NA | V15: NA | W15: NA | X15: NA | Y15: DATE | Z15: AAAAMMJJ | AA15: YYYYMMDD | AB15: 8 | AC15: NA | AD15: 43 | AE15: NA | AF15: NA | AG15: USAGE ZP | AH15: NA | AI15: NA | AJ15: NA | AK15: NA | AL15: NA
A16: A1 | B16: 13 | C16: 00 - En-tête du flux | D16: 00 - File header | E16: A1 H.NUMSEQ | F16: Numéro de séquence du fichier | G16: File sequence number | H16: Permet d'identifier un lot | I16: Allows to identify a batch | P16: ND | Q16: ND | R16: NUMSEQ | S16: Obligatoire | T16: Mandatory | U16: NA | V16: NA | W16: A alimenter avec une valeur comprise entre "00001" et "99999" en fonction des lots définis par l'entité | X16: To be filled with a value between "00001" and "99999" depending of batches defined by entity | Y16: ALPHA | Z16: NA | AA16: NA | AB16: 5 | AC16: NA | AD16: 43 | AE16: NA | AF16: NA | AG16: USAGE ZP | AH16: NA | AI16: NA | AJ16: NA | AK16: NA | AL16: NA
A17: A1 | B17: 14 | C17: 00 - En-tête du flux | D17: 00 - File header | E17: A1 H.NMAPPFIN | F17: Application émettrice Finance | G17: Issuing Finance application code | H17: Code de l'application émettrice spécifique à PALMA | I17: Issuing application code specific to PALMA | P17: ND | Q17: ND | R17: NMAPPFIN | S17: Facultatif | T17: Optional | U17: NA | V17: NA | W17: Non alimenté | X17: Not filled | Y17: ALPHA | Z17: NA | AA17: NA | AB17: 5 | AC17: NA | AD17: 43 | AE17: NA | AF17: NA | AG17: USAGE ZP | AH17: NA | AI17: NA | AJ17: NA | AK17: NA | AL17: NA
A18: A1 | B18: 15 | C18: 00 - En-tête du flux | D18: 00 - File header | E18: A1 H.FILLER | F18: Filler | G18: Filler | H18: Filler pour évolutions futures | I18: Filler for future evolution | P18: ND | Q18: ND | R18: FILLER | S18: Facultatif | T18: Optional | U18: NA | V18: NA | W18: Non alimenté | X18: Not filled | Y18: ALPHA | Z18: NA | AA18: NA | AB18: =2000-(SUM(AB4:AB17)+COUNT(AB4:AB17)) -> 1886 | AC18: NA | AD18: 43 | AE18: NA | AF18: NA | AG18: NA | AH18: NA | AI18: NA | AJ18: NA | AK18: NA | AL18: NA
A19: A1 | B19: 1 | C19: 02 - Caractéristiques d'identification fonctionnelles | D19: 02 - Functional identification characteristics | E19: 0.1 (A1) | F19: Date d'arrêté | G19: Closing date | H19: Correspond à la date d'arrêté des données transmises (dernier jour calendaire du mois) | I19: Represents the cut-off date of the data transmitted (final calendar day of the month) | P19: ND | Q19: ND | R19: SttmDt | S19: Obligatoire | T19: Mandatory | U19: NA | V19: NA | W19: Il doit y avoir unicité de la date d'arrêté au sein du flux | X19: The cut-off date must be the same across the flow | Y19: ALPHA | Z19: AAAAMMJJ | AA19: YYYYMMDD | AB19: 8 | AC19: NA | AD19: 40 | AE19: NA | AF19: 45.00 | AG19: CALCULS PRUDENTIELS, LIQUIDITE | AH19: ND | AI19: N | AJ19: NA | AK19: NA | AL19: NA
A20: A1 | B20: 2 | C20: 02 - Caractéristiques d'identification fonctionnelles | D20: 02 - Functional identification characteristics | E20: 0.2 (A1) | F20: Entité Porteuse de Risques | G20: Risk taker entity | H20: Correspond au code consolidation comptable de l'Entité porteuse de risque dans les comptes de Crédit Agricole S.A. | I20: Represents the accounting consolidation code of the Entity bearing risks in the financial statements of Crédit Agricole S.A. | P20: ND | Q20: ND | R20: EntPortRisq | S20: Obligatoire | T20: Mandatory | U20: LC.0003 | V20: TA FI59 | W20: NA | X20: NA | Y20: ALPHA | Z20: NA | AA20: NA | AB20: 5 | AC20: NA | AD20: 40 | AE20: NA | AF20: 45.00 | AG20: CALCULS PRUDENTIELS, LIQUIDITE, NPE | AH20: ND | AI20: N | AJ20: NA | AK20: NA | AL20: NA | AN20: La donnée est obligatoire | AO20: The data is mandatory | AP20: 7 | AQ20: TP0001 | AR20: Si elle est renseignée, la valeur doit être connue du Langage Commun associé | AS20: If specified, the value must be known to the associated Common Language | AT20: 7 | AU20: TIG0001 | BD20: Unicité au sein de l'entité porteuse de risque | BE20: Uniqueness within the entity bearing the risk | BF20: 7 | BG20: TU0001
A21: A1 | B21: 3 | C21: 02 - Caractéristiques d'identification fonctionnelles | D21: 02 - Functional identification characteristics | E21: 0.3 (A1) | F21: Application source | G21: Source application | H21: Correspond au code du Système d'Information utilisé en local pour générer le flux En Alimentation dégradée, il faut préfixer par la lettre ‘A' le code application source | I21: Represents the code of the Information System used locally to generate the flow In Degraded data entry, the source application code must be prefix with the letter 'A' | P21: ND | Q21: ND | R21: AppliSource | S21: Obligatoire | T21: Mandatory | U21: NA | V21: TA KVAPPBK | W21: Il convient à chaque entité émettrice du flux de déterminer le(s) code(s) ‘Application source' qu'elle utilise et de le(s) porter à la connaissance de la DRG avant première utilisation dans le flux. Une fois communiqué, le code est définitif Les flux tardifs ou correctifs tardifs seront déclarés sous le code application source "CORE" imposé par la DRG | X21: Every entity issuing flows must determine what ‘Source application' code(s) it uses and inform the Group Risk Management Division thereof prior to using them in the flow. Once notified, the code can't be changed Later corrections or flows will be declared under the source application code 'CORE' imposed by DRG | Y21: ALPHA | Z21: NA | AA21: NA | AB21: 12 | AC21: NA | AD21: 40 | AE21: NA | AF21: NA | AG21: CALCULS PRUDENTIELS | AH21: ND | AI21: N | AJ21: NA | AK21: NA | AL21: NA | AN21: La donnée est obligatoire | AO21: The data is mandatory | AP21: 7 | AQ21: TP0001 | AR21: Si elle est renseignée, la valeur doit être connue du Langage Commun associé | AS21: If specified, the value must be known to the associated Common Language | AT21: 7 | AU21: TIS0067 | AV21: La donnée doit commencer par 'A' ou 'ACORE' | AW21: Data must be start with 'A' or 'ACORE' | AX21: 7 | AY21: TVS0749 | BD21: Unicité au sein de l'entité porteuse de risque | BE21: Uniqueness within the entity bearing the risk | BF21: 7 | BG21: TU0001
A22: A1 | B22: 4 | C22: 02 - Caractéristiques d'identification fonctionnelles | D22: 02 - Functional identification characteristics | E22: 0.4 (A1) | F22: Fréquence de transmission | G22: Transmission frequency | H22: Permet d'identifier le flux dans les traitements | I22: Makes it possible to identify the flow in the treatments | P22: ND | Q22: ND | R22: FreqTrans | S22: Obligatoire | T22: Mandatory | U22: NA | V22: NA | W22: 'M' pour mensuel | X22: ‘M' for monthly | Y22: ALPHA | Z22: NA | AA22: NA | AB22: 1 | AC22: NA | AD22: 40 | AE22: NA | AF22: NA | AG22: USAGE ZP | AH22: ND | AI22: N | AJ22: NA | AK22: NA | AL22: NA
A23: A1 | B23: 5 | C23: 02 - Caractéristiques d'identification fonctionnelles | D23: 02 - Functional identification characteristics | E23: 0.5 (A1) | F23: Date et Heure de traitement | G23: Date and time of processing | H23: Correspond à la date et heure du début du traitement ayant produit le flux | I23: Represents the date and time at which flow treatment began | P23: ND | Q23: ND | R23: DtHeureTrait | S23: Obligatoire | T23: Mandatory | U23: NA | V23: NA | W23: Pour un lot déterminé, la valeur de la donnée doit être unique | X23: Rule: for a given batch, the data value is unique | Y23: ALPHA | Z23: AAAAMMJJHHMM | AA23: YYYYMMDDHHMM | AB23: 12 | AC23: NA | AD23: 40 | AE23: NA | AF23: NA | AG23: USAGE ZP | AH23: ND | AI23: N | AJ23: NA | AK23: NA | AL23: NA
A24: A1 | B24: 6 | C24: 02 - Caractéristiques d'identification fonctionnelles | D24: 02 - Functional identification characteristics | E24: 0.6 (A1) | F24: Type d'enregistrement | G24: Record type | H24: Caractérise le type d'enregistrement remonté par le site | I24: Represents the record type reported by the site | P24: ND | Q24: ND | R24: TypEnreg | S24: Obligatoire | T24: Mandatory | U24: NA | V24: NA | W24: Valeur admise : 'A1' (domaine Alimentation dégradée) | X24: Permitted value: 'A1' (Degraded Data Entry section) | Y24: ALPHA | Z24: NA | AA24: NA | AB24: 2 | AC24: NA | AD24: 40 | AE24: NA | AF24: NA | AG24: USAGE ZP | AH24: ND | AI24: N | AJ24: NA | AK24: NA | AL24: NA
A25: A1 | B25: 7 | C25: 02 - Caractéristiques d'identification fonctionnelles | D25: 02 - Functional identification characteristics | E25: 0.7 (A1) | F25: Nature de flux (Zone réservée DRG) | G25: Nature of flow (Zone reserved for Group Risk Management Division) | H25: Nature de flux (Zone réservée DRG) | I25: Nature of flow (Zone reserved for Group Risk Management Division) | P25: NA | Q25: NA | R25: NatFlux | S25: NA | T25: NA | U25: NA | V25: NA | W25: (Zone réservée DRG) | X25: (Zone reserved for the Group Risk Management Division) | Y25: ALPHA | Z25: NA | AA25: NA | AB25: 1 | AC25: NA | AD25: 40 | AE25: 41 | AF25: NA | AG25: NA | AH25: NA | AI25: N | AJ25: NA | AK25: NA | AL25: NA
A26: A1 | B26: 8 | C26: 02 - Caractéristiques d'identification fonctionnelles | D26: 02 - Functional identification characteristics | E26: 0.8 (A1) | F26: Centre de Responsabilité Comptable (Zone réservée CAsa social) | G26: Accounting responsibility center (Zone reserved for Crédit Agricole S.A. Holding) | H26: Zone réservée CAsa social | I26: Zone reserved for Crédit Agricole S.A. | P26: ND | Q26: ND | R26: ZoneResCasa | S26: Obligatoire sous conditions | T26: Mandatory under conditions | U26: LC.0072 | V26: TA KVCRC | W26: Zone exploitée uniquement par les entités déclarant les risques portés par Crédit Agricole S.A. Décomposition comptable du Siège en Activités (comptabilités auxiliaires). Permet de gérer les opérations pour compte propre Casa | X26: Zone only used for entities reporting risks borne by Crédit Agricole S.A. Accounting breakdown of HQ into Activities (sub-ledgers). Makes it possible to manage Crédit Agricole S.A. proprietary trading | Y26: ALPHA | Z26: NA | AA26: NA | AB26: 2 | AC26: NA | AD26: 40 | AE26: NA | AF26: 45.00 | AG26: CALCULS PRUDENTIELS, LIQUIDITE, NPE | AH26: ND | AI26: N | AJ26: NA | AK26: NA | AL26: NA | AN26: La donnée est obligatoire, si Entité Porteuse de Risques [0.2 (A1)] = '00018' | AO26: The data is mandatory if Entity Id [0.2 (A1)] = '00018' | AP26: 7 | AQ26: TPS1782 | AR26: Si elle est renseignée, la valeur doit être connue du Langage Commun associé | AS26: If specified, the value must be known to the associated Common Language | AT26: 7 | AU26: TIG0001
A27: A1 | B27: 9 | C27: 02 - Caractéristiques d'identification fonctionnelles | D27: 02 - Functional identification characteristics | E27: 0.99 (A1) | F27: Zone Libre | G27: Free zone | H27: Zone Libre | I27: Free zone | P27: NA | Q27: NA | R27: ZoneLibre0 | S27: NA | T27: NA | U27: NA | V27: NA | W27: NA | X27: NA | Y27: ALPHA | Z27: NA | AA27: NA | AB27: 7 | AC27: NA | AD27: 40 | AE27: 41 | AF27: NA | AG27: NA | AH27: NA | AI27: N | AJ27: NA | AK27: NA | AL27: NA
A28: A1 | B28: 10 | C28: 02 - Caractéristiques d'identification fonctionnelles | D28: 02 - Functional identification characteristics | E28: A1 1.98 | F28: Zone réservée DRG | G28: Zone reserved for the Group Risk Management Division | H28: Zone réservée DRG | I28: Zone reserved for the Group Risk Management Division | P28: NA | Q28: NA | R28: ZoneResDRG1 | S28: NA | T28: NA | U28: NA | V28: NA | W28: (Zone réservée DRG) | X28: (Zone reserved for the Group Risk Management Division) | Y28: ALPHA | Z28: NA | AA28: NA | AB28: 130 | AC28: NA | AD28: 40 | AE28: 41 | AF28: NA | AG28: NA | AH28: NA | AI28: N | AJ28: NA | AK28: NA | AL28: NA
A29: A1 | B29: 11 | C29: 02a - Caractéristiques d'identification fonctionnelles (clé) | D29: 02a - Functional identification characteristics (key) | E29: A1 1.11 | F29: Identifiant de l'engagement | G29: Product identifier | H29: Identifiant unique dans le système local utilisé pour générer le flux | I29: Unique ID in the local system used to generate the flow | P29: ND | Q29: ND | R29: IdEng | S29: Obligatoire | T29: Mandatory | U29: NA | V29: NA | W29: Pour un lot déterminé, l'identifiant doit être unique au sein du lot | X29: For a given batch, the ID must be unique within the batch | Y29: ALPHA | Z29: NA | AA29: NA | AB29: 40 | AC29: NA | AD29: 40 | AE29: NA | AF29: 45.00 | AG29: CALCULS PRUDENTIELS, LIQUIDITE, NPE | AH29: ND | AI29: N | AJ29: NA | AK29: NA | AL29: NA | AN29: La donnée est obligatoire | AO29: The data is mandatory | AP29: 7 | AQ29: TP0001 | BD29: L'identifiant renseigné doit être unique au sein de l'entité porteuse de risque | BE29: The identifier provided must be unique within the entity carrying the risk | BF29: 7 | BG29: TU0001
A30: A1 | B30: 12 | C30: 02 - Caractéristiques d'identification fonctionnelles | D30: 02 - Functional identification characteristics | E30: A1 1.99 | F30: Zone réservée DRG | G30: Zone reserved for the Group Risk Management Division | H30: Zone réservée DRG | I30: Zone reserved for the Group Risk Management Division | P30: NA | Q30: NA | R30: ZoneResDRG2 | S30: NA | T30: NA | U30: NA | V30: NA | W30: (Zone réservée DRG) | X30: (Zone reserved for the Group Risk Management Division) | Y30: ALPHA | Z30: NA | AA30: NA | AB30: 60 | AC30: NA | AD30: 40 | AE30: 41 | AF30: NA | AG30: NA | AH30: NA | AI30: N | AJ30: NA | AK30: NA | AL30: NA
A31: A1 | B31: 13 | C31: 16 - Identification Tiers | D31: 16 - Third party identification | E31: A1 2.1 | F31: CAP de l'exposition | G31: CAP of exposure | H31: Le champ correspond à la Classe d'Actif de Pondération de l'encours (contrepartie, émetteur des titres ou autres) | I31: The field represents the Asset class for weighting purposes of the outstanding amount (counterparty, issuer of securities or other) | P31: ND | Q31: ND | R31: cdCapExpo | S31: Obligatoire | T31: Mandatory | U31: LC.0084 | V31: TA H8CAP | W31: Les valeurs autorisées en méthode Standard : - actions et assimilés : CAP = 14 - titrisation : CAP = 15 - titres hors actions, la CAP correspond à l'émetteur du titre - expositions sur la Clientèle de détail, la CAP correspond au type d'engagement ou à la typologie de la contrepartie - autres types d'engagement, la CAP correspond à la contrepartie | X31: Values autorised for Standard approach: - For equities and equivalent: CAP = 14 - For securitisation: CAP = 15 - For securities excluding equities, the CAP represents the issuer of the security - For exposures vis-à-vis retail banking customers, the CAP represents the type of commitment or the type of counterparty - For other commitment types, the CAP represents the counterparty | Y31: ALPHA | Z31: NA | AA31: NA | AB31: 12 | AC31: NA | AD31: 40 | AE31: NA | AF31: NA | AG31: CALCULS PRUDENTIELS, ESG PILIER 3 | AH31: ND | AI31: N | AJ31: NA | AK31: NA | AL31: NA | AN31: La donnée est obligatoire | AO31: The data is mandatory | AP31: 7 | AQ31: TPG0001 | AR31: Si elle est renseignée, la valeur doit être connue du Langage Commun associé | AS31: If specified, the value must be known to the associated Common Language | AT31: 7 | AU31: TIG0001 | AV31: Si Méthodologie Bâloise [A1 3.2] = 'NA330', alors la donnée doit être égale à ('14', '60') | AW31: If Basel methodology [A1 3.2] = 'NA330', then data must be equal to ('14', '60') | AX31: 6 | AY31: TVS0766
A32: A1 | B32: 14 | C32: 16 - Identification Tiers | D32: 16 - Third party identification | E32: A1 2.2 | F32: État - pays de résidence fiscal | G32: Sovereign - country of fiscal residence | H32: Le champ correspond au pays de résidence fiscal de la contrepartie / de l'émetteur des titres | I32: The field is for the country of fiscal residence of the counterparty / issuer of securities | P32: ND | Q32: ND | R32: cdPaysFisc | S32: Obligatoire | T32: Mandatory | U32: LC.0004 LC.0273 | V32: TA NM252 (pour la partie ISO 3166) TA NM258 (organisation supra nationales) | W32: NA | X32: NA | Y32: ALPHA | Z32: NA | AA32: NA | AB32: 2 | AC32: NA | AD32: 40 | AE32: NA | AF32: NA | AG32: CALCULS PRUDENTIELS, ESG PILIER 3 | AH32: ND | AI32: N | AJ32: NA | AK32: NA | AL32: NA | AN32: La donnée est obligatoire | AO32: The data is mandatory | AP32: 7 | AQ32: TPG0001 | AR32: Si elle est renseignée, la valeur doit être connue du Langage Commun associé | AS32: If specified, the value must be known to the associated Common Language | AT32: 7 | AU32: TIG0001
A33: A1 | B33: 15 | C33: 16 - Identification Tiers | D33: 16 - Third party identification | E33: A1 2.3 | F33: Indicateur Contrepartie/Emetteur - Traitement spécifique | G33: Counterparty / Issuer indicator - specific treatment | H33: Le champ permet d'identifier les contreparties/émetteur de titres ayant un traitement spécifique | I33: The field makes it possible to identify the counterparties / issuer of securities subject to special treatment | P33: ND | Q33: ND | R33: idCtpTraitSpe | S33: Facultatif | T33: Optional | U33: LC.0146 | V33: TA KVCPPREF | W33: NA | X33: NA | Y33: ALPHA | Z33: NA | AA33: NA | AB33: 2 | AC33: NA | AD33: 40 | AE33: NA | AF33: NA | AG33: CALCULS PRUDENTIELS | AH33: ND | AI33: N | AJ33: NA | AK33: NA | AL33: NA | AR33: Si elle est renseignée, la valeur doit être connue du Langage Commun associé | AS33: If specified, the value must be known to the associated Common Language | AT33: 7 | AU33: TIG0001
A34: A1 | B34: 16 | C34: 16 - Identification Tiers | D34: 16 - Third party identification | E34: A1 2.4 | F34: Code partenaire de la contrepartie en risque | G34: Partner code of the counterparty at-risk | H34: Le champ permet de distinguer les opérations intragroupes et hors-groupe | I34: The field makes it possible to distinguish between inter-company and non-group transactions | P34: ND | Q34: ND | R34: cdPartCtp | S34: Obligatoire | T34: Mandatory | U34: LC.0003 | V34: TA FI59 RB NM281 | W34: Il s'agit du code de consolidation de l'entité partenaire dans le cas d'une opération intragroupe ou à un code générique dans le cas d'une opération hors-groupe Liste des codes partenaire : - '99999' s'il s'agit d'une entité Hors Groupe | X34: This is the consolidation code of the partner entity in the case of an inter-company transaction or a generic code in the case of a non-group transaction List of partner codes: - '99999' where it involves a Non-Group entity | Y34: NUM | Z34: NA | AA34: NA | AB34: 5 | AC34: NA | AD34: 40 | AE34: NA | AF34: 45.00 | AG34: CALCULS PRUDENTIELS, ESG PILIER 3, LIQUIDITE | AH34: ND | AI34: N | AJ34: NA | AK34: NA | AL34: NA | AN34: La donnée est obligatoire | AO34: The data is mandatory | AP34: 7 | AQ34: TPG0001 | AR34: Si elle est renseignée, la valeur doit être connue du Langage Commun associé | AS34: If specified, the value must be known to the associated Common Language | AT34: 7 | AU34: TIG0001
A35: A1 | B35: 17 | C35: 16 - Identification Tiers | D35: 16 - Third party identification | E35: A1 2.5 | F35: Echelon de qualité de crédit de la Contrepartie/Emetteur | G35: Issuer/ Counterparty credit quality level | H35: Echelon de qualité de crédit de la Contrepartie/Emetteur | I35: Issuer/ Counterparty credit quality level | P35: ND | Q35: ND | R35: cdEchelQualCreCtp | S35: Facultatif | T35: Optional | U35: LC.0178 | V35: TA KVECHLON | W35: NA | X35: NA | Y35: ALPHA | Z35: NA | AA35: NA | AB35: 1 | AC35: NA | AD35: 40 | AE35: NA | AF35: NA | AG35: CALCULS PRUDENTIELS | AH35: ND | AI35: N | AJ35: NA | AK35: NA | AL35: NA | AR35: Si elle est renseignée, la valeur doit être connue du Langage Commun associé | AS35: If specified, the value must be known to the associated Common Language | AT35: 7 | AU35: TIG0001
A36: A1 | B36: 18 | C36: 16 - Identification Tiers | D36: 16 - Third party identification | E36: A1 2.6 | F36: Code ISIN pour les opérations sur titres | G36: ISIN code for securities transactions | H36: Le code ISIN (International Securities Identification Numbers) est un identifiant unique, propre à chaque actif financier (actions, obligations, produits monétaires, OPCVM, warrants...) Le code ISIN est composé de deux lettres indiquant le pays d'émission du titre (FR pour la France) et de dix chiffres propres à chaque titre | I36: The ISIN code (International Securities Identification Numbers) is a single ID, peculiar to each financial asset (share, bond, currency product, UCITS, warrants, etc.) The ISIN code includes two letters for the country (FR for France) and ten figures peculiar to each security | P36: ND | Q36: ND | R36: cdISIN | S36: Obligatoire sous conditions | T36: Mandatory under conditions | U36: NA | V36: NA | W36: Toutes les opérations sur titres (titre détenu, repo, reverse, prêts, emprunts, OPCVM, …) doivent être remontées à une maille granulaire par code ISIN | X36: All securities transactions (securities held, repo, reverse, loans, borrowings, UCITS, etc.) must be traced back to a granular mesh by ISIN code | Y36: ALPHA | Z36: NA | AA36: NA | AB36: 12 | AC36: NA | AD36: 40 | AE36: NA | AF36: 45.00 | AG36: CALCULS PRUDENTIELS, ESG PILIER 3, LIQUIDITE | AH36: ND | AI36: N | AJ36: NA | AK36: NA | AL36: NA | AN36: La donnée est obligatoire, si Type de produit bancaire [A1 3.7] = 'EMTI01, PRTI01, REPO01, RREP01, TDET*' | AO36: The data is mandatory, if Banking Product type [A1 3.7] = 'EMTI01, PRTI01, REPO01, RREP01, TDET*' | AP36: 7 | AQ36: TBD | AV36: Si la donnée est renseignée, alors la donnée doit commencer par 2 caractères alphabétiques et avoir une longueur de 12 caractères avec un caractère numérique pour le dernier caractère ET la donnée doit être validée comme un code ISIN à l'aide de l'algorithme de Luhn | AW36: If filled, then the data must start with 2 alphabetic characters and have a length of 12 characters with a numeric character for the last character AND the data must be validated as an ISIN code using the Luhn algorithm | AX36: 6 | AY36: TVG0006
A37: A1 | B37: 19 | C37: 16 - Identification Tiers | D37: 16 - Third party identification | E37: A1 2.7 | F37: Nombre de contreparties | G37: Number of counterparties | H37: Nombre de contreparties constituant l'encours dégradé | I37: Number of counterparties which forms the degraded outstanding | P37: ND | Q37: ND | R37: nbCtp | S37: Facultatif | T37: Optional | U37: NA | V37: NA | W37: Il s'agit du nombre de contreparties constituant l'encours dégradé | X37: Number of counterparties which forms the degraded outstanding | Y37: ALPHA | Z37: NA | AA37: NA | AB37: 8 | AC37: NA | AD37: 40 | AE37: NA | AF37: NA | AG37: CALCULS PRUDENTIELS | AH37: ND | AI37: N | AJ37: NA | AK37: NA | AL37: NA
A38: A1 | B38: 20 | C38: 16 - Identification Tiers | D38: 16 - Third party identification | E38: A1 2.99 | F38: Zone libre | G38: Free zone | H38: Zone libre | I38: Free zone | P38: NA | Q38: NA | R38: ZoneLibre2 | S38: NA | T38: NA | U38: NA | V38: NA | W38: NA | X38: NA | Y38: ALPHA | Z38: NA | AA38: NA | AB38: 30 | AC38: NA | AD38: 40 | AE38: 41 | AF38: NA | AG38: NA | AH38: NA | AI38: N | AJ38: NA | AK38: NA | AL38: NA
A39: A1 | B39: 21 | C39: 03 - Caractéristiques Générales | D39: 03 - General characteristics | E39: A1 3.1 | F39: Méthodologie Bâloise | G39: Basel methodology | H39: Correspond à la méthode de calcul des risques pondérés dans Bâle | I39: Represents the risk-weighted asset calculation method in Basel | P39: ND | Q39: ND | R39: cdMetBal | S39: Obligatoire | T39: Mandatory | U39: LC.0068 | V39: TA KVBAL22 | W39: La seule valeur autorisée est : - STD (STANDARD) | X39: The only permitted value is: - STD (STANDARDISED) | Y39: ALPHA | Z39: NA | AA39: NA | AB39: 7 | AC39: NA | AD39: 40 | AE39: NA | AF39: NA | AG39: CALCULS PRUDENTIELS, ESG PILIER 3, NPE | AH39: ND | AI39: N | AJ39: NA | AK39: NA | AL39: NA | AN39: La donnée est obligatoire | AO39: The data is mandatory | AP39: 7 | AQ39: TPG0001 | AR39: Si elle est renseignée, la valeur doit être connue du Langage Commun associé | AS39: If specified, the value must be known to the associated Common Language | AT39: 7 | AU39: TIG0001 | AV39: Si renseignée, la donnée doit être égale à 'STD' | AW39: If filled, data must be equal to 'STD' | AX39: 7 | AY39: TVS0750
A40: A1 | B40: 22 | C40: 03 - Caractéristiques Générales | D40: 03 - General characteristics | E40: A1 3.5 | F40: Traitement moteur bâlois | G40: Basel engine treatment | H40: Correspond au traitement moteur de calcul des RWA Bâlois | I40: Represents treatment by the Basel RWA calculation engine | P40: ND | Q40: ND | R40: cdTraitMot | S40: Obligatoire | T40: Mandatory | U40: LC.0154 | V40: TA KVTBALE | W40: NA | X40: NA | Y40: ALPHA | Z40: NA | AA40: NA | AB40: 2 | AC40: NA | AD40: 40 | AE40: NA | AF40: NA | AG40: CALCULS PRUDENTIELS | AH40: ND | AI40: N | AJ40: NA | AK40: NA | AL40: NA | AN40: La donnée est obligatoire | AO40: The data is mandatory | AP40: 7 | AQ40: TPG0001 | AR40: Si elle est renseignée, la valeur doit être connue du Langage Commun associé | AS40: If specified, the value must be known to the associated Common Language | AT40: 7 | AU40: TIG0001 | AV40: Si renseignée, la donnée doit être égale à '01' (réglementaire) ou '07' (simulation) | AW40: If filled, data must be equal to '01' (regulatory) or '07' (simulation) | AX40: 7 | AY40: TVS0751
A41: A1 | B41: 23 | C41: 03 - Caractéristiques Générales | D41: 03 - General characteristics | E41: A1 3.98 | F41: Zone libre | G41: Free zone | H41: Zone libre | I41: Free zone | P41: NA | Q41: NA | R41: ZoneLibre3_98 | S41: NA | T41: NA | U41: NA | V41: NA | W41: NA | X41: NA | Y41: ALPHA | Z41: NA | AA41: NA | AB41: 5 | AC41: NA | AD41: 40 | AE41: 41 | AF41: NA | AG41: NA | AH41: NA | AI41: N | AJ41: NA | AK41: NA | AL41: NA
A42: A1 | B42: 24 | C42: 03 - Caractéristiques Générales | D42: 03 - General characteristics | E42: A1 3.2 | F42: NATO de l'exposition | G42: NATure of Operation (NATO) for exposure | H42: Correspond à la classification de l'encours selon la nomenclature Groupe CA "NATO" commune aux Risques et à la Comptabilité | I42: Represents the classification of outstanding amounts on the basis of the CA Group shared Risk and Accounting "NATO" (transaction nature) nomenclature | P42: ND | Q42: ND | R42: cdNatOp | S42: Obligatoire | T42: Mandatory | U42: LC.0064 | V42: TA H8NATOPE | W42: NA | X42: NA | Y42: ALPHA | Z42: NA | AA42: NA | AB42: 12 | AC42: NA | AD42: 40 | AE42: NA | AF42: NA | AG42: CALCULS PRUDENTIELS, ESG PILIER 3, NPE | AH42: ND | AI42: N | AJ42: NA | AK42: NA | AL42: NA | AN42: La donnée est obligatoire | AO42: The data is mandatory | AP42: 7 | AQ42: TPG0001 | AR42: Si elle est renseignée, la valeur doit être connue du Langage Commun associé | AS42: If specified, the value must be known to the associated Common Language | AT42: 7 | AU42: TIG0001 | AV42: Si renseignée, la donnée ne doit pas appartenir à la famille de NATO 'NAT08' --- Si 'Code ISIN pour OPCVM' [A1 2.6] est renseignée, alors la donnée doit être égale à 'NA330' | AW42: If filled, the data must not be part of NATO family 'NAT08' --- If 'UCITS ISIN code' [A1 2.6] is filled, then data must be equal to 'NA330' | AX42: 7 6 | AY42: TVS0752 TVS0754 | AZ42: La donnée doit correspondre à la donnée [A1 3.1] liée dans Table H8NATOPE (H8IRB, H8STD, H8IRBF) --- La donnée doit correspondre à la donnée [A1 2.1] liée dans Table H8CAPNAT (H8CAP) | BA42: Data must match with data [A1 3.1] linked in H8NATOPE table (H8IRB, H8STD, H8IRBF) --- Data must match with data [A1 2.1] linked in table H8CAPNAT (H8CAP) | BB42: 7 | BC42: TCS0764 TCS0765 | BH42: Si la combinaison de donnée n'est pas trouvée dans la matrice des règles de gestion C11, le contrôle doit se lever --- Si la combinaison de donnée n'est pas trouvée dans la matrice des règles de gestion C26, le contrôle doit se lever | BI42: If the data combinaison is not found in the C11 business rules matrix, the control must trigger --- If the data combinaison is not found in the C26 business rules matrix, the control must trigger | BJ42: 6 | BK42: TC0C11 TC0C26
A43: A1 | B43: 25 | C43: 03 - Caractéristiques Générales | D43: 03 - General characteristics | E43: A1 3.3 | F43: Devise de liasse | G43: Package currency | H43: Le champ correspond à la devise comptable de reporting de l'entité porteuse de risque | I43: The field represents the reporting accounting currency of the risk bearing entity | P43: ND | Q43: ND | R43: cdDev | S43: Obligatoire | T43: Mandatory | U43: LC.0005 | V43: TA NM253 | W43: Toutes les données de type "Montant" doivent être valorisées et restituées dans cette devise | X43: All “Amount” type data must be measured and input in this currency | Y43: ALPHA | Z43: NA | AA43: NA | AB43: 3 | AC43: NA | AD43: 40 | AE43: NA | AF43: 45.00 | AG43: CALCULS PRUDENTIELS, LIQUIDITE, NPE | AH43: ND | AI43: N | AJ43: NA | AK43: NA | AL43: NA | AN43: La donnée est obligatoire | AO43: The data is mandatory | AP43: 7 | AQ43: TPG0001 | AR43: Si elle est renseignée, la valeur doit être connue du Langage Commun associé | AS43: If specified, the value must be known to the associated Common Language | AT43: 7 | AU43: TIG0001 | AZ43: La donnée doit être égale à la devise de l'entité Porteuse de Risques [0.2 (A1)] renseignée dans H8PECO (RB 0990 H8DEVENT) | BA43: Data must be equal to Entity Id [0.2 (A1)] currency in H8PECO (RB 0990 H8DEVENT) | BB43: 7 | BC43: TCS0766
A44: A1 | B44: 26 | C44: 03 - Caractéristiques Générales | D44: 03 - General characteristics | E44: A1 3.4 | F44: Portefeuille de booking / Intention de Gestion | G44: Booking portfolio / Management intent | H44: Classification de l'opération dans le portefeuille bancaire (Banking book) ou portefeuille de négociation (Trading book) selon les normes Bâle | I44: Classification of the transaction in the Banking book or Trading book pursuant to Basel standards | P44: ND | Q44: ND | R44: cdIntGest | S44: Obligatoire | T44: Mandatory | U44: LC.0029 | V44: TA KVINTENT | W44: Cette information permet d'identifier en particulier les titres de dettes qui doivent être exclus du traitement de calcul des emplois pondérés | X44: This information makes it possible to identify in particular the debt securities that must be excluded from the treatment of the calculation of risk-weighted assets | Y44: ALPHA | Z44: NA | AA44: NA | AB44: 1 | AC44: NA | AD44: 40 | AE44: NA | AF44: 45.00 | AG44: CALCULS PRUDENTIELS, ESG PILIER 3, LIQUIDITE | AH44: ND | AI44: N | AJ44: NA | AK44: NA | AL44: NA | AN44: La donnée est obligatoire | AO44: The data is mandatory | AP44: 7 | AQ44: TPG0001 | AR44: Si elle est renseignée, la valeur doit être connue du Langage Commun associé | AS44: If specified, the value must be known to the associated Common Language | AT44: 7 | AU44: TIG0001
A45: A1 | B45: 27 | C45: 03 - Caractéristiques Générales | D45: 03 - General characteristics | E45: A1 3.6 | F45: Ligne Métier | G45: Business line | H45: Classification de l'opération selon la ligne Métier | I45: Classification of the transaction by business line | P45: ND | Q45: ND | R45: cdLm | S45: Obligatoire (SC) | T45: Mandatory (SC) | U45: LC.0033 | V45: TA KVMETIER | W45: Nomenclature définie par CACIB. Permet de distinguer les encours par ligne métier dans les outils de consolidation risques et notamment la distinction des lignes métier Leasing et Affacturage. | X45: Nomenclature defined by CACIB. Allows to distinguish the outstandings by business line in the risk consolidation tools and in particular the distinction of business lines Leasing and Factoring | Y45: ALPHA | Z45: NA | AA45: NA | AB45: 5 | AC45: NA | AD45: 41 | AE45: NA | AF45: 45.00 | AG45: CALCULS PRUDENTIELS, LIQUIDITE, NPE | AH45: ND | AI45: N | AJ45: NA | AK45: NA | AL45: NA | AR45: Si elle est renseignée, la valeur doit être connue du Langage Commun associé | AS45: If specified, the value must be known to the associated Common Language | AT45: 7 | AU45: TIG0001
A46: A1 | B46: 28 | C46: 03 - Caractéristiques Générales | D46: 03 - General characteristics | E46: A1 3.7 | F46: Type de produit bancaire | G46: Banking Product type | H46: Classification des produits bancaires et financiers | I46: Classification of products covering the entities's entire balance sheet (assets and liabilities) | P46: ND | Q46: ND | R46: TypProdCd | S46: Obligatoire | T46: Mandatory | U46: LC.0303 | V46: TA Z8PRODUI | W46: Valeur admise : ' CPTA01' (COMPLEMENT COMPTABLE) | X46: Permitted value: 'CPTA01' (ACCOUNTING SUPPLEMENT) | Y46: ALPHA | Z46: NA | AA46: NA | AB46: 6 | AC46: NA | AD46: 43 | AE46: NA | AF46: 45.00 | AG46: CALCULS PRUDENTIELS, LIQUIDITE | AH46: ND | AI46: N | AJ46: NA | AK46: NA | AL46: NA | AN46: La donnée est obligatoire | AO46: The data is mandatory | AP46: 7 | AQ46: TPG0001 | AR46: Si elle est renseignée, la valeur doit être connue du Langage Commun associé | AS46: If specified, the value must be known to the associated Common Language | AT46: 7 | AU46: TIG0001 | AZ46: Le type de produit bancaire doit être cohérent avec le type d'enregistrement (la colonne Z8OMZPFR lié au type de produit de la table Z8COPROM doit correspondre à l'objet métier concerné) | BA46: The value filled must be consistent with the business object (LC.0303 - TA 0990 Z8COPROM) | BB46: 7 | BC46: TCG0001
A47: A1 | B47: 29 | C47: 03 - Caractéristiques Générales | D47: 03 - General characteristics | E47: A1 3.8 | F47: Code entité de la succursale à l'origine de l'opération | G47: Entity code of the branch that originated the transaction | H47: Code consolidation de la succursale qui a fait l'opération/contrat dans le cas où les engagements sont portés par la maison mère | I47: Consolidation code of the branch that has made the transaction/contract in case the commitments are carried out by the parent company | P47: ND | Q47: ND | R47: CdEntSucc | S47: Facultatif | T47: Optional | U47: LC.0475 | V47: TA H8ENTITY | W47: NA | X47: NA | Y47: ALPHA | Z47: NA | AA47: NA | AB47: 5 | AC47: NA | AD47: 43 | AE47: NA | AF47: NA | AG47: CALCULS PRUDENTIELS, NPE | AH47: ND | AI47: N | AJ47: NA | AK47: NA | AL47: NA | AR47: Si elle est renseignée, la valeur doit être connue du Langage Commun associé | AS47: If specified, the value must be known to the associated Common Language | AT47: 7 | AU47: TIG0001
A48: A1 | B48: 30 | C48: 03 - Caractéristiques Générales | D48: 03 - General characteristics | E48: A1 3.99 | F48: Zone libre | G48: Free zone | H48: Zone libre | I48: Free zone | P48: NA | Q48: NA | R48: ZoneLibre3 | S48: NA | T48: NA | U48: NA | V48: NA | W48: NA | X48: NA | Y48: ALPHA | Z48: NA | AA48: NA | AB48: 14 | AC48: NA | AD48: 43 | AE48: 41 | AF48: NA | AG48: NA | AH48: NA | AI48: N | AJ48: NA | AK48: NA | AL48: NA
A49: A1 | B49: 31 | C49: 03 - Caractéristiques Générales | D49: 03 - General characteristics | E49: A1 4.1 | F49: Nature du sous-jacent | G49: Nature of underlying | H49: Le champ correspond à la nature du sous-jacent de l'exposition | I49: The field represents the nature of the exposure underlying | P49: ND | Q49: ND | R49: cdNatSJ | S49: Facultatif | T49: Optional | U49: LC.0046 | V49: TA KVNSJACE | W49: NA | X49: NA | Y49: ALPHA | Z49: NA | AA49: NA | AB49: 2 | AC49: NA | AD49: 40 | AE49: NA | AF49: 45.00 | AG49: CALCULS PRUDENTIELS, LIQUIDITE | AH49: ND | AI49: N | AJ49: NA | AK49: NA | AL49: NA | AR49: Si elle est renseignée, la valeur doit être connue du Langage Commun associé | AS49: If specified, the value must be known to the associated Common Language | AT49: 7 | AU49: TIG0001
A50: A1 | B50: 32 | C50: 03 - Caractéristiques Générales | D50: 03 - General characteristics | E50: A1 4.2 | F50: Produits à pondération préférentielle | G50: Products with preferred weighting | H50: Le champ permet d'identifier certains engagements (Repos,...) bénéficiant d'un traitement spécifique sous réserve du respect de certaines conditions | I50: The field makes it possible to identify certain commitments (Repos, Equities) enjoying special treatment subject to satisfaction of certain conditions | P50: ND | Q50: ND | R50: cdProdPondePref | S50: Facultatif | T50: Optional | U50: LC.0149 | V50: TA KVPPREF | W50: A renseigner uniquement sous conditions pour les Repos, P/E de titres | X50: To only be filled in under certain circumstances for Repos, Lending / Borrowing of securities | Y50: ALPHA | Z50: NA | AA50: NA | AB50: 2 | AC50: NA | AD50: 40 | AE50: NA | AF50: NA | AG50: CALCULS PRUDENTIELS | AH50: ND | AI50: N | AJ50: NA | AK50: NA | AL50: NA | AR50: Si elle est renseignée, la valeur doit être connue du Langage Commun associé | AS50: If specified, the value must be known to the associated Common Language | AT50: 7 | AU50: TIG0001
A51: A1 | B51: 33 | C51: 03 - Caractéristiques Générales | D51: 03 - General characteristics | E51: A1 4.3 | F51: Indicateur LFD (Libellé et financé dans la devise de l'emprunteur) | G51: LFD Indicator (Denominated and financed in the borrower's currency) | H51: Le champ permet de préciser si la créance est libellée et financée dans la devise de l'emprunteur | I51: The field makes it possible to indicate if the claim is denominated and financed in the borrower's currency | P51: ND | Q51: ND | R51: indLFD | S51: Obligatoire sous conditions | T51: Mandatory under conditions | U51: LC.0179 | V51: TA KVILFD | W51: Ne concerne que les expositions sur les Administrations centrales et Banques centrales et sur les Établissements Cette donnée est utilisée parmi d'autres critères et permet d'affecter des pondérations préférentielles | X51: Only relate to exposures vis-à-vis central governments and central banks and vis-à-vis Institutions This data is used among other criteria and makes it possible to assign preferred weightings | Y51: ALPHA | Z51: NA | AA51: NA | AB51: 1 | AC51: NA | AD51: 40 | AE51: NA | AF51: 45.00 | AG51: CALCULS PRUDENTIELS | AH51: ND | AI51: N | AJ51: NA | AK51: NA | AL51: NA | AN51: La donnée est obligatoire, si 'CAP de l'exposition' [A1 2.1] = (‘12','13','23', ‘24', ‘25', ‘26', ‘40', ‘41', ‘42') | AO51: The data is mandatory if CAP of exposure [A1 2.1] = (‘12','13','23', ‘24', ‘25', ‘26', ‘40', ‘41', ‘42') | AP51: 6 | AQ51: TPS1785 | AR51: Si elle est renseignée, la valeur doit être connue du Langage Commun associé | AS51: If specified, the value must be known to the associated Common Language | AT51: 7 | AU51: TIG0001
A52: A1 | B52: 34 | C52: 03 - Caractéristiques Générales | D52: 03 - General characteristics | E52: A1 4.4 | F52: Indicateur de maturité résiduelle | G52: Remaining maturity indicator | H52: Le champ permet de préciser la maturité résiduelle de l'opération | I52: The field makes it possible to indicate if the transaction remaining maturity | P52: ND | Q52: ND | R52: indMatRes | S52: Obligatoire sous conditions | T52: Mandatory under conditions | U52: LC.0161 | V52: TA KVMATRES | W52: NA | X52: NA | Y52: ALPHA | Z52: NA | AA52: NA | AB52: 1 | AC52: NA | AD52: 40 | AE52: NA | AF52: 45.00 | AG52: CALCULS PRUDENTIELS, ESG PILIER 3 | AH52: ND | AI52: N | AJ52: NA | AK52: NA | AL52: NA | AN52: La donnée est obligatoire, si ['CAP de l'exposition' [A1 2.1] = (‘12', '23', ‘24', ‘25', ‘26', ‘40', ‘41', ‘42')] OU ['NATO de l'exposition' [A1 3.2] = ('NAT10')] | AO52: The data is mandatory if ['CAP of exposure' [A1 2.1] = (‘12', '23', ‘24', ‘25', ‘26', ‘40', ‘41', ‘42')] OR ['NATure of Operation' [A1 3.2] = ('NAT10')] | AP52: 6 | AQ52: TPS1786 | AR52: Si elle est renseignée, la valeur doit être connue du Langage Commun associé | AS52: If specified, the value must be known to the associated Common Language | AT52: 7 | AU52: TIG0001
A53: A1 | B53: 35 | C53: 08 - Caractéristiques d'arriérés et de restructuration | D53: 08 - Characteristics of overdues and restructuring | E53: A1 4.14 | F53: Indicateur Engagement en défaut | G53: Defaulted commitments indicator | H53: Indicateur permettant de préciser si les opérations sont comptabilisées en engagement en défaut | I53: ndicator to specify whether transactions are recognised as defaulted commitments | P53: ND | Q53: ND | R53: cdIndEngDout | S53: Obligatoire | T53: Mandatory | U53: LC.0175 | V53: TA KVIED | W53: NA | X53: NA | Y53: ALPHA | Z53: NA | AA53: NA | AB53: 1 | AC53: NA | AD53: 40 | AE53: NA | AF53: 45.00 | AG53: CALCULS PRUDENTIELS, ESG PILIER 3, LIQUIDITE, NPE | AH53: ND | AI53: N | AJ53: NA | AK53: NA | AL53: NA | AN53: La donnée est obligatoire | AO53: The data is mandatory | AP53: 7 | AQ53: TPG0001 | AR53: Si elle est renseignée, la valeur doit être connue du Langage Commun associé | AS53: If specified, the value must be known to the associated Common Language | AT53: 7 | AU53: TIG0001
A54: A1 | B54: 36 | C54: 08 - Caractéristiques d'arriérés et de restructuration | D54: 08 - Characteristics of overdues and restructuring | E54: A1 4.15 | F54: Indicateur de passage en défaut | G54: Default grade indicator | H54: Cet indicateur permet d'identifier les engagements entrés en défaut ou impayés prudentiels depuis le dernier arrêté trimestriel | I54: Enables to identify commitments in default or prudential outstanding payments since the latest quarterly closing | P54: ND | Q54: ND | R54: cdIndPassDef | S54: Obligatoire | T54: Mandatory | U54: LC.0180 | V54: TA KVIPED | W54: NA | X54: NA | Y54: ALPHA | Z54: NA | AA54: NA | AB54: 1 | AC54: NA | AD54: 40 | AE54: NA | AF54: 45.00 | AG54: CALCULS PRUDENTIELS, ESG PILIER 3, NPE | AH54: ND | AI54: N | AJ54: NA | AK54: NA | AL54: NA | AN54: La donnée est obligatoire | AO54: The data is mandatory | AP54: 6 | AQ54: TPG0001 | AR54: Si elle est renseignée, la valeur doit être connue du Langage Commun associé | AS54: If specified, the value must be known to the associated Common Language | AT54: 7 | AU54: TIG0001
A55: A1 | B55: 37 | C55: 08 - Caractéristiques d'arriérés et de restructuration | D55: 08 - Characteristics of overdues and restructuring | E55: A1 4.5 | F55: Durée initiale ≤ 3 mois | G55: Initial maturity ≤ 3 months | H55: Le champ permet de préciser si la maturité initiale de l'opération est inférieure ou égale à 3 mois | I55: The field makes it possible to indicate if the initial maturity of the transaction is under or equal to 3 months | P55: ND | Q55: ND | R55: indMatInf3Mois | S55: Facultatif | T55: Optional | U55: NA | V55: NA | W55: Ne concerne que les expositions sur les Etablissements - ‘Y' : maturité initiale ≤ 3 mois - ‘N' : maturité initiale > 3 mois Cette donnée est utilisée parmi d'autres critères (LFD, ..) pour déterminer la pondération | X55: Only relates to exposures vis-à-vis Institutions - 'Y': initial maturity ≤ 3 months - 'N': initial maturity > 3 months This data is used among other criteria (LFD, ..) to determine the weighting | Y55: ALPHA | Z55: NA | AA55: NA | AB55: 1 | AC55: NA | AD55: 40 | AE55: NA | AF55: 45.00 | AG55: USAGE ZP | AH55: ND | AI55: N | AJ55: NA | AK55: NA | AL55: NA | AV55: Si renseignée, alors la donnée doit être égale à 'Y' ou 'N' | AW55: If is filled, then data must be equal to 'Y' or 'N' | AX55: 7 | AY55: TVS0755
A56: A1 | B56: 38 | C56: 18 - Caractéristiques Titrisation | D56: 18 - Securitization characteristics | E56: A1 4.6 | F56: Taux de pondération de l'exposition de titrisation | G56: Weighting ratio of the security exposure | H56: Taux de pondération de l'exposition de titrisation. Exprimé en % | I56: Weighting ratio of the security exposure. Expressed as % | P56: ND | Q56: ND | R56: txPondeOrig | S56: Obligatoire sous conditions | T56: Mandatory under conditions | U56: NA | V56: NA | W56: Correspond au taux de pondération à appliquer sur les expositions de titrisation (CAP15) Par défaut, sur les expositions de titrisation, pondération à 1250% Exprimé en % | X56: Represents the weighting ratio to apply to securitisation exposures (CAP15) By default, securitisation exposures, weighted at 1250% Expressed as % | Y56: NUM | Z56: 10 dont signe et 5 décimales | AA56: 10 including sign and 5 decimals | AB56: 10 | AC56: NA | AD56: 40 | AE56: NA | AF56: NA | AG56: CALCULS PRUDENTIELS | AH56: ND | AI56: N | AJ56: NA | AK56: NA | AL56: NA | AN56: La donnée est obligatoire, si 'CAP de l'exposition' [A1 2.1] = (‘15', '16', '95') | AO56: The data is mandatory if 'CAP of exposure' [A1 2.1] = (‘15', '16', '95) | AP56: 6 | AQ56: TPS1788 | AV56: Si renseignée, la donnée doit être positive (supérieure ou égale à 0) | AW56: If filled, data must be positive (greater or equal to 0) | AX56: 7 | AY56: TVG0001
A57: A1 | B57: 39 | C57: 03 - Caractéristiques Générales | D57: 03 - General characteristics | E57: A1 4.7 | F57: CCF (Crédit Conversion Factor) | G57: Credit Conversion Factor (CCF) | H57: CCF (Crédit Conversion Factor) | I57: Credit Conversion Factor (CCF) | P57: ND | Q57: ND | R57: txCCF | S57: Obligatoire sous conditions | T57: Mandatory under conditions | U57: NA | V57: NA | W57: A renseigner uniquement pour les opérations de hors-bilan Le champ correspond au facteur de conversion des opérations de hors-bilan (engagement de financement et de garantie,…) Si inconnu laisser le champ vide | X57: To only be filled in for off-balance sheet transactions The field represents the conversion factor for off-balance sheet transactions (financing and guarantee commitment,…) If unknown leave empty | Y57: NUM | Z57: 10 dont signe et 5 décimales | AA57: 10 including sign and 5 decimals | AB57: 10 | AC57: NA | AD57: 40 | AE57: NA | AF57: NA | AG57: CALCULS PRUDENTIELS, NPE | AH57: ND | AI57: N | AJ57: NA | AK57: NA | AL57: NA | AN57: La donnée est obligatoire, si 'NATO de l'exposition' [A1 3.2] = ('NAT06' ou 'NAT07') | AO57: The data is mandatory if 'NATure of Operation (NATO) for exposure' [A1 3.2] = ('NAT06' or 'NAT07') | AP57: 6 | AQ57: TPS1789 | AV57: Si renseignée, la donnée doit être positive (supérieure ou égale à 0) | AW57: If filled, data must be positive (greater or equal to 0) | AX57: 7 | AY57: TVG0001
A58: A1 | B58: 40 | C58: 19 - Données comptables | D58: 19 - Accounting data | E58: A1 4.8 | F58: Numéro du PCCO 1 | G58: Number of PCCO 1 | H58: Le champ correspond au code du compte consolidé | I58: The field represents the consolidated account code | P58: ND | Q58: ND | R58: noPCCO1 | S58: Obligatoire sous conditions | T58: Mandatory under conditions | U58: LC.0111 | V58: TA H8PCCO | W58: - Pour les NAT01 / NAT02 / NAT03, il faut renseigner le PCCO du bilan - Pour les dérivés (NAT10), il faut renseigner le PCCO du bilan (MtM) - Pour les NAT06 et NAT 07, il faut renseigner le PCCO du hors-bilan - Pour les cessions temporaires (NAT04), il faut renseigner le PCCO correspond à la jambe prêteuse | X58: - For NAT01 / NAT02 / NAT03, the balance sheet PCCO must be input - For derivatives (NAT10), the balance sheet PCCO (MtM) must be input - For NAT06 and NAT 07, the off-balance sheet PCCO must be input - For temporary sales (NAT04), the PCCO corresponding to the lending leg must be input | Y58: ALPHA | Z58: NA | AA58: NA | AB58: 12 | AC58: NA | AD58: 40 | AE58: NA | AF58: 45.00 | AG58: CALCULS PRUDENTIELS, LIQUIDITE | AH58: ND | AI58: N | AJ58: NA | AK58: NA | AL58: NA | AN58: La donnée est obligatoire, si le 'Montant du PCCO 1' [A1 4.9] est renseigné et différent de 0 | AO58: The data is mandatory, if 'Amount of PCCO 1' [A1 4.9] is filled and different of 0 | AP58: 6 | AQ58: TPS1790 | AR58: Si elle est renseignée, la valeur doit être connue du Langage Commun associé | AS58: If specified, the value must be known to the associated Common Language | AT58: 7 | AU58: TIG0001 | AZ58: Le couple H8PCCO/H8NATO (correspondant au Numéro du PCCO 1 [A1 4.8] et à la NATO de l'exposition [A1 3.2]) doit exister dans la table START H8PCNATO, avec H8NATO composé des 5 premiers caractères | BA58: The H8PCCO/H8NATO pair (corresponding to Number of PCCO 1 [A1 4.8] and NATure of Operation (NATO) for exposure [A1 3.2]) must exist in the START table H8PCNATO, with H8NATO 5 first posititions | BB58: 6 | BC58: TCS0767
A59: A1 | B59: 41 | C59: 19 - Données comptables | D59: 19 - Accounting data | E59: A1 4.9 | F59: Montant du PCCO 1 | G59: Amount of PCCO 1 | H59: Montant du PCCO 1 | I59: Amount of PCCO 1 | P59: ND | Q59: ND | R59: mtPCCO1 | S59: Obligatoire | T59: Mandatory | U59: NA | V59: NA | W59: Ce champ correspond à la valeur comptable (tout ou partie du solde) du PCCO1 Pour le crédit-bail, il s'agit du montant des loyers hors Valeur Résiduelle Pour un titre déprécié, comptabilisé en coût historique, il s'agit du montant du coût d'acquisition, augmenté le cas échéant du montant d'ajustement de valeur | X59: This field represents the accounting value (all or part of the balance) of PCCO1 For leasing (Amount of lease payments excluding Residual Value) For the impaired security, recognized at historical cost, this is the cost of acquisition, plus the Value Adjustment if needed | Y59: NUM | Z59: 19 dont signe et 2 décimales | AA59: 19 including sign and 2 decimals | AB59: 19 | AC59: NA | AD59: 40 | AE59: NA | AF59: 45.00 | AG59: CALCULS PRUDENTIELS, ESG PILIER 3, LIQUIDITE | AH59: ND | AI59: N | AJ59: NA | AK59: NA | AL59: NA | AN59: La donnée est obligatoire | AO59: The data is mandatory | AP59: 7 | AQ59: TPG0001 | AV59: Si la donnée est renseignée, et si Application source [0.3 (A1)] <> 'ACORE', alors la donnée doit être positive (>= à 0). | AW59: If data is filled, and if Source application [0.3 (A1)] <> 'ACORE', then data must be positive (>= 0). | AX59: 7 | AY59: TVS0756
A60: A1 | B60: 42 | C60: 19 - Données comptables | D60: 19 - Accounting data | E60: A1 4.10 | F60: Numéro du PCCO 2 | G60: Number of PCCO 2 | H60: Le champ correspond au code du compte consolidé | I60: The field represents the consolidated account code | P60: ND | Q60: ND | R60: noPCCO2 | S60: Obligatoire sous conditions | T60: Mandatory under conditions | U60: LC.0111 | V60: TA H8PCCO | W60: Ne concerne que les IFT et les Repos - Pour les dérivés (NAT10), il faut renseigner le PCCO du hors bilan (Notionnel) - Pour les cessions temporaires (NAT04), il faut renseigner le PCCO correspondant à la jambe emprunteuse | X60: Only relates to Forward Financial Instruments and Repos - For derivatives (NAT10), the off-balance sheet PCCO (Notional) must be input - For temporary sales (NAT04), the PCCO corresponding to the borrowing leg must be input | Y60: ALPHA | Z60: NA | AA60: NA | AB60: 12 | AC60: NA | AD60: 40 | AE60: NA | AF60: 45.00 | AG60: CALCULS PRUDENTIELS, LIQUIDITE | AH60: ND | AI60: N | AJ60: NA | AK60: NA | AL60: NA | AN60: La donnée est obligatoire, si le 'Montant du PCCO 2' [A1 4.11] est renseigné et différent de 0 | AO60: The data is mandatory, if 'Amount of PCCO 2' [A1 4.11] is filled and different of 0 | AP60: 6 | AQ60: TPS1791 | AR60: Si elle est renseignée, la valeur doit être connue du Langage Commun associé | AS60: If specified, the value must be known to the associated Common Language | AT60: 7 | AU60: TIG0001 | AZ60: Le couple H8PCCO/H8NATO (correspondant au Numéro du PCCO 2 [A1 4.10] et à la NATO de l'exposition [A1 3.2]) doit exister dans la table START H8PCNATO, avec H8NATO composé des 5 premiers caractères | BA60: The H8PCCO/H8NATO pair (corresponding to Number of PCCO 2 [A1 4.10] and NATure of Operation (NATO) for exposure [A1 3.2]) must exist in the START table H8PCNATO, with H8NATO 5 first posititions | BB60: 6 | BC60: TCS0768
A61: A1 | B61: 43 | C61: 19 - Données comptables | D61: 19 - Accounting data | E61: A1 4.11 | F61: Montant du PCCO 2 | G61: Amount of PCCO 2 | H61: Montant du PCCO 2 | I61: Amount of PCCO 2 | P61: ND | Q61: ND | R61: mtPCCO2 | S61: Obligatoire sous conditions | T61: Mandatory under conditions | U61: NA | V61: NA | W61: Ce champ correspond à la valeur comptable (tout ou partie du solde) du PCCO2 | X61: This field represents the accounting value (all or part of the balance) of PCCO2 | Y61: NUM | Z61: 19 dont signe et 2 décimales | AA61: 19 including sign and 2 decimals | AB61: 19 | AC61: NA | AD61: 40 | AE61: NA | AF61: 45.00 | AG61: CALCULS PRUDENTIELS, LIQUIDITE | AH61: ND | AI61: N | AJ61: NA | AK61: NA | AL61: NA | AN61: La donnée est obligatoire, si 'NATO de l'exposition' [A1 3.2] = ('NAT10') --- La donnée est obligatoire, si 'NATO de l'exposition' [A1 3.2] = ('NAT04') | AO61: The data is mandatory, if 'NATure of Operation (NATO) for exposure' [A1 3.2] = ('NAT10') --- The data is mandatory, if 'NATure of Operation (NATO) for exposure' [A1 3.2] = ('NAT04') | AP61: 7 6 | AQ61: TPS1792 TPS1793 | AV61: Si la donnée est renseignée, et si Application source [0.3 (A1)] <> 'ACORE', alors la donnée doit être positive (>= à 0). | AW61: If data is filled, and if Source application [0.3 (A1)] <> 'ACORE', then data must be positive (>= 0). | AX61: 7 | AY61: TVS0756
A62: A1 | B62: 44 | C62: 10 - Caractéristiques Engagements par Signature | D62: 10 - Funds in use by signature characteristics | E62: A1 4.12 | F62: IFT - Assiette réglementaire calculée en local | G62: Financial instruments - Regulatory exposure calculated locally | H62: IFT - Assiette réglementaire calculée en local | I62: Financial instruments - Regulatory exposure calculated locally | P62: ND | Q62: ND | R62: mtAssieRegl | S62: Obligatoire sous conditions | T62: Mandatory under conditions | U62: NA | V62: NA | W62: Ce champ correspond à l'équivalent risque de crédit (ERC) des IFT | X62: This field represent the credit risk equivalent of Forward Financial Instruments | Y62: NUM | Z62: 19 dont signe et 2 décimales | AA62: 19 including sign and 2 decimals | AB62: 19 | AC62: NA | AD62: 40 | AE62: NA | AF62: NA | AG62: CALCULS PRUDENTIELS, NPE | AH62: ND | AI62: N | AJ62: NA | AK62: NA | AL62: NA | AN62: La donnée est obligatoire, si 'NATO de l'exposition' [A1 3.2] = ('NAT10') | AO62: The data is mandatory, if 'NATure of Operation (NATO) for exposure' [A1 3.2] = ('NAT10') | AP62: 7 | AQ62: TPS1792 | AV62: SI [la donnée est renseignée] ET SI ['NATO de l'exposition' [A1 3.2] = 'NAT10'] ET SI ['Application source' [0.3 (A1)] <> 'ACORE'], ALORS la donnée doit être positive (>= à 0). | AW62: IF [data is filled] AND IF ['NATure of Operation' [A1 3.2] = 'NAT10'], AND IF ['Source application' [0.3 (A1)] <> 'ACORE'], THEN data must be positive (>= à 0). | AX62: 7 | AY62: TVS0758
A63: A1 | B63: 45 | C63: 10 - Caractéristiques Engagements par Signature | D63: 10 - Funds in use by signature characteristics | E63: A1 4.13 | F63: Code partenaire du bénéficiaire de l'engagement par signature | G63: Partner code of the beneficiary of the commitment by signing | H63: Le champ permet de distinguer les opérations intragroupes et hors-groupe classées en NAT06 | I63: The field enables to make the difference between intra and extra-CA group transactions classified as NAT06 | P63: ND | Q63: ND | R63: cdPartEPS | S63: Obligatoire sous conditions | T63: Mandatory under conditions | U63: LC.0003 | V63: TA FI59 RB NM281 | W63: Il s'agit du code de consolidation de l'entité partenaire dans le cas d'une opération intragroupe ou à un code générique dans le cas d'une opération hors-groupe Liste des codes partenaire : - '99999' s'il s'agit d'une entité Hors Groupe | X63: This is a consolidation code of the partner entity in case of intra-group transaction or a generic code in case of extra-group transaction: - '99999' if extra-group | Y63: NUM | Z63: NA | AA63: NA | AB63: 5 | AC63: NA | AD63: 40 | AE63: NA | AF63: NA | AG63: CALCULS PRUDENTIELS, ESG PILIER 3 | AH63: ND | AI63: N | AJ63: NA | AK63: NA | AL63: NA | AN63: La donnée est obligatoire, si 'NATO de l'exposition' [A1 3.2] = ('NAT06' ou 'NAT07') --- La donnée doit être vide, si 'NATO de l'exposition' [A1 3.2] est différente de 'NAT06' ou 'NAT07' | AO63: The data is mandatory if 'NATure of Operation (NATO) for exposure' [A1 3.2] = ('NAT06' or 'NAT07') --- The data must be empty, if NATure of Operation [A1 3.2] is different from 'NAT06' or 'NAT07' family | AP63: 6 7 | AQ63: TPS1789 TPS1803 | AR63: Si elle est renseignée, la valeur doit être connue du Langage Commun associé | AS63: If specified, the value must be known to the associated Common Language | AT63: 7 | AU63: TIG0001
A64: A1 | B64: 46 | C64: NA | D64: NA | E64: A1 4.98 | F64: Zone libre (Ex titre déprécié) | G64: Free zone (Ex Impaired Security Indicator) | H64: Zone libre | I64: Free zone | P64: NA | Q64: NA | R64: ZoneLibre4_98 | S64: NA | T64: NA | U64: NA | V64: NA | W64: NA | X64: NA | Y64: NUM | Z64: NA | AA64: NA | AB64: 1 | AC64: NA | AD64: 43 | AE64: 41 | AF64: NA | AG64: NA | AH64: NA | AI64: N | AJ64: NA | AK64: NA | AL64: NA
A65: A1 | B65: 47 | C65: 13 - Caractéristiques Provision | D65: 13 - Provision characteristics | E65: A1 4.17 | F65: Bucket IFRS9 | G65: Bucket IFRS9 | H65: Permet d'indiquer le classement de l'encours en norme IFRS9 | I65: Used to indicate the classification of exposure in IFRS9 | P65: ND | Q65: ND | R65: cdBcktIFRS9 | S65: Obligatoire sous conditions | T65: Mandatory under conditions | U65: LC.0257 | V65: TA KVBUCKET | W65: Laisser à vide si encours non soumis à dépréciation en norme IFRS 9 ou Bucket non encore déterminé (nouveau contrat) La provision sur encours sain, sur sensible ou sur douteux devra être déclarée dans la rubrique « 7 - INFORMATIONS Provision spécifique » de l'encours A1 alimentation adapté (PCCO, NATO et montant de la provision) | X65: Leave empty if not subject to impairment under IFRS 9 or Bucket not yet determined (new exposure) The provision for healthy, sensitive or doubtful exposures will have to be declared in the "7 - INFORMATION Specific Provision" section of the A1 adapted domain (PCCO, NATO and amount of the provision) | Y65: ALPHA | Z65: NA | AA65: NA | AB65: 2 | AC65: NA | AD65: 42 | AE65: NA | AF65: 45.00 | AG65: CALCULS PRUDENTIELS, ESG PILIER 3, LIQUIDITE, NPE | AH65: ND | AI65: N | AJ65: NA | AK65: NA | AL65: NA | AN65: Si Montant du PCCO 4 (provision) [A1 7.2] renseigné et <> 0, alors Bucket IFRS9 doit être renseigné | AO65: If Amount of PCCO 4 (provision amount) [A1 7.2] is filled and <> 0, then Bucket IFRS9 must be filled | AP65: 7 | AQ65: TPS1804 | AR65: Si elle est renseignée, la valeur doit être connue du Langage Commun associé | AS65: If specified, the value must be known to the associated Common Language | AT65: 7 | AU65: TIG0001 | AV65: Si la donnée est renseignée, et si 'Indicateur Engagement Douteux' [A1 4.14] = 'Y', alors la donnée doit être égale à 'B3' --- Si la donnée est renseignée, et si 'Indicateur Engagement Douteux' [A1 4.14] = 'N', alors la donnée doit être égale à ('B1', 'B2') | AW65: If data is filled, and if 'Doubtful Commitments indicator' [A1 4.14] = 'Y', then data must be equal to 'B3' --- If data is filled, and if 'Doubtful Commitments indicator' [A1 4.14] = 'N', then data must be equal to ('B1', 'B2') | AX65: 6 | AY65: TVS0759 TVS0760
A66: A1 | B66: 48 | C66: NA | D66: NA | E66: A1 4.99 | F66: Zone libre | G66: Free zone | H66: Zone libre | I66: Free zone | P66: NA | Q66: NA | R66: ZoneLibre4 | S66: NA | T66: NA | U66: NA | V66: NA | W66: NA | X66: NA | Y66: ALPHA | Z66: NA | AA66: NA | AB66: 27 | AC66: NA | AD66: 40 | AE66: 43 | AF66: NA | AG66: NA | AH66: NA | AI66: N | AJ66: NA | AK66: NA | AL66: NA
A67: A1 | B67: 49 | C67: 07 - Caractéristiques Crédit Bail | D67: 07 - Credit Lease characteristics | E67: A1 5.1 | F67: Usage du bien immobilier apporté en garantie | G67: Use of real-estate brought into guarantee | H67: Le champ permet de préciser si l'exposition est garantie par un bien immobilier à usage résidentiel ou professionnel | I67: The field makes it possible to indicate if: the exposure is guaranteed by a residential or commercial real-estate asset | P67: ND | Q67: ND | R67: cdUsBien | S67: Obligatoire sous conditions | T67: Mandatory under conditions | U67: LC.0166 | V67: TA KVUSGBI | W67: Ce champ est utilisé pour les prêts immobiliers garantis par une hypothèque et pour les contrats de location-financement ou de contrats de location à caractère financier dont le bien sous-jacent est immobilier Si cette donnée n'est pas renseignée, les pondérations préférentielles (35%; 50%) ne peuvent s'appliquer. Dans ce cas c'est la pondération de la contrepartie qui sera effective | X67: This field is used for real-estate loans guaranteed by a mortgage and for finance leasing or finance leases involving real-estate Where this data is not input, the preferred weightings (35%; 50%) cannot apply. In this instance the counterparty weighting will be effective | Y67: ALPHA | Z67: NA | AA67: NA | AB67: 1 | AC67: NA | AD67: 40 | AE67: NA | AF67: NA | AG67: CALCULS PRUDENTIELS, ESG PILIER 3 | AH67: ND | AI67: N | AJ67: NA | AK67: NA | AL67: NA | AN67: La donnée est obligatoire, si 'Famille de sûreté' [A1 6.7] = 'RI0' (sûreté immobilière) | AO67: The data is mandatory, if 'Mitigant family' [A1 6.7] = 'RI0' (Security interest on real estate) | AP67: 6 | AQ67: TPS1795 | AR67: Si elle est renseignée, la valeur doit être connue du Langage Commun associé | AS67: If specified, the value must be known to the associated Common Language | AT67: 7 | AU67: TIG0001 | AV67: Si 'Famille de sûreté' [A1 6.7] = 'RI0' (sûreté immobilière), alors la donnée doit être égale à '1' ou '2' | AW67: If 'Mitigant family' [A1 6.7] = 'RI0' (Security interest on real estate), then the data must be equal to '1' or '2' | AX67: 6 | AY67: TVS0761
A68: A1 | B68: 50 | C68: 07 - Caractéristiques Crédit Bail | D68: 07 - Credit Lease characteristics | E68: A1 5.6 | F68: Respect des conditions réglementaires | G68: Compliance with regulatory conditions | H68: Le champ permet de préciser si les conditions réglementaires relatives à ces opérations sont respectées | I68: The field enables to specify if regulatory conditions related to these transactions are compliant | P68: NA | Q68: NA | R68: indRespectCdtRegle | S68: NA | T68: NA | U68: LC.0171 | V68: TA KVRCR | W68: NA | X68: NA | Y68: ALPHA | Z68: NA | AA68: NA | AB68: 1 | AC68: NA | AD68: 40 | AE68: 45 | AF68: NA | AG68: CALCULS PRUDENTIELS, NPE | AH68: NA | AI68: N | AJ68: NA | AK68: NA | AL68: NA
A69: A1 | B69: 51 | C69: 07 - Caractéristiques Crédit Bail | D69: 07 - Credit Lease characteristics | E69: A1 5.2 | F69: Valeur de marché du bien loué à la date d'évaluation | G69: Market value of leased asset as of the valuation date | H69: Valeur de marché du bien loué à la date d'évaluation | I69: Market value of leased asset as of the valuation date | P69: ND | Q69: ND | R69: cdDevMtMarLastEval | S69: Obligatoire sous conditions | T69: Mandatory under conditions | U69: NA | V69: NA | W69: Réservé au Crédit-Bail immobilier | X69: Reserved for Real-estate leasing | Y69: NUM | Z69: 19 dont signe et 2 décimales | AA69: 19 including sign and 2 decimals | AB69: 19 | AC69: NA | AD69: 40 | AE69: NA | AF69: NA | AG69: CALCULS PRUDENTIELS, NPE | AH69: ND | AI69: N | AJ69: NA | AK69: NA | AL69: NA | AN69: La donnée est obligatoire, si 'Usage du bien immobilier apporté en garantie' [A1 5.1] est égal à '1' ou '2', OU si le 'Respect des Conditions Réglementaires' [A1 5.6] est égal à 'Y' | AO69: The data is mandatory, if the 'Use of real-estate brought into guarantee' [A1 5.1] is equal to '1' or '2', OR if the 'Compliance with Regulatory Conditions' [A1 5.6] is equal to 'Y' | AP69: 6 | AQ69: TPS1796 | AV69: Si la donnée est renseignée, et si Application source [0.3 (A1)] <> 'ACORE', alors la donnée doit être positive (>= à 0). | AW69: If data is filled, and if Source application [0.3 (A1)] <> 'ACORE', then data must be positive (>= 0). | AX69: 7 | AY69: TVS0756
A70: A1 | B70: 52 | C70: 07 - Caractéristiques Crédit Bail | D70: 07 - Credit Lease characteristics | E70: A1 5.3 | F70: Valeur hypothécaire du bien immobilier loué à la date d'évaluation | G70: Mortgage lending value of the leased real-estate as of the valuation date | H70: Valeur hypothécaire du bien immobilier loué à la date d'évaluation | I70: Mortgage lending value of the leased real-estate as of the valuation date | P70: ND | Q70: ND | R70: mtHypoLastEval | S70: Obligatoire sous conditions | T70: Mandatory under conditions | U70: NA | V70: NA | W70: Réservé au Crédit-Bail immobilier professionnel | X70: Reserved for Commercial real-estate leasing | Y70: NUM | Z70: 19 dont signe et 2 décimales | AA70: 19 including sign and 2 decimals | AB70: 19 | AC70: NA | AD70: 40 | AE70: NA | AF70: NA | AG70: CALCULS PRUDENTIELS, NPE | AH70: ND | AI70: N | AJ70: NA | AK70: NA | AL70: NA | AN70: La donnée est obligatoire, si 'Usage du bien immobilier apporté en garantie' [A1 5.1] est égal à '1' ou '2', OU si le 'Respect des Conditions Réglementaires' [A1 5.6] est égal à 'Y' | AO70: The data is mandatory, if the 'Use of real-estate brought into guarantee' [A1 5.1] is equal to '1' or '2', OR if the 'Compliance with Regulatory Conditions' [A1 5.6] is equal to 'Y' | AP70: 6 | AQ70: TPS1796 | AV70: Si la donnée est renseignée, et si Application source [0.3 (A1)] <> 'ACORE', alors la donnée doit être positive (>= à 0). | AW70: If data is filled, and if Source application [0.3 (A1)] <> 'ACORE', then data must be positive (>= 0). | AX70: 7 | AY70: TVS0756
A71: A1 | B71: 53 | C71: 07 - Caractéristiques Crédit Bail | D71: 07 - Credit Lease characteristics | E71: A1 5.4 | F71: Achat en fin de contrat du bien loué | G71: Purchase of leased asset at end of lease | H71: Achat en fin de contrat du bien loué | I71: Purchase of leased asset at end of lease | P71: ND | Q71: ND | R71: cdAchatFinContrBien | S71: Facultatif | T71: Optional | U71: LC.0155 | V71: TA KVIACHAT | W71: Réservé au Crédit-Bail | X71: Reserved for Leasing | Y71: ALPHA | Z71: NA | AA71: NA | AB71: 1 | AC71: NA | AD71: 40 | AE71: NA | AF71: NA | AG71: CALCULS PRUDENTIELS, NPE | AH71: ND | AI71: N | AJ71: NA | AK71: NA | AL71: NA | AV71: Si renseignée, alors la donnée doit être égale à '1' ou '2' | AW71: If is filled, then data must be equal to '1' or '2' | AX71: 7 | AY71: TVS0762 | BH71: Si la combinaison de donnée n'est pas trouvée dans la matrice des règles de gestion C16, le contrôle doit se lever | BI71: If the data combinaison is not found in the C16 business rules matrix, the control must trigger | BJ71: 6 | BK71: TC0C16
A72: A1 | B72: 54 | C72: 07 - Caractéristiques Crédit Bail | D72: 07 - Credit Lease characteristics | E72: A1 5.5 | F72: Valeur estimée en fin de période du bien loué (valeur résiduelle) | G72: Estimated value of leased asset at end of period (residual value) | H72: Ce champ correspond à la valeur résiduelle du bien loué dans le cadre de contrat de crédit-bail | I72: This field represents the residual value of the leased asset under the lease | P72: ND | Q72: ND | R72: mtFinContrBien | S72: Obligatoire sous conditions | T72: Mandatory under conditions | U72: NA | V72: NA | W72: Remarque : la valeur estimée en fin de période est enregistrée dans le même PCCO que les loyers à recevoir, il faut donc la soustraire du solde du PCCO Réservé au Crédit-Bail | X72: Note: the estimated value at the end of the period is input in the same PCCO as lease payments receivable, so the balance of the PCCO must be deducted Reserved for Leasing | Y72: NUM | Z72: 19 dont signe et 2 décimales | AA72: 19 including sign and 2 decimals | AB72: 19 | AC72: NA | AD72: 40 | AE72: NA | AF72: NA | AG72: CALCULS PRUDENTIELS, NPE | AH72: ND | AI72: N | AJ72: NA | AK72: NA | AL72: NA | AN72: La donnée est obligatoire, si 'Achat en fin de contrat du bien loué' [A1 5.4]= '1 ou 2' | AO72: The data is mandatory, if 'Purchase of leased asset at end of lease' [A1 5.4] = '1 or 2' | AP72: 6 | AQ72: TPS1797 | AV72: Si la donnée est renseignée, et si Application source [0.3 (A1)] <> 'ACORE', alors la donnée doit être positive (>= à 0). | AW72: If data is filled, and if Source application [0.3 (A1)] <> 'ACORE', then data must be positive (>= 0). | AX72: 7 | AY72: TVS0756
A73: A1 | B73: 55 | C73: 07 - Caractéristiques Crédit Bail | D73: 07 - Credit Lease characteristics | E73: A1 5.99 | F73: Zone libre | G73: Free zone | H73: Zone libre | I73: Free zone | P73: NA | Q73: NA | R73: ZoneLibre5 | S73: NA | T73: NA | U73: NA | V73: NA | W73: NA | X73: NA | Y73: ALPHA | Z73: NA | AA73: NA | AB73: 30 | AC73: NA | AD73: 40 | AE73: 41 | AF73: NA | AG73: NA | AH73: NA | AI73: N | AJ73: NA | AK73: NA | AL73: NA
A74: A1 | B74: 56 | C74: 15 - Caractéristiques Sureté | D74: 15 - Safety characteristics | E74: A1 6.1 | F74: CAP de la sûreté | G74: CAP of the mitigant | H74: Le champ correspond à la Classe d'Actif de Pondération du garant / émetteur / dépositaire de la sûreté | I74: The field represents the Asset class for weighting purposes (CAP) of the guarantor / issuer / depository of the mitigant | P74: ND | Q74: ND | R74: cdCAPSur | S74: Obligatoire (SC) | T74: Mandatory (SC) | U74: LC.0084 | V74: TA H8CAP | W74: - Pour les titres, la CAP correspond à l'émetteur des titres considérés comme des sûretés - Pour les autres types d'engagement, la CAP correspond au fournisseur de protection | X74: - For securities, the CAP represents the issuer of securities deemed to be guarantees - For other types of commitments, the CAP represents the party providing the cover | Y74: ALPHA | Z74: NA | AA74: NA | AB74: 12 | AC74: NA | AD74: 40 | AE74: NA | AF74: NA | AG74: CALCULS PRUDENTIELS | AH74: ND | AI74: N | AJ74: NA | AK74: NA | AL74: NA | AR74: Si elle est renseignée, la valeur doit être connue du Langage Commun associé | AS74: If specified, the value must be known to the associated Common Language | AT74: 7 | AU74: TIG0001
A75: A1 | B75: 57 | C75: 15 - Caractéristiques Sureté | D75: 15 - Safety characteristics | E75: A1 6.2 | F75: État - Pays de résidence fiscal du garant / émetteur / dépositaire de la sûreté | G75: Sovereign – Country of fiscal residence of the guarantor / issuer / depository of the mitigant | H75: Le champ correspond au pays de résidence fiscal du fournisseur de sûreté | I75: The field represents the country of fiscal residence of the party providing the mitigant | P75: ND | Q75: ND | R75: cdPaysFiscSur | S75: Obligatoire sous conditions | T75: Mandatory under conditions | U75: LC.0004 LC.0073 | V75: TA NM252 (pour la partie ISO 3166) TA NM258 (organisation supra nationales) | W75: NA | X75: NA | Y75: ALPHA | Z75: NA | AA75: NA | AB75: 2 | AC75: NA | AD75: 40 | AE75: NA | AF75: NA | AG75: CALCULS PRUDENTIELS, ESG PILIER 3 | AH75: ND | AI75: N | AJ75: NA | AK75: NA | AL75: NA | AN75: La donnée est obligatoire, si 'CAP de la sûreté' [A1 6.1] est renseigné | AO75: The data is mandatory if CAP of the mitigant [A1 6.1] is filled | AP75: 6 | AQ75: TPS1798 | AR75: Si elle est renseignée, la valeur doit être connue du Langage Commun associé | AS75: If specified, the value must be known to the associated Common Language | AT75: 7 | AU75: TIG0001
A76: A1 | B76: 58 | C76: 15 - Caractéristiques Sureté | D76: 15 - Safety characteristics | E76: A1 6.3 | F76: Indicateur Garant / Emetteur / Dépositaire de la sûreté | G76: Indicator of Guarantor / Issuer / Depository of the mitigant | H76: Le champ permet d'identifier les contreparties garant/émetteur de titres ayant un traitement spécifique | I76: The field makes it possible to identify the guarantor / issuer of securities counterparties subject to a specific treatment | P76: ND | Q76: ND | R76: idCtpTraitSpeSur | S76: Facultatif | T76: Optional | U76: LC.0146 | V76: TA KVCPPREF | W76: Les valeurs autorisées : - BCE - BMD (y compris FEI) pondérées à 0% - OI pondérées à 0% - FGAS | X76: The permitted values are: - ECB - Multilateral development banks (including the EIF) weighted at 0% - IOs weighted at 0% - FGAS | Y76: ALPHA | Z76: NA | AA76: NA | AB76: 2 | AC76: NA | AD76: 40 | AE76: NA | AF76: NA | AG76: CALCULS PRUDENTIELS | AH76: ND | AI76: N | AJ76: NA | AK76: NA | AL76: NA | AR76: Si elle est renseignée, la valeur doit être connue du Langage Commun associé | AS76: If specified, the value must be known to the associated Common Language | AT76: 7 | AU76: TIG0001
A77: A1 | B77: 59 | C77: 15 - Caractéristiques Sureté | D77: 15 - Safety characteristics | E77: A1 6.4 | F77: Code partenaire du garant / émetteur / dépositaire de la sûreté | G77: Partner code of guarantor / issuer / depository of the mitigant | H77: Le champ permet de distinguer le caractère intragroupe de la sûreté | I77: This field makes it possible to indicate the inter-company nature of the mitigant | P77: ND | Q77: ND | R77: cdPartCtpSur | S77: Obligatoire sous conditions | T77: Mandatory under conditions | U77: LC.0003 | V77: TA FI59 RB NM281 | W77: Le champ correspond au code de consolidation de l'entité partenaire dans le cas d'une sûreté fournie par une entité du Groupe ou à un code générique dans le cas d'une opération hors-groupe Liste des codes partenaire : - '99999' s'il s'agit d'une entité Hors Groupe | X77: The field represents the consolidation code of the partner entity in the case of a guarantee provided by a Group entity or a generic code in the case of a non-group transaction List of partner codes: - '99999' where it involves a Non-Group entity | Y77: NUM | Z77: NA | AA77: NA | AB77: 5 | AC77: NA | AD77: 40 | AE77: NA | AF77: NA | AG77: CALCULS PRUDENTIELS | AH77: ND | AI77: N | AJ77: NA | AK77: NA | AL77: NA | AN77: La donnée est obligatoire, si 'CAP de la sûreté' [A1 6.1] est renseigné | AO77: The data is mandatory if CAP of the mitigant [A1 6.1] is filled | AP77: 6 | AQ77: TPS1798 | AR77: Si elle est renseignée, la valeur doit être connue du Langage Commun associé | AS77: If specified, the value must be known to the associated Common Language | AT77: 7 | AU77: TIG0001
A78: A1 | B78: 60 | C78: 15 - Caractéristiques Sureté | D78: 15 - Safety characteristics | E78: A1 6.5 | F78: NATO de la sûreté | G78: Transaction nature (NATO) of the mitigant | H78: Le champ correspond à la classification de la sûreté selon la nomenclature Groupe CA "NATO" commune aux Risques et à la Comptabilité | I78: The field represents the classification of the mitigant under the CA Group shared Risk and Accounting "NATO" (transaction nature) nomenclature | P78: ND | Q78: ND | R78: cdNatOpSur | S78: Obligatoire sous conditions | T78: Mandatory under conditions | U78: LC.0064 | V78: TA H8NATOPE | W78: Elle correspond à une NAT8… Cette information est nécessaire aux restitutions COREP | X78: It represents a NAT8… This information is necessary for COREP reporting | Y78: ALPHA | Z78: NA | AA78: NA | AB78: 12 | AC78: NA | AD78: 40 | AE78: NA | AF78: NA | AG78: CALCULS PRUDENTIELS | AH78: ND | AI78: N | AJ78: NA | AK78: NA | AL78: NA | AN78: La donnée est obligatoire, si 'CAP de la sûreté' [A1 6.1] est renseigné | AO78: The data is mandatory if CAP of the mitigant [A1 6.1] is filled | AP78: 6 | AQ78: TPS1798 | AR78: Si elle est renseignée, la valeur doit être connue du Langage Commun associé | AS78: If specified, the value must be known to the associated Common Language | AT78: 7 | AU78: TIG0001 | BH78: Si la combinaison de donnée n'est pas trouvée dans la matrice des règles de gestion C11, le contrôle doit se lever | BI78: If the data combinaison is not found in the C11 business rules matrix, the control must trigger | BJ78: 6 | BK78: TC0C11
A79: A1 | B79: 61 | C79: 15 - Caractéristiques Sureté | D79: 15 - Safety characteristics | E79: A1 6.6 | F79: Fournisseur de sûreté | G79: Party providing the mitigant | H79: Le champ correspond au type de Garant / Emetteur / Dépositaire de la sûreté | I79: The field represents the type of Guarantor / Issuer / Depository of the mitigant | P79: ND | Q79: ND | R79: cdFnrSur | S79: Obligatoire sous conditions | T79: Mandatory under conditions | U79: LC.0147 | V79: TA AHFPRO | W79: Cette information est nécessaire aux restitutions COREP | X79: This information is necessary for COREP reporting | Y79: ALPHA | Z79: NA | AA79: NA | AB79: 4 | AC79: NA | AD79: 40 | AE79: NA | AF79: NA | AG79: CALCULS PRUDENTIELS | AH79: ND | AI79: N | AJ79: NA | AK79: NA | AL79: NA | AN79: La donnée est obligatoire, si 'CAP de la sûreté' [A1 6.1] est renseigné | AO79: The data is mandatory if CAP of the mitigant [A1 6.1] is filled | AP79: 6 | AQ79: TPS1798 | AR79: Si elle est renseignée, la valeur doit être connue du Langage Commun associé | AS79: If specified, the value must be known to the associated Common Language | AT79: 7 | AU79: TIG0001
A80: A1 | B80: 62 | C80: 15 - Caractéristiques Sureté | D80: 15 - Safety characteristics | E80: A1 6.7 | F80: Famille de sûreté | G80: Mitigant family | H80: Le champ correspond à la famille de sûreté | I80: The field represents the mitigant family | P80: ND | Q80: ND | R80: cdFamSur | S80: Obligatoire sous conditions | T80: Mandatory under conditions | U80: LC.0150 | V80: TA KVFAMSUR | W80: Cette information est nécessaire aux restitutions COREP | X80: This information is necessary for COREP reporting | Y80: ALPHA | Z80: NA | AA80: NA | AB80: 3 | AC80: NA | AD80: 40 | AE80: NA | AF80: NA | AG80: CALCULS PRUDENTIELS | AH80: ND | AI80: N | AJ80: NA | AK80: NA | AL80: NA | AN80: La donnée est obligatoire, si 'CAP de la sûreté' [A1 6.1] est renseigné | AO80: The data is mandatory if CAP of the mitigant [A1 6.1] is filled | AP80: 6 | AQ80: TPS1798 | AR80: Si elle est renseignée, la valeur doit être connue du Langage Commun associé | AS80: If specified, the value must be known to the associated Common Language | AT80: 7 | AU80: TIG0001
A81: A1 | B81: 63 | C81: 15 - Caractéristiques Sureté | D81: 15 - Safety characteristics | E81: A1 6.8 | F81: Numéro du PCCO3 de la sûreté reçue | G81: Number of PCCO3 of the received mitigant | H81: Le champ correspond au code du compte consolidé | I81: The field represents the consolidated account code | P81: ND | Q81: ND | R81: noPCCO3 | S81: Facultatif | T81: Optional | U81: LC.0111 | V81: TA H8PCCO | W81: Pour les garanties reçues (NAT08), ce numéro correspond à un PCCO du hors-bilan | X81: For guarantees received (NAT08), this number represents an off-balance sheet PCCO | Y81: ALPHA | Z81: NA | AA81: NA | AB81: 12 | AC81: NA | AD81: 40 | AE81: NA | AF81: NA | AG81: CALCULS PRUDENTIELS | AH81: ND | AI81: N | AJ81: NA | AK81: NA | AL81: NA | AR81: Si elle est renseignée, la valeur doit être connue du Langage Commun associé | AS81: If specified, the value must be known to the associated Common Language | AT81: 7 | AU81: TIG0001 | AZ81: Le couple H8PCCO/H8NATO (correspondant au Numéro du PCCO3 de la sûreté reçue [A1 6.8] et à la NATO de la sûreté [A1 6.5]) doit exister dans la table START H8PCNATO, avec H8NATO composé des 5 premiers caractères | BA81: The H8PCCO/H8NATO pair (corresponding to Number of PCCO3 of the received mitigant [A1 6.8] and Transaction nature (NATO) of the mitigant [A1 6.5]) must exist in the START table H8PCNATO, with H8NATO 5 first posititions | BB81: 6 | BC81: TCS0769
A82: A1 | B82: 64 | C82: 15 - Caractéristiques Sureté | D82: 15 - Safety characteristics | E82: A1 6.9 | F82: Montant de la sûreté reçue | G82: Amount of the mitigant received | H82: Montant de la sûreté reçue | I82: Amount of the mitigant received | P82: ND | Q82: ND | R82: mtSur | S82: Obligatoire sous conditions | T82: Mandatory under conditions | U82: NA | V82: NA | W82: Le champ correspond au montant de la sûreté reçue et éligible Bâle II (éventuellement ajusté des asymétries d'échéances) | X82: The field represents the amount of the guarantee received and eligible under Basel II (where necessary adjusted for maturity mismatches) | Y82: NUM | Z82: 19 dont signe et 2 décimales | AA82: 19 including sign and 2 decimals | AB82: 19 | AC82: NA | AD82: 40 | AE82: NA | AF82: NA | AG82: CALCULS PRUDENTIELS | AH82: ND | AI82: N | AJ82: NA | AK82: NA | AL82: NA | AN82: La donnée est obligatoire, si 'CAP de la sûreté' [A1 6.1] est renseigné | AO82: The data is mandatory if CAP of the mitigant [A1 6.1] is filled | AP82: 6 | AQ82: TPS1798 | AV82: Si la donnée est renseignée, et si Application source [0.3 (A1)] <> 'ACORE', alors la donnée doit être positive (>= à 0). | AW82: If data is filled, and if Source application [0.3 (A1)] <> 'ACORE', then data must be positive (>= 0). | AX82: 7 | AY82: TVS0756
A83: A1 | B83: 65 | C83: 15 - Caractéristiques Sureté | D83: 15 - Safety characteristics | E83: A1 6.10 | F83: Méthode de valorisation du bien | G83: Property valuation method | H83: Permet d'identifier la nature du montant de la sûreté immobilière : soit la valeur de marché du bien, soit le montant hypothécaire | I83: Enables to identify the nature of the amount of real-estate mitigant: or the property market value, either the amount of the mortgage | P83: ND | Q83: ND | R83: cdMetRev | S83: Obligatoire sous conditions | T83: Mandatory under conditions | U83: LC.0057 | V83: TA KVVALOR | W83: NA | X83: NA | Y83: ALPHA | Z83: NA | AA83: NA | AB83: 1 | AC83: NA | AD83: 40 | AE83: NA | AF83: NA | AG83: CALCULS PRUDENTIELS, NPE | AH83: ND | AI83: N | AJ83: NA | AK83: NA | AL83: NA | AN83: La donnée est obligatoire, si 'Famille de sûreté' [A1 6.7] = 'RI0' (sûreté immobilière) | AO83: The data is mandatory, if 'Mitigant family' [A1 6.7] = 'RI0' (Security interest on real estate) | AP83: 6 | AQ83: TPS1795 | AR83: Si elle est renseignée, la valeur doit être connue du Langage Commun associé | AS83: If specified, the value must be known to the associated Common Language | AT83: 7 | AU83: TIG0001
A84: A1 | B84: 66 | C84: 15 - Caractéristiques Sureté | D84: 15 - Safety characteristics | E84: A1 6.11 | F84: Echelon de qualité de crédit du garant | G84: Guarantor / Issuer / Depository credit quality level | H84: Echelon de qualité de crédit du garant / émetteur / dépositaire de la sûreté | I84: Guarantor / Issuer / Depository credit quality level | P84: ND | Q84: ND | R84: cdEchelQualGar | S84: Facultatif | T84: Optional | U84: LC.0178 | V84: TA KVECHLON | W84: NA | X84: NA | Y84: ALPHA | Z84: NA | AA84: NA | AB84: 1 | AC84: NA | AD84: 40 | AE84: NA | AF84: NA | AG84: CALCULS PRUDENTIELS | AH84: ND | AI84: N | AJ84: NA | AK84: NA | AL84: NA | AR84: Si elle est renseignée, la valeur doit être connue du Langage Commun associé | AS84: If specified, the value must be known to the associated Common Language | AT84: 7 | AU84: TIG0001
A85: A1 | B85: 67 | C85: 15 - Caractéristiques Sureté | D85: 15 - Safety characteristics | E85: A1 6.99 | F85: Zone libre | G85: Free zone | H85: Zone libre | I85: Free zone | P85: NA | Q85: NA | R85: ZoneLibre6 | S85: NA | T85: NA | U85: NA | V85: NA | W85: NA | X85: NA | Y85: ALPHA | Z85: NA | AA85: NA | AB85: 29 | AC85: NA | AD85: 40 | AE85: 41 | AF85: NA | AG85: NA | AH85: NA | AI85: N | AJ85: NA | AK85: NA | AL85: NA
A86: A1 | B86: 68 | C86: 13 - Caractéristiques Provision | D86: 13 - Provision characteristics | E86: A1 7.1 | F86: Numéro du PCCO4 | G86: Number of PCCO4 | H86: Le champ correspond au code du compte consolidé | I86: The field represents the consolidated account code | P86: ND | Q86: ND | R86: noPCCO4 | S86: Facultatif | T86: Optional | U86: LC.0111 | V86: TA H8PCCO | W86: NA | X86: NA | Y86: ALPHA | Z86: NA | AA86: NA | AB86: 12 | AC86: NA | AD86: 40 | AE86: NA | AF86: 45.00 | AG86: CALCULS PRUDENTIELS, LIQUIDITE | AH86: ND | AI86: N | AJ86: NA | AK86: NA | AL86: NA | AR86: Si elle est renseignée, la valeur doit être connue du Langage Commun associé | AS86: If specified, the value must be known to the associated Common Language | AT86: 7 | AU86: TIG0001 | AZ86: Le couple H8PCCO/H8NATO (correspondant au Numéro du PCCO4 [A1 7.1] et à la NATO de la provision [A1 7.3]) doit exister dans la table START H8PCNATO, avec H8NATO composé des 5 premiers caractères | BA86: The H8PCCO/H8NATO pair (corresponding to Number of PCCO4 [A1 7.1] and Transaction nature (NATO) of the provision [A1 7.3]) must exist in the START table H8PCNATO, with H8NATO 5 first posititions | BB86: 6 | BC86: TCS0770
A87: A1 | B87: 69 | C87: 13 - Caractéristiques Provision | D87: 13 - Provision characteristics | E87: A1 7.2 | F87: Montant du PCCO 4 | G87: Amount of PCCO 4 | H87: Montant du PCCO 4 | I87: Amount of PCCO 4 | P87: ND | Q87: ND | R87: mtPCCO4 | S87: Obligatoire sous conditions | T87: Mandatory under conditions | U87: NA | V87: NA | W87: Ce champ correspond à la valeur comptable (tout ou partie du solde) du PCCO4 Ce champ correspond à la valeur comptable de la dépréciation (provision spécifique) | X87: This field represents the accounting value (all or part of the balance) of PCCO4 This field represents the accounting value of the impairment (special provision) | Y87: NUM | Z87: 19 dont signe et 2 décimales | AA87: 19 including sign and 2 decimals | AB87: 19 | AC87: NA | AD87: 40 | AE87: NA | AF87: 45.00 | AG87: CALCULS PRUDENTIELS, ESG PILIER 3, LIQUIDITE | AH87: ND | AI87: N | AJ87: NA | AK87: NA | AL87: NA | AN87: La donnée est obligatoire, si le 'Numéro de PCCO 4' [A1 7.1] est renseigné | AO87: The data is mandatory, if 'Number of PCCO 4' [A1 7.1] is filled | AP87: 6 | AQ87: TPS1799 | AV87: Si la donnée est renseignée, et si Application source [0.3 (A1)] <> 'ACORE', alors la donnée doit être positive (>= à 0). --- Si NATO de l'exposition [A1 3.2] IN ('NAT10','NAT04'), alors la donnée doit être NULL. | AW87: If data is filled, and if Source application [0.3 (A1)] <> 'ACORE', then data must be positive (>= 0). --- If NATure of Operation (NATO) for exposure [A1 3.2] IN ('NAT10','NAT04'), this data must be NULL. | AX87: 6 | AY87: TVS0756 TVS0757
A88: A1 | B88: 70 | C88: 13 - Caractéristiques Provision | D88: 13 - Provision characteristics | E88: A1 7.3 | F88: NATO de la provision | G88: Transaction nature (NATO) of the provision | H88: Correspond à la NATO de la provision (NAS ou NAC) | I88: Represents the Transaction nature (NATO) of the provision | P88: ND | Q88: ND | R88: cdNatOpProv | S88: Obligatoire sous conditions | T88: Mandatory under conditions | U88: LC.0064 | V88: TA H8NATOPE | W88: NA | X88: NA | Y88: ALPHA | Z88: NA | AA88: NA | AB88: 12 | AC88: NA | AD88: 40 | AE88: NA | AF88: NA | AG88: CALCULS PRUDENTIELS | AH88: ND | AI88: N | AJ88: NA | AK88: NA | AL88: NA | AN88: La donnée est obligatoire, si le 'Montant du PCCO 4' [A1 7.2] est renseigné et différent de 0 | AO88: The data is mandatory, if 'Amount of PCCO 4' [A1 7.2] is filled and different of 0 | AP88: 6 | AQ88: TPS1801 | AR88: Si elle est renseignée, la valeur doit être connue du Langage Commun associé | AS88: If specified, the value must be known to the associated Common Language | AT88: 7 | AU88: TIG0001 | AV88: Si renseignée, alors la donnée doit commencer par 'NAS' ou 'NAC' | AW88: If filled, the data should start with 'NAS' or 'NAC' | AX88: 6 | AY88: TVS0763
A89: A1 | B89: 71 | C89: 19 - Données comptables | D89: 19 - Accounting data | E89: A1 8.1 | F89: Numéro du PCCO5 | G89: Number of PCCO5 | H89: Le champ correspond au code du compte consolidé | I89: The field represents the consolidated account code | P89: ND | Q89: ND | R89: noPCCO5 | S89: Facultatif | T89: Optional | U89: LC.0111 | V89: TA H8PCCO | W89: NA | X89: NA | Y89: ALPHA | Z89: NA | AA89: NA | AB89: 12 | AC89: NA | AD89: 40 | AE89: NA | AF89: 45.00 | AG89: CALCULS PRUDENTIELS, LIQUIDITE | AH89: ND | AI89: N | AJ89: NA | AK89: NA | AL89: NA | AR89: Si elle est renseignée, la valeur doit être connue du Langage Commun associé | AS89: If specified, the value must be known to the associated Common Language | AT89: 7 | AU89: TIG0001 | AZ89: Le couple H8PCCO/H8NATO (correspondant au Numéro du PCCO5 [A1 8.1] et à la NATO de la décote [A1 8.3]) doit exister dans la table START H8PCNATO, avec H8NATO composé des 5 premiers caractères | BA89: The H8PCCO/H8NATO pair (corresponding to Number of PCCO5 [A1 8.1] and Transaction nature (NATO) of the haircut [A1 8.3]) must exist in the START table H8PCNATO, with H8NATO 5 first posititions | BB89: 6 | BC89: TCS0771
A90: A1 | B90: 72 | C90: 19 - Données comptables | D90: 19 - Accounting data | E90: A1 8.2 | F90: Montant du PCCO 5 | G90: Amount of PCCO 5 | H90: Montant du PCCO 5 | I90: Amount of PCCO 5 | P90: ND | Q90: ND | R90: mtPCCO5 | S90: Obligatoire sous conditions | T90: Mandatory under conditions | U90: NA | V90: NA | W90: Ce champ correspond à la valeur comptable (tout ou partie du solde) du PCCO5 Ce champ correspond à la valeur comptable de la dépréciation (décote) | X90: This field represents the accounting value (all or part of the balance) of PCCO5 This field represents the accounting value of the impairment (haircut) | Y90: NUM | Z90: 19 dont signe et 2 décimales | AA90: 19 including sign and 2 decimals | AB90: 19 | AC90: NA | AD90: 40 | AE90: NA | AF90: 45.00 | AG90: CALCULS PRUDENTIELS, LIQUIDITE | AH90: ND | AI90: N | AJ90: NA | AK90: NA | AL90: NA | AN90: La donnée est obligatoire, si le 'Numéro de PCCO 5' [A1 8.1] est renseigné | AO90: The data is mandatory, if 'Number of PCCO 5' [A1 8.1] is filled | AP90: 6 | AQ90: TPS1800 | AV90: Si la donnée est renseignée, et si Application source [0.3 (A1)] <> 'ACORE', alors la donnée doit être positive (>= à 0). | AW90: If data is filled, and if Source application [0.3 (A1)] <> 'ACORE', then data must be positive (>= 0). | AX90: 7 | AY90: TVS0756
A91: A1 | B91: 73 | C91: 19 - Données comptables | D91: 19 - Accounting data | E91: A1 8.3 | F91: NATO de la décote | G91: Transaction nature (NATO) of the haircut | H91: Correspond à la NATO de la décote (NAA) | I91: Represents the Transaction nature (NATO) of the haircut | P91: ND | Q91: ND | R91: cdNatOptDecote | S91: Obligatoire sous conditions | T91: Mandatory under conditions | U91: LC.0064 | V91: TA H8NATOPE | W91: NA | X91: NA | Y91: ALPHA | Z91: NA | AA91: NA | AB91: 12 | AC91: NA | AD91: 40 | AE91: NA | AF91: NA | AG91: CALCULS PRUDENTIELS | AH91: ND | AI91: N | AJ91: NA | AK91: NA | AL91: NA | AN91: La donnée est obligatoire, si le 'Montant du PCCO 5' [A1 8.2] est renseigné et différent de 0 | AO91: The data is mandatory, if 'Amount of PCCO 5' [A1 8.2] is filled and different of 0 | AP91: 6 | AQ91: TPS1802 | AR91: Si elle est renseignée, la valeur doit être connue du Langage Commun associé | AS91: If specified, the value must be known to the associated Common Language | AT91: 7 | AU91: TIG0001 | AV91: Si renseignée, alors la donnée doit commencer par 'NAA' | AW91: If filled, the data should start with 'NAA' | AX91: 6 | AY91: TVS0764
A92: A1 | B92: 74 | C92: 03 - Caractéristiques Générales | D92: 03 - General characteristics | E92: A1 523 | F92: Indicateur tiers connu | G92: Known Third Party indicator | H92: Indique si le tiers associé à la ligne d'encours est connu ou non. Cet indicateur permet ainsi de déterminer si les données sont présentées à la maille contrat/engagement (granularité fine) ou agrégées | I92: Indicate whether the third party associated with the outstanding line is known or not. This indicator thus makes it possible to determine whether the data are presented at the contract/commitment mesh (fine granularity) or aggregated | J92: NON | M92: Ne pas alimenter Il n'y aura pas de colonne créé pour ce champ | P92: ND | Q92: ND | R92: TBD | S92: Obligatoire | T92: Mandatory | U92: LC.0577 | V92: RB Z8IDTICO | W92: Les données doivent être renseignées à la maille code ISIN pour les titres et à la maille engagement pour les autres produits | X92: The data must be entered in the ISIN mesh for securities and the commitment mesh for other products | Y92: ALPHA | Z92: NA | AA92: NA | AB92: 1 | AC92: NA | AD92: 45 | AE92: NA | AF92: NA | AG92: LIQUIDITE | AH92: ND | AI92: N | AJ92: NA | AK92: NA | AL92: NA | AN92: La donnée est obligatoire | AO92: The data is mandatory | AP92: 7 | AQ92: TPG0001 | AR92: Si elle est renseignée, la valeur doit être connue du Langage Commun associé | AS92: If specified, the value must be known to the associated Common Language | AT92: 7 | AU92: TIG0001
A93: A1 | B93: 75 | C93: 03 - Caractéristiques Générales | D93: 03 - General characteristics | E93: A1 2.0 | F93: Type de risque | G93: Risk type | H93: Classification de l'opération selon la nomenclature risque | I93: Classification of transaction on the basis of the risk nomenclature | J93: OUI | K93: Fichier envoyé par MERCA et partagé par le métier | L93: A1_DEGRADE_GMBH Nouvelle donnée à créér Nom de la donnée: | M93: Champ inclut dans le fichier en provenance de MERCA et partagé par le métier. Une nouveau champ est à créer dans la table d'integration de ce fichier. Nom du champ dans le fichier partagé par MERCA: RISKTYPE | O93: Version 1 | P93: ND | Q93: ND | R93: cdTypRis | S93: Obligatoire sous conditions | T93: Mandatory under conditions | U93: LC.0030 | V93: TA KVTYPRIS | W93: Les titres de créances sont classés en ISS200 ou ISS300, en norme française, en fonction de la durée de conservation de ces titres dans le bilan de l'établissement | X93: Debts securities are classified in ISS200 or ISS300, in French standard, depending on the length of retention of these securities in the balance sheet of the institution | Y93: ALPHA | Z93: NA | AA93: NA | AB93: 6 | AC93: NA | AD93: 45 | AE93: NA | AF93: NA | AG93: CALCULS PRUDENTIELS | AH93: ND | AI93: N | AJ93: NA | AK93: NA | AL93: NA | AN93: La donnée est obligatoire, si l'Indicateur tiers connu [A1 523] = 'Y' | AO93: The data is mandatory, if Known Third Party indicator [A1 523] = 'Y' | AP93: 7 | AQ93: TPSxxxx | AR93: Si elle est renseignée, la valeur doit être connue du Langage Commun associé | AS93: If specified, the value must be known to the associated Common Language | AT93: 7 | AU93: TIG0001 | AV93: Si renseignée, la valeur doit être différente de 'DVP100' | AW93: If filled, the value must be different from 'DVP100' | AX93: 7 | AY93: TVS0707 | AZ93: La valeur renseignée doit être cohérente avec l'objet métier (LC.0030 - TA 0990 Z8COTROM) | BA93: The value filled must be consistent with the business object (LC.0030 - TA 0990 Z8COTROM) | BB93: 7 | BC93: TCG0005
A94: A1 | B94: 76 | C94: 16 - Identification Tiers | D94: 16 - Third party identification | E94: A1 86 | F94: Indicateur de présence du tiers principal dans TIGRE | G94: Indicator of principal counterparty presence in TIGRE | H94: Indicateur de présence du tiers principal dans TIGRE | I94: Indicator of principal counterparty presence in TIGRE | J94: NON | M94: Ne pas alimenter Il n'y aura pas de colonne créé pour ce champ | P94: ND | Q94: ND | R94: tpTiersDansTIGRE | S94: Obligatoire sous conditions | T94: Mandatory under conditions | U94: LC.0262 | V94: TA KVIIDTCA | W94: NA | X94: NA | Y94: ALPHA | Z94: NA | AA94: NA | AB94: 1 | AC94: NA | AD94: 45 | AE94: NA | AF94: NA | AG94: ESG PILIER 3, LIQUIDITE | AH94: ND | AI94: N | AJ94: NA | AK94: NA | AL94: NA | AN94: La donnée est obligatoire, si l'Indicateur tiers connu [A1 523] = 'Y' | AO94: The data is mandatory, if Known Third Party indicator [A1 523] = 'Y' | AP94: 7 | AQ94: TPSxxxx | AR94: Si elle est renseignée, la valeur doit être connue du Langage Commun associé | AS94: If specified, the value must be known to the associated Common Language | AT94: 7 | AU94: TIG0001
A95: A1 | B95: 77 | C95: 16 - Identification Tiers | D95: 16 - Third party identification | E95: A1 86.1 | F95: Identifiant IDTCA du tiers principal | G95: IDTCA identifier of the principal third party | H95: Identifiant IDTCA du tiers principal | I95: IDTCA identifier of the principal third party | J95: NON | M95: Ne pas alimenter Il n'y aura pas de colonne créé pour ce champ | P95: ND | Q95: ND | R95: IDTCATiers | S95: Obligatoire sous conditions | T95: Mandatory under conditions | U95: NA | V95: NA | W95: Renseigner l'IDTCA (Identifiant central du Tiers) s'il est connu. Sinon, laisser à vide. | X95: Must be completed with IDTCA (third party central identifier) if known. If not, empty field. | Y95: ALPHA | Z95: NA | AA95: NA | AB95: 20 | AC95: NA | AD95: 45 | AE95: NA | AF95: NA | AG95: ESG PILIER 3, LIQUIDITE | AH95: ND | AI95: N | AJ95: NA | AK95: NA | AL95: NA | AN95: La donnée est obligatoire si Indicateur de présence du tiers principal dans TIGRE [A1 86] = 'Y' ET si (la Référence d'Identification nationale du Tiers principal CORPORATE [A1 86.2] et l'Identifiant national du Tiers principal CORPORATE [A1 86.3]) ne sont pas renseignés | AO95: The data is mandatory if Indicator of principal counterparty presence in TIGRE [A1 86] = 'Y' AND if (the Reference of national ID of the principal third party CORPORATE [A1 86.2] and the National ID of the principal third party CORPORATE [A1 86.3]) are not filled | AP95: 7 | AQ95: TBD | BD95: Le tiers doit exister (présence du tiers dans TIGRE) | BE95: The third-party must exist (presence of the third-party in TIGRE) | BF95: 7 | BG95: TIG0002
A96: A1 | B96: 78 | C96: 16 - Identification Tiers | D96: 16 - Third party identification | E96: A1 86.2 | F96: Référence d'Identification nationale du Tiers principal CORPORATE | G96: Reference of national ID of the principal third party CORPORATE | H96: Référence d'Identification nationale du Tiers principal CORPORATE | I96: Reference of national ID of the principal third party CORPORATE | J96: OUI | K96: Fichier envoyé par MERCA et partagé par le métier | L96: A1_DEGRADE_GMBH Nouvelle donnée à créér Nom de la donnée: | M96: Champ à renseigner inclus dans le fichier MERCA Une nouveau champ est à créer dans la table d'integration de ce fichier. Nom du champ dans le fichier partagé par MERCA: REFERENCEOFNATIONALID | O96: Version 1 | P96: ND | Q96: ND | R96: cdRefIdNatTiers | S96: Obligatoire sous conditions | T96: Mandatory under conditions | U96: LC.0013 | V96: TA KVIDENT | W96: Cette donnée permet de connaître le type d'identifiant national renseigné. | X96: This data makes it possible to know the type of national identifier provided. | Y96: ALPHA | Z96: NA | AA96: NA | AB96: 2 | AC96: NA | AD96: 45 | AE96: NA | AF96: NA | AG96: ESG PILIER 3, LIQUIDITE | AH96: ND | AI96: N | AJ96: NA | AK96: NA | AL96: NA | AN96: La donnée est obligatoire si Indicateur de présence du tiers principal dans TIGRE [A1 86] = 'Y' ET si Identifiant IDTCA du tiers principal [A1 86.1] n'est pas renseigné | AO96: The data is mandatory if Indicator of principal counterparty presence in TIGRE [A1 86] = 'Y' AND if IDTCA identifier of the principal third party [A1 86.1] is not filled | AP96: 7 | AQ96: TBD | AR96: Si elle est renseignée, la valeur doit être connue du Langage Commun associé | AS96: If specified, the value must be known to the associated Common Language | AT96: 7 | AU96: TIG0001
A97: A1 | B97: 79 | C97: 16 - Identification Tiers | D97: 16 - Third party identification | E97: A1 86.3 | F97: Identifiant national du Tiers principal CORPORATE | G97: National ID of the third party CORPORATE | H97: Identification nationale du Tiers issue des référentiels nationaux désignés dans la Référence d'Identification nationale du Tiers principal CORPORATE [A1 86.2] | I97: National ID of the third party from the national standards designated in Reference of national ID of the principal third party CORPORATE [A1 86.2] | J97: OUI | K97: Fichier envoyé par MERCA et partagé par le métier | L97: A1_DEGRADE_GMBH Nouvelle donnée à créér Nom de la donnée: | M97: Champ à renseigner inclus dans le fichier MERCA Une nouveau champ est à créer dans la table d'integration de ce fichier. Nom du champ dans le fichier partagé par MERCA: NATIONALID | O97: Version 1 | P97: ND | Q97: ND | R97: idNatTiers | S97: Obligatoire sous conditions | T97: Mandatory under conditions | U97: NA | V97: NA | W97: Cette référence doit être préfixée par le code pays (ISO 2 alpha) de résidence du Tiers si la référence d'identification nationale choisie = "6 " ou "7" ou "99" | X97: This reference must be prefixed by the country code (ISO 2 alpha) of the counterparty residence, if the chosen National ID reference = "6" or "7" or "99" | Y97: ALPHA | Z97: NA | AA97: NA | AB97: 20 | AC97: NA | AD97: 45 | AE97: NA | AF97: NA | AG97: ESG PILIER 3, LIQUIDITE | AH97: ND | AI97: N | AJ97: NA | AK97: NA | AL97: NA | AN97: La donnée est obligatoire si Indicateur de présence du tiers principal dans TIGRE [A1 86] = 'Y' ET si Identifiant IDTCA du tiers principal [A1 86.1] n'est pas renseigné | AO97: The data is mandatory if Indicator of counterparty presence in TIGRE [A1 86] = 'Y' AND if IDTCA identifier of the third party [A1 86.1] is not filled | AP97: 7 | AQ97: TBD | BD97: Le couple 'Référence d'Identification nationale du Tiers CORPORATE' [A1 86.2] et 'Identifiant national du Tiers CORPORATE' [A1 86.3] doit exister (présence du tiers dans TIGRE) | BE97: The couple 'Reference of national ID of the third party CORPORATE' [A1 86.2] and 'National ID of the third party CORPORATE' [A1 86.3] must exist (presence of the third-party in TIGRE) | BF97: 7 | BG97: TIG0003
A98: A1 | B98: 80 | C98: 16 - Identification Tiers | D98: 16 - Third party identification | E98: A1 86.4 | F98: Identifiant technique d'échange du tiers principal | G98: Technical exchange id. of the principal third party | H98: Identifiant technique d'échange du tiers principal | I98: Technical exchange id. of the principal third party | J98: NON | M98: Ne pas alimenter Il n'y aura pas de colonne créé pour ce champ | P98: ND | Q98: ND | R98: idTechEchTiers | S98: Obligatoire sous conditions | T98: Mandatory under conditions | U98: NA | V98: NA | W98: Il s'agit de l'identifiant technique unique du flux C2/C3. | X98: This is the unique technical identifier from C2 / C3 flow | Y98: ALPHA | Z98: NA | AA98: NA | AB98: 20 | AC98: NA | AD98: 45 | AE98: NA | AF98: NA | AG98: ESG PILIER 3, LIQUIDITE | AH98: ND | AI98: N | AJ98: NA | AK98: NA | AL98: NA | AN98: La donnée est obligatoire si Indicateur de présence du tiers principal dans TIGRE [A1 86] = 'N' | AO98: The data is mandatory if Indicator of principal counterparty presence in TIGRE [A1 86] = 'N' | AP98: 6 | AQ98: TBD | BD98: Le tiers existe (présence du tiers dans un C2 ou C3) | BE98: The third-party exists (presence of the third-party in C2 or C3) | BF98: 7 | BG98: TI0060
A99: A1 | B99: 81 | C99: 16 - Identification Tiers | D99: 16 - Third party identification | E99: A1 86.5 | F99: Identifiant local du tiers principal | G99: Local ID of the principal third party | H99: Identifiant local du tiers principal | I99: Local ID of the third party principal | J99: NON | M99: Ne pas alimenter Il n'y aura pas de colonne créé pour ce champ | P99: ND | Q99: ND | R99: idLocTiers | S99: Facultatif | T99: Optional | U99: NA | V99: NA | W99: Pour information. Sera potentiellement utile pour des déclaratifs avec le régulateur local. | X99: For information. Will be potentially useful for declarations with the local regulator. | Y99: ALPHA | Z99: NA | AA99: NA | AB99: 20 | AC99: NA | AD99: 45 | AE99: NA | AF99: NA | AG99: ESG PILIER 3, LIQUIDITE | AH99: ND | AI99: N | AJ99: NA | AK99: NA | AL99: NA
A100: A1 | B100: 82 | C100: 03 - Caractéristiques Générales | D100: 03 - General characteristics | E100: A1 500 | F100: Plan Produit Liquidité | G100: Liquidity product code | H100: Code produit exploité pour la construction du bilan de Liquidité | I100: Product code used for the construction of the liquidity balancesheet | J100: Champ en attente de clarification | K100: Champ en attente de clarification | L100: Champ en attente de clarification | M100: Champ en attente de clarification | P100: ND | Q100: ND | R100: TBD | S100: Obligatoire | T100: Mandatory | U100: LC.0550 | V100: RB Z8COPRLQ | W100: NA | X100: NA | Y100: ALPHA | Z100: NA | AA100: NA | AB100: 12 | AC100: NA | AD100: 45 | AE100: NA | AF100: NA | AG100: LIQUIDITE | AH100: ND | AI100: N | AJ100: NA | AK100: NA | AL100: NA | AN100: La donnée est obligatoire | AO100: The data is mandatory | AP100: 7 | AQ100: TPG0001 | AR100: Si elle est renseignée, la valeur doit être connue du Langage Commun associé | AS100: If specified, the value must be known to the associated Common Language | AT100: 7 | AU100: TIG0001
...

Sheet Ctrl cohérence-consistency ctr 
B2: Contrôles de cohérence | L2: Consistency controls
B4: Principe : Ces contrôles consistent à vérifier que la valeur portée par une donnée pivot est cohérente avec des données associées. Un contrôle de cohérence peut porter sur : · Une ou plusieurs données d’un même objet de collecte · Plusieurs données de plusieurs objets de collecte | L4: Principle: These controls are to ensure that the value of a pivot data is consistent with associated data. A consistency check may cover: ・ One or more data from the same data collection object ・ Several data from several data collection objects
B6: Périmètre d'application : - CRR Corporate - CRR Retail Agrégé - CRR Adapté | L6: Scope of application: - CRR Corporate - CRR Aggregated Retail - Adapted CRR
B8: Fonctionnement : - Contrôles exécutés en étape E4.4 des traitements ZP (après mise au modèle) - Contrôles paramétrés en score 6TA (non bloquant) - Les combinaisons de valeurs conformes sont précisées ci-dessous pour chaque contrôle sauf contrôle TC0C03 pour lequel sont précisées les combinaisons en anomalie. En dehors des combinaisons conformes, la Zone de Partage recensera une anomalie. | L8: Functions: - Checks performed in step E4.4 of ZP treatments (after the model has been set) - Controls configured in scoring 6TA (non-blocking) - The combinations of conforming values are specified below for each control except control TC0C03 for which the combinations in anomaly are specified. Apart from the compliant combinations, the Sharing Zone will identify an anomaly.
B10: Légende : | L10: Legend:
B11: * : Quelle que soit la valeur | L11: * Whatever the value
B12: Donnée pivot | L12: Pivot data
B13: Donnée complémentaire | L13: Additional data
B19: Contrôle TC0C11 : Cohérence NATO/Domaine CRR | L19: Control TC0C11 : NATO/CRR domain consistency
B20: Description du contrôle | D20: Périmètre | L20: Description of control | N20: Scope
B21: Ce contrôle consiste à vérifier l’utilisation de la NATO avec les domaines du CRR pour chacun des flux CRR transmis | D21: Grande Clientèle, Clientèle de détail et Alimentation adaptée | L21: This control consists in checking the use of the NATO with the CRR domains for each of the CRR flows transmitted | N21: Corporate customers, Retail customers and Adapted food
B24: A1 | L24: A1
C26: Nature d'Opération (A1 3.2, A1 6.5) | D26: Objet de collecte | M26: NATure of funds in use transaction (A1 3.2, A1 6.5) | N26: Business object
B27: A1 3.2 | C27: NA011, NA012, NA021, NA022, NA311, NA312, NA321, NA322, NA323, NA330, NA341, NA342, NA343, NA344, NA350, NA361, NA362, NA363, NA364, NA365, NA366, NA367, NA368, NA369, NA370, NA371, NAT41, NAT42, NAT43, NAT44, NAT06, NAT07, NA101, NA102 | D27: A1 | L27: A1 3.2 | M27: NA011, NA012, NA021, NA022, NA311, NA312, NA321, NA322, NA323, NA330, NA341, NA342, NA343, NA344, NA350, NA361, NA362, NA363, NA364, NA365, NA366, NA367, NA368, NA369, NA370, NA371, NAT41, NAT42, NAT43, NAT44, NAT06, NAT07, NA101, NA102 | N27: A1
B28: A1 6.5 | C28: NAT81, NAT82, NAT83, NAT84, NAT85 | D28: A1 | L28: A1 6.5 | M28: NAT81, NAT82, NAT83, NAT84, NAT85 | N28: A1
B33: Contrôle TC0C16 : Cohérence Crédit-bail | L33: Control TC0C16 : Credit-lease consistency
B34: Description du contrôle | D34: Périmètre | L34: Description of control | N34: Scope
B35: Le contrôle consiste à s’assurer que la saisie de certains champs a bien été effectuée pour les expositions du portefeuille CREDIT BAIL | D35: Grande Clientèle, Clientèle de détail et Standard en Alimentation adaptée | L35: The control consists in ensuring that certain fields have been entered for exposures of the CREDIT BAIL portfolio | N35: Corporate customers, Retail Customers and Standard in Adapted Feeding
B37: A1 | L37: A1
B39: Achat en fin de contrat du bien loué (A1 5.4) | C39: Usage du bien immobilier apporté en garantie (A1 5.1) | D39: Valeur estimée en fin de période du bien loué (A1 5.5) | E39: Devise de la valeur estimée en fin de période du bien loué (A1 3.3) | F39: Valeur hypothécaire du bien immobilier loué à la date d'évaluation (A1 5.3) | G39: Devise de la valeur hypothécaire du bien immobilier loué à la date d'évaluation (A1 3.3) | H39: Valeur de marché du bien immobilier loué à la date d'évaluation (A1 5.2) | I39: Devise de la valeur de marché du bien immobilier loué à la date d'évaluation (A1 3.3) | L39: Purchase at the end of the lease of the leased property (A1 5.4) | M39: Use of real estate (A1 5.1) | N39: Estimated value at the end of the period of the leased property (A1 5.5) | O39: Currency of the estimated value at the end of the period of the leased property (A1 3.3) | P39: Mortgage value of leased real estate at valuation date (A1 5.3) | Q39: Currency of the mortgage value of the leased property at the valuation date (A1 3.3) | R39: Market value|fair value of leased real estate at the latest valuation date (A1 5.2) | S39: Currency of the market value|fair value of the leased property on the valuation date (A1 3.3)
B40: 1 | C40: 1 | D40: ≠ 0 | E40: (Non vide) | F40: ≠ 0 | G40: (Non vide) | H40: ≠ 0 | I40: (Non vide) | L40: 1 | M40: 1 | N40: ≠ 0 | O40: (Non vide) | P40: ≠ 0 | Q40: (Non vide) | R40: ≠ 0 | S40: (Non vide)
B41: 2 | C41: 1 | D41: * | E41: * | F41: ≠ 0 | G41: (Non vide) | H41: ≠ 0 | I41: (Non vide) | L41: 2 | M41: 1 | N41: * | O41: * | P41: ≠ 0 | Q41: (Non vide) | R41: ≠ 0 | S41: (Non vide)
B42: 1 | C42: 2 | D42: ≠ 0 | E42: (Non vide) | F42: * | G42: * | H42: ≠ 0 | I42: (Non vide) | L42: 1 | M42: 2 | N42: ≠ 0 | O42: (Non vide) | P42: * | Q42: * | R42: ≠ 0 | S42: (Non vide)
B43: 2 | C43: 2 | D43: * | E43: * | F43: * | G43: * | H43: ≠ 0 | I43: (Non vide) | L43: 2 | M43: 2 | N43: * | O43: * | P43: * | Q43: * | R43: ≠ 0 | S43: (Non vide)
B44: 1 | C44: ≠ 1 et ≠ 2 | D44: ≠ 0 | E44: (Non vide) | F44: * | G44: * | H44: * | I44: * | L44: 1 | M44: ≠ 1 et ≠ 2 | N44: ≠ 0 | O44: (Non vide) | P44: * | Q44: * | R44: * | S44: *
B50: Contrôle TC0C26 : Cohérence NATO/Engagement douteux en STD | L50: Control TC0C26 : NATO/doubtful Funds in use consistency in STD
B51: Description du contrôle | D51: Périmètre | L51: Description of control | N51: Scope
B52: Le contrôle consiste à vérifier que la NATure d’Opération dans laquelle l’encours a été classé est cohérente avec le caractère douteux/non douteux de l’encours traité en méthode Standard STD | D52: Grande Clientèle, Clientèle de détail et Alimentation adaptée, en méthode Standard | L52: The control consists in checking that the NATure of the operation in which the outstanding has been classified is consistent with the doubtful/undoubted nature of the outstanding treated in the STD standard method | N52: Corporate customers, Retail customers and appropriate food, using the Standard method
B54: A1 | L54: A1
B56: NATO de l'exposition (A1 3.2) | C56: Indicateur 'Engagement Douteux' (A1 4.14) | L56: NATO of the exhibition (A1 3.2) | M56: 'Doubtful Funds in use' indicator (A1 4.14)
B57: NA011, NA021, NA101 | C57: N | L57: NA011, NA021, NA101 | M57: N
B58: NA012, NA022, NA102 | C58: Y | L58: NA012, NA022, NA102 | M58: Y
